{
  "c80eb0293658685903bd1fd24f492c08" : {
    "statistic" : {
      "failed" : 0,
      "broken" : 0,
      "skipped" : 0,
      "passed" : 1,
      "unknown" : 0,
      "total" : 1
    },
    "items" : [ {
      "uid" : "2ffab15f0154a095",
      "reportUrl" : "https://MohabMohie.github.io/SHAFT_ENGINE/allure/Linux/Web/1238//#testresult/2ffab15f0154a095",
      "status" : "passed",
      "time" : {
        "start" : 1647483075609,
        "stop" : 1647483077519,
        "duration" : 1910
      }
    } ]
  },
  "5d486709805afb09377652af1cb44b43" : {
    "statistic" : {
      "failed" : 0,
      "broken" : 0,
      "skipped" : 1,
      "passed" : 0,
      "unknown" : 0,
      "total" : 1
    },
    "items" : [ {
      "uid" : "e86968fc39951222",
      "reportUrl" : "https://MohabMohie.github.io/SHAFT_ENGINE/allure/Linux/Web/1238//#testresult/e86968fc39951222",
      "status" : "skipped",
      "statusDetails" : "Method testPackage01.TestJSPromptBox.acceptPromptAlertWithTextMessage() on instance testPackage01.TestJSPromptBox@fd9ebde depends on not successfully finished methods \n[testPackage01.TestJSPromptBox.assertOnConfirmPromptAlertWithoutTypingTextMessageResultText() on instance testPackage01.TestJSPromptBox@fd9ebde]",
      "time" : {
        "start" : 1647483175042,
        "stop" : 1647483175051,
        "duration" : 9
      }
    } ]
  },
  "7b0f8854a7aed9a150b2fc57963781fa" : {
    "statistic" : {
      "failed" : 0,
      "broken" : 0,
      "skipped" : 0,
      "passed" : 1,
      "unknown" : 0,
      "total" : 1
    },
    "items" : [ {
      "uid" : "2e11dbdda5442646",
      "reportUrl" : "https://MohabMohie.github.io/SHAFT_ENGINE/allure/Linux/Web/1238//#testresult/2e11dbdda5442646",
      "status" : "passed",
      "time" : {
        "start" : 1647483452432,
        "stop" : 1647483452433,
        "duration" : 1
      }
    } ]
  },
  "42db9a0b95e9103a321dfe36eb368c1b" : {
    "statistic" : {
      "failed" : 0,
      "broken" : 0,
      "skipped" : 0,
      "passed" : 1,
      "unknown" : 0,
      "total" : 1
    },
    "items" : [ {
      "uid" : "7b17743ae79f98c4",
      "reportUrl" : "https://MohabMohie.github.io/SHAFT_ENGINE/allure/Linux/Web/1238//#testresult/7b17743ae79f98c4",
      "status" : "passed",
      "time" : {
        "start" : 1647483055754,
        "stop" : 1647483058172,
        "duration" : 2418
      }
    } ]
  },
  "9557c3315a180b8221de8066c242409a" : {
    "statistic" : {
      "failed" : 0,
      "broken" : 0,
      "skipped" : 0,
      "passed" : 1,
      "unknown" : 0,
      "total" : 1
    },
    "items" : [ {
      "uid" : "90722068773dd113",
      "reportUrl" : "https://MohabMohie.github.io/SHAFT_ENGINE/allure/Linux/Web/1238//#testresult/90722068773dd113",
      "status" : "passed",
      "time" : {
        "start" : 1647483566291,
        "stop" : 1647483566552,
        "duration" : 261
      }
    } ]
  },
  "2314bd23a656a36ab83c22386848f0d4" : {
    "statistic" : {
      "failed" : 0,
      "broken" : 0,
      "skipped" : 0,
      "passed" : 1,
      "unknown" : 0,
      "total" : 1
    },
    "items" : [ {
      "uid" : "b4e768463b3dd156",
      "reportUrl" : "https://MohabMohie.github.io/SHAFT_ENGINE/allure/Linux/Web/1238//#testresult/b4e768463b3dd156",
      "status" : "passed",
      "time" : {
        "start" : 1647483142598,
        "stop" : 1647483143059,
        "duration" : 461
      }
    } ]
  },
  "3f6e5843fc6c685f5ebc75fde75ac218" : {
    "statistic" : {
      "failed" : 0,
      "broken" : 0,
      "skipped" : 0,
      "passed" : 1,
      "unknown" : 0,
      "total" : 1
    },
    "items" : [ {
      "uid" : "81cd586446fd1dad",
      "reportUrl" : "https://MohabMohie.github.io/SHAFT_ENGINE/allure/Linux/Web/1238//#testresult/81cd586446fd1dad",
      "status" : "passed",
      "time" : {
        "start" : 1647483600841,
        "stop" : 1647483602316,
        "duration" : 1475
      }
    } ]
  },
  "973cdadfe7b0529022bcd219aff55968" : {
    "statistic" : {
      "failed" : 0,
      "broken" : 0,
      "skipped" : 0,
      "passed" : 1,
      "unknown" : 0,
      "total" : 1
    },
    "items" : [ {
      "uid" : "7c7b429aa5340cbe",
      "reportUrl" : "https://MohabMohie.github.io/SHAFT_ENGINE/allure/Linux/Web/1238//#testresult/7c7b429aa5340cbe",
      "status" : "passed",
      "time" : {
        "start" : 1647483486008,
        "stop" : 1647483486009,
        "duration" : 1
      }
    } ]
  },
  "4a29903560362dbd17b5dd05d236bc8b" : {
    "statistic" : {
      "failed" : 0,
      "broken" : 0,
      "skipped" : 0,
      "passed" : 1,
      "unknown" : 0,
      "total" : 1
    },
    "items" : [ {
      "uid" : "9a98aa1e086e1947",
      "reportUrl" : "https://MohabMohie.github.io/SHAFT_ENGINE/allure/Linux/Web/1238//#testresult/9a98aa1e086e1947",
      "status" : "passed",
      "time" : {
        "start" : 1647483109331,
        "stop" : 1647483110041,
        "duration" : 710
      }
    } ]
  },
  "7ce456f557879027bc598b94d15d7182" : {
    "statistic" : {
      "failed" : 0,
      "broken" : 0,
      "skipped" : 0,
      "passed" : 1,
      "unknown" : 0,
      "total" : 1
    },
    "items" : [ {
      "uid" : "4c3d294639d37aae",
      "reportUrl" : "https://MohabMohie.github.io/SHAFT_ENGINE/allure/Linux/Web/1238//#testresult/4c3d294639d37aae",
      "status" : "passed",
      "time" : {
        "start" : 1647483584015,
        "stop" : 1647483584016,
        "duration" : 1
      }
    } ]
  },
  "7e80de2d453155ab307b931149cee737" : {
    "statistic" : {
      "failed" : 0,
      "broken" : 0,
      "skipped" : 0,
      "passed" : 1,
      "unknown" : 0,
      "total" : 1
    },
    "items" : [ {
      "uid" : "8c1026e6424a2e10",
      "reportUrl" : "https://MohabMohie.github.io/SHAFT_ENGINE/allure/Linux/Web/1238//#testresult/8c1026e6424a2e10",
      "status" : "passed",
      "time" : {
        "start" : 1647483454740,
        "stop" : 1647483485901,
        "duration" : 31161
      }
    } ]
  },
  "d22b5e6c4280f54bf49831434b9e5018" : {
    "statistic" : {
      "failed" : 0,
      "broken" : 0,
      "skipped" : 0,
      "passed" : 1,
      "unknown" : 0,
      "total" : 1
    },
    "items" : [ {
      "uid" : "b33b01680d120ba5",
      "reportUrl" : "https://MohabMohie.github.io/SHAFT_ENGINE/allure/Linux/Web/1238//#testresult/b33b01680d120ba5",
      "status" : "passed",
      "time" : {
        "start" : 1647483692284,
        "stop" : 1647483692792,
        "duration" : 508
      }
    } ]
  },
  "d9c1f161fa2285acc4faca119ad8939" : {
    "statistic" : {
      "failed" : 0,
      "broken" : 0,
      "skipped" : 0,
      "passed" : 1,
      "unknown" : 0,
      "total" : 1
    },
    "items" : [ {
      "uid" : "fcf46574694e299a",
      "reportUrl" : "https://MohabMohie.github.io/SHAFT_ENGINE/allure/Linux/Web/1238//#testresult/fcf46574694e299a",
      "status" : "passed",
      "time" : {
        "start" : 1647483055386,
        "stop" : 1647483055389,
        "duration" : 3
      }
    } ]
  },
  "d766de23786c53f441d161eddaf1215a" : {
    "statistic" : {
      "failed" : 0,
      "broken" : 0,
      "skipped" : 0,
      "passed" : 1,
      "unknown" : 0,
      "total" : 1
    },
    "items" : [ {
      "uid" : "5f70263cf8421e12",
      "reportUrl" : "https://MohabMohie.github.io/SHAFT_ENGINE/allure/Linux/Web/1238//#testresult/5f70263cf8421e12",
      "status" : "passed",
      "time" : {
        "start" : 1647483452414,
        "stop" : 1647483452416,
        "duration" : 2
      }
    } ]
  },
  "64a8852b286bab5ef838177e652e731e" : {
    "statistic" : {
      "failed" : 0,
      "broken" : 0,
      "skipped" : 0,
      "passed" : 1,
      "unknown" : 0,
      "total" : 1
    },
    "items" : [ {
      "uid" : "fe6b7b42396c467b",
      "reportUrl" : "https://MohabMohie.github.io/SHAFT_ENGINE/allure/Linux/Web/1238//#testresult/fe6b7b42396c467b",
      "status" : "passed",
      "time" : {
        "start" : 1647483693303,
        "stop" : 1647483693304,
        "duration" : 1
      }
    } ]
  },
  "bb31d8b47e1a96c6836334320447d229" : {
    "statistic" : {
      "failed" : 0,
      "broken" : 0,
      "skipped" : 0,
      "passed" : 1,
      "unknown" : 0,
      "total" : 1
    },
    "items" : [ {
      "uid" : "e4f87ba04f24c58c",
      "reportUrl" : "https://MohabMohie.github.io/SHAFT_ENGINE/allure/Linux/Web/1238//#testresult/e4f87ba04f24c58c",
      "status" : "passed",
      "time" : {
        "start" : 1647483499803,
        "stop" : 1647483500348,
        "duration" : 545
      }
    } ]
  },
  "eb85811949f431b7a228b6de557ce34e" : {
    "statistic" : {
      "failed" : 0,
      "broken" : 0,
      "skipped" : 0,
      "passed" : 1,
      "unknown" : 0,
      "total" : 1
    },
    "items" : [ {
      "uid" : "de2858eadb0d4e10",
      "reportUrl" : "https://MohabMohie.github.io/SHAFT_ENGINE/allure/Linux/Web/1238//#testresult/de2858eadb0d4e10",
      "status" : "passed",
      "time" : {
        "start" : 1647483452497,
        "stop" : 1647483452498,
        "duration" : 1
      }
    } ]
  },
  "e025b82a7d1b9f5f8cfaebf774709daa" : {
    "statistic" : {
      "failed" : 0,
      "broken" : 0,
      "skipped" : 0,
      "passed" : 1,
      "unknown" : 0,
      "total" : 1
    },
    "items" : [ {
      "uid" : "630dc8ef6fc88489",
      "reportUrl" : "https://MohabMohie.github.io/SHAFT_ENGINE/allure/Linux/Web/1238//#testresult/630dc8ef6fc88489",
      "status" : "passed",
      "time" : {
        "start" : 1647483070452,
        "stop" : 1647483075309,
        "duration" : 4857
      }
    } ]
  },
  "89010c35d43262e5174c0abc3b833ff2" : {
    "statistic" : {
      "failed" : 1,
      "broken" : 0,
      "skipped" : 0,
      "passed" : 0,
      "unknown" : 0,
      "total" : 1
    },
    "items" : [ {
      "uid" : "93737f8660761f11",
      "reportUrl" : "https://MohabMohie.github.io/SHAFT_ENGINE/allure/Linux/Web/1238//#testresult/93737f8660761f11",
      "status" : "failed",
      "statusDetails" : "Element Action [WaitForAlertToBePresent] failed.",
      "time" : {
        "start" : 1647483144356,
        "stop" : 1647483175022,
        "duration" : 30666
      }
    } ]
  },
  "f5eb3e0657331ec851f236cbdec9dbc3" : {
    "statistic" : {
      "failed" : 0,
      "broken" : 0,
      "skipped" : 0,
      "passed" : 1,
      "unknown" : 0,
      "total" : 1
    },
    "items" : [ {
      "uid" : "f0e191f737ae976d",
      "reportUrl" : "https://MohabMohie.github.io/SHAFT_ENGINE/allure/Linux/Web/1238//#testresult/f0e191f737ae976d",
      "status" : "passed",
      "time" : {
        "start" : 1647483616429,
        "stop" : 1647483617712,
        "duration" : 1283
      }
    } ]
  },
  "18ebb827f5e596bdd48750256bb3ed08" : {
    "statistic" : {
      "failed" : 0,
      "broken" : 0,
      "skipped" : 0,
      "passed" : 1,
      "unknown" : 0,
      "total" : 1
    },
    "items" : [ {
      "uid" : "ec28f0e44410d3ef",
      "reportUrl" : "https://MohabMohie.github.io/SHAFT_ENGINE/allure/Linux/Web/1238//#testresult/ec28f0e44410d3ef",
      "status" : "passed",
      "time" : {
        "start" : 1647483578393,
        "stop" : 1647483579615,
        "duration" : 1222
      }
    } ]
  },
  "b7fc3abf80e9bbdd5097280c59543cd9" : {
    "statistic" : {
      "failed" : 0,
      "broken" : 0,
      "skipped" : 0,
      "passed" : 1,
      "unknown" : 0,
      "total" : 1
    },
    "items" : [ {
      "uid" : "76a18dc484b8ab60",
      "reportUrl" : "https://MohabMohie.github.io/SHAFT_ENGINE/allure/Linux/Web/1238//#testresult/76a18dc484b8ab60",
      "status" : "passed",
      "time" : {
        "start" : 1647483692273,
        "stop" : 1647483692274,
        "duration" : 1
      }
    } ]
  },
  "e13eda38936ccb8186efbcb0f47508c8" : {
    "statistic" : {
      "failed" : 0,
      "broken" : 0,
      "skipped" : 0,
      "passed" : 1,
      "unknown" : 0,
      "total" : 1
    },
    "items" : [ {
      "uid" : "59c4082314cb9e69",
      "reportUrl" : "https://MohabMohie.github.io/SHAFT_ENGINE/allure/Linux/Web/1238//#testresult/59c4082314cb9e69",
      "status" : "passed",
      "time" : {
        "start" : 1647483419278,
        "stop" : 1647483419971,
        "duration" : 693
      }
    } ]
  },
  "17b5b8806ac7eb710c4c7956140eaecf" : {
    "statistic" : {
      "failed" : 0,
      "broken" : 0,
      "skipped" : 0,
      "passed" : 1,
      "unknown" : 0,
      "total" : 1
    },
    "items" : [ {
      "uid" : "d6f70f027674f75e",
      "reportUrl" : "https://MohabMohie.github.io/SHAFT_ENGINE/allure/Linux/Web/1238//#testresult/d6f70f027674f75e",
      "status" : "passed",
      "time" : {
        "start" : 1647483697320,
        "stop" : 1647483698088,
        "duration" : 768
      }
    } ]
  },
  "19999555bce5de3735ec04b0e0646e14" : {
    "statistic" : {
      "failed" : 0,
      "broken" : 0,
      "skipped" : 1,
      "passed" : 0,
      "unknown" : 0,
      "total" : 1
    },
    "items" : [ {
      "uid" : "d0cef8894a3002b3",
      "reportUrl" : "https://MohabMohie.github.io/SHAFT_ENGINE/allure/Linux/Web/1238//#testresult/d0cef8894a3002b3",
      "status" : "skipped",
      "statusDetails" : "Method testPackage01.TestJSAlertBox.assertOnConfirmAlertResultText() on instance testPackage01.TestJSAlertBox@5300cac depends on not successfully finished methods \n[testPackage01.TestJSAlertBox.acceptAlert() on instance testPackage01.TestJSAlertBox@5300cac]",
      "time" : {
        "start" : 1647483530925,
        "stop" : 1647483530931,
        "duration" : 6
      }
    } ]
  },
  "fa8089fdd54895368300d31f35070cea" : {
    "statistic" : {
      "failed" : 0,
      "broken" : 0,
      "skipped" : 0,
      "passed" : 1,
      "unknown" : 0,
      "total" : 1
    },
    "items" : [ {
      "uid" : "dc1edd379fb063b7",
      "reportUrl" : "https://MohabMohie.github.io/SHAFT_ENGINE/allure/Linux/Web/1238//#testresult/dc1edd379fb063b7",
      "status" : "passed",
      "time" : {
        "start" : 1647483692795,
        "stop" : 1647483693298,
        "duration" : 503
      }
    } ]
  },
  "381ba714b0c66de2985d3ae81acb5e17" : {
    "statistic" : {
      "failed" : 0,
      "broken" : 0,
      "skipped" : 0,
      "passed" : 1,
      "unknown" : 0,
      "total" : 1
    },
    "items" : [ {
      "uid" : "e8eab098abea4ee5",
      "reportUrl" : "https://MohabMohie.github.io/SHAFT_ENGINE/allure/Linux/Web/1238//#testresult/e8eab098abea4ee5",
      "status" : "passed",
      "time" : {
        "start" : 1647483452438,
        "stop" : 1647483452439,
        "duration" : 1
      }
    } ]
  },
  "8a857219522d374b9811362ab4602182" : {
    "statistic" : {
      "failed" : 0,
      "broken" : 0,
      "skipped" : 0,
      "passed" : 1,
      "unknown" : 0,
      "total" : 1
    },
    "items" : [ {
      "uid" : "504f6f9dcc1df70a",
      "reportUrl" : "https://MohabMohie.github.io/SHAFT_ENGINE/allure/Linux/Web/1238//#testresult/504f6f9dcc1df70a",
      "status" : "passed",
      "time" : {
        "start" : 1647483622227,
        "stop" : 1647483623825,
        "duration" : 1598
      }
    } ]
  },
  "b1a09b6933c16fdc5feb53cd6bbf1690" : {
    "statistic" : {
      "failed" : 0,
      "broken" : 0,
      "skipped" : 0,
      "passed" : 1,
      "unknown" : 0,
      "total" : 1
    },
    "items" : [ {
      "uid" : "66033ebb932a98bb",
      "reportUrl" : "https://MohabMohie.github.io/SHAFT_ENGINE/allure/Linux/Web/1238//#testresult/66033ebb932a98bb",
      "status" : "passed",
      "time" : {
        "start" : 1647483625494,
        "stop" : 1647483627014,
        "duration" : 1520
      }
    } ]
  },
  "7c02c0395504a7a7869fd091b6dfff0b" : {
    "statistic" : {
      "failed" : 0,
      "broken" : 0,
      "skipped" : 0,
      "passed" : 1,
      "unknown" : 0,
      "total" : 1
    },
    "items" : [ {
      "uid" : "76f6ebffb7447d3b",
      "reportUrl" : "https://MohabMohie.github.io/SHAFT_ENGINE/allure/Linux/Web/1238//#testresult/76f6ebffb7447d3b",
      "status" : "passed",
      "time" : {
        "start" : 1647483052427,
        "stop" : 1647483053895,
        "duration" : 1468
      }
    } ]
  },
  "7546566432535191f8975bb3f3cb9a48" : {
    "statistic" : {
      "failed" : 0,
      "broken" : 0,
      "skipped" : 0,
      "passed" : 1,
      "unknown" : 0,
      "total" : 1
    },
    "items" : [ {
      "uid" : "3f3bf47c6573e760",
      "reportUrl" : "https://MohabMohie.github.io/SHAFT_ENGINE/allure/Linux/Web/1238//#testresult/3f3bf47c6573e760",
      "status" : "passed",
      "time" : {
        "start" : 1647483486012,
        "stop" : 1647483486013,
        "duration" : 1
      }
    } ]
  },
  "81dccf0fa5dda2c07b8a2e38642301d4" : {
    "statistic" : {
      "failed" : 0,
      "broken" : 0,
      "skipped" : 0,
      "passed" : 1,
      "unknown" : 0,
      "total" : 1
    },
    "items" : [ {
      "uid" : "421c16fc388e6a41",
      "reportUrl" : "https://MohabMohie.github.io/SHAFT_ENGINE/allure/Linux/Web/1238//#testresult/421c16fc388e6a41",
      "status" : "passed",
      "time" : {
        "start" : 1647483180274,
        "stop" : 1647483183219,
        "duration" : 2945
      }
    } ]
  },
  "24d179f984390efd4095c1ca70d9ae83" : {
    "statistic" : {
      "failed" : 0,
      "broken" : 0,
      "skipped" : 1,
      "passed" : 0,
      "unknown" : 0,
      "total" : 1
    },
    "items" : [ {
      "uid" : "8492e569620d66a2",
      "reportUrl" : "https://MohabMohie.github.io/SHAFT_ENGINE/allure/Linux/Web/1238//#testresult/8492e569620d66a2",
      "status" : "skipped",
      "statusDetails" : "Method testPackage01.TestJSConfirmBox.assertOnConfirmAlertResultText() on instance testPackage01.TestJSConfirmBox@1ac4ccad depends on not successfully finished methods \n[testPackage01.TestJSConfirmBox.acceptAlert() on instance testPackage01.TestJSConfirmBox@1ac4ccad]",
      "time" : {
        "start" : 1647483141426,
        "stop" : 1647483141440,
        "duration" : 14
      }
    } ]
  },
  "c5a92213d3cbe213658c780681a07039" : {
    "statistic" : {
      "failed" : 0,
      "broken" : 0,
      "skipped" : 0,
      "passed" : 1,
      "unknown" : 0,
      "total" : 1
    },
    "items" : [ {
      "uid" : "ed5eaa7d1457aec9",
      "reportUrl" : "https://MohabMohie.github.io/SHAFT_ENGINE/allure/Linux/Web/1238//#testresult/ed5eaa7d1457aec9",
      "status" : "passed",
      "time" : {
        "start" : 1647483581417,
        "stop" : 1647483581668,
        "duration" : 251
      }
    } ]
  },
  "5eb7f769276356accd4c25c7c882af5f" : {
    "statistic" : {
      "failed" : 0,
      "broken" : 0,
      "skipped" : 0,
      "passed" : 1,
      "unknown" : 0,
      "total" : 1
    },
    "items" : [ {
      "uid" : "50398e6506396837",
      "reportUrl" : "https://MohabMohie.github.io/SHAFT_ENGINE/allure/Linux/Web/1238//#testresult/50398e6506396837",
      "status" : "passed",
      "time" : {
        "start" : 1647483421027,
        "stop" : 1647483421809,
        "duration" : 782
      }
    } ]
  },
  "50b134c4ce45667640a8b328092e77c" : {
    "statistic" : {
      "failed" : 0,
      "broken" : 0,
      "skipped" : 0,
      "passed" : 1,
      "unknown" : 0,
      "total" : 1
    },
    "items" : [ {
      "uid" : "63779f4abc3632b2",
      "reportUrl" : "https://MohabMohie.github.io/SHAFT_ENGINE/allure/Linux/Web/1238//#testresult/63779f4abc3632b2",
      "status" : "passed",
      "time" : {
        "start" : 1647483695373,
        "stop" : 1647483697317,
        "duration" : 1944
      }
    } ]
  },
  "b27c77614b887aad9233c87f6d999b88" : {
    "statistic" : {
      "failed" : 0,
      "broken" : 0,
      "skipped" : 0,
      "passed" : 1,
      "unknown" : 0,
      "total" : 1
    },
    "items" : [ {
      "uid" : "77917c0c02536933",
      "reportUrl" : "https://MohabMohie.github.io/SHAFT_ENGINE/allure/Linux/Web/1238//#testresult/77917c0c02536933",
      "status" : "passed",
      "time" : {
        "start" : 1647483498949,
        "stop" : 1647483498973,
        "duration" : 24
      }
    } ]
  },
  "5514b76ba1dc4de2d7fa6ed8af87a94e" : {
    "statistic" : {
      "failed" : 0,
      "broken" : 0,
      "skipped" : 0,
      "passed" : 1,
      "unknown" : 0,
      "total" : 1
    },
    "items" : [ {
      "uid" : "4037c6a8f6ad9909",
      "reportUrl" : "https://MohabMohie.github.io/SHAFT_ENGINE/allure/Linux/Web/1238//#testresult/4037c6a8f6ad9909",
      "status" : "passed",
      "time" : {
        "start" : 1647483551960,
        "stop" : 1647483553190,
        "duration" : 1230
      }
    } ]
  },
  "259a17265cbc92933de3cafb98400a6e" : {
    "statistic" : {
      "failed" : 0,
      "broken" : 0,
      "skipped" : 0,
      "passed" : 1,
      "unknown" : 0,
      "total" : 1
    },
    "items" : [ {
      "uid" : "f36cef9b798991c3",
      "reportUrl" : "https://MohabMohie.github.io/SHAFT_ENGINE/allure/Linux/Web/1238//#testresult/f36cef9b798991c3",
      "status" : "passed",
      "time" : {
        "start" : 1647483424568,
        "stop" : 1647483450503,
        "duration" : 25935
      }
    } ]
  },
  "a55bf854e3301a0d60e84ba8c52fc696" : {
    "statistic" : {
      "failed" : 0,
      "broken" : 0,
      "skipped" : 0,
      "passed" : 1,
      "unknown" : 0,
      "total" : 1
    },
    "items" : [ {
      "uid" : "11bcb3e03b82a186",
      "reportUrl" : "https://MohabMohie.github.io/SHAFT_ENGINE/allure/Linux/Web/1238//#testresult/11bcb3e03b82a186",
      "status" : "passed",
      "time" : {
        "start" : 1647483490755,
        "stop" : 1647483490902,
        "duration" : 147
      }
    } ]
  },
  "29286b1e51fc227b9e82df438242ddee" : {
    "statistic" : {
      "failed" : 0,
      "broken" : 0,
      "skipped" : 0,
      "passed" : 1,
      "unknown" : 0,
      "total" : 1
    },
    "items" : [ {
      "uid" : "f9394aa3fdc83a84",
      "reportUrl" : "https://MohabMohie.github.io/SHAFT_ENGINE/allure/Linux/Web/1238//#testresult/f9394aa3fdc83a84",
      "status" : "passed",
      "time" : {
        "start" : 1647483110045,
        "stop" : 1647483110576,
        "duration" : 531
      }
    } ]
  },
  "8a4b6fbdb2fb99adceabd3a1832314da" : {
    "statistic" : {
      "failed" : 0,
      "broken" : 0,
      "skipped" : 0,
      "passed" : 1,
      "unknown" : 0,
      "total" : 1
    },
    "items" : [ {
      "uid" : "9ca015954a6305d4",
      "reportUrl" : "https://MohabMohie.github.io/SHAFT_ENGINE/allure/Linux/Web/1238//#testresult/9ca015954a6305d4",
      "status" : "passed",
      "time" : {
        "start" : 1647483498976,
        "stop" : 1647483499000,
        "duration" : 24
      }
    } ]
  },
  "8f7225c8a7be388cf13fecdcb10b58f2" : {
    "statistic" : {
      "failed" : 0,
      "broken" : 0,
      "skipped" : 0,
      "passed" : 1,
      "unknown" : 0,
      "total" : 1
    },
    "items" : [ {
      "uid" : "87a1010bb818b682",
      "reportUrl" : "https://MohabMohie.github.io/SHAFT_ENGINE/allure/Linux/Web/1238//#testresult/87a1010bb818b682",
      "status" : "passed",
      "time" : {
        "start" : 1647483452489,
        "stop" : 1647483452490,
        "duration" : 1
      }
    } ]
  },
  "449a6e184141d72ffe54fd6d696434a1" : {
    "statistic" : {
      "failed" : 0,
      "broken" : 0,
      "skipped" : 0,
      "passed" : 1,
      "unknown" : 0,
      "total" : 1
    },
    "items" : [ {
      "uid" : "a2c4f11b59422004",
      "reportUrl" : "https://MohabMohie.github.io/SHAFT_ENGINE/allure/Linux/Web/1238//#testresult/a2c4f11b59422004",
      "status" : "passed",
      "time" : {
        "start" : 1647483641899,
        "stop" : 1647483652587,
        "duration" : 10688
      }
    } ]
  },
  "4604ee6340e8cffa6c36a592668ef42b" : {
    "statistic" : {
      "failed" : 0,
      "broken" : 0,
      "skipped" : 0,
      "passed" : 1,
      "unknown" : 0,
      "total" : 1
    },
    "items" : [ {
      "uid" : "a276ffaa92333d02",
      "reportUrl" : "https://MohabMohie.github.io/SHAFT_ENGINE/allure/Linux/Web/1238//#testresult/a276ffaa92333d02",
      "status" : "passed",
      "time" : {
        "start" : 1647483693309,
        "stop" : 1647483693310,
        "duration" : 1
      }
    } ]
  },
  "8fbac502e2af59bbc9b8d6966d933655" : {
    "statistic" : {
      "failed" : 0,
      "broken" : 0,
      "skipped" : 0,
      "passed" : 1,
      "unknown" : 0,
      "total" : 1
    },
    "items" : [ {
      "uid" : "89f9b8e49adb2142",
      "reportUrl" : "https://MohabMohie.github.io/SHAFT_ENGINE/allure/Linux/Web/1238//#testresult/89f9b8e49adb2142",
      "status" : "passed",
      "time" : {
        "start" : 1647483576501,
        "stop" : 1647483576949,
        "duration" : 448
      }
    } ]
  },
  "544df7d2fdf8d5d984aa580e8196cbfd" : {
    "statistic" : {
      "failed" : 0,
      "broken" : 0,
      "skipped" : 0,
      "passed" : 1,
      "unknown" : 0,
      "total" : 1
    },
    "items" : [ {
      "uid" : "888e18ab52705f43",
      "reportUrl" : "https://MohabMohie.github.io/SHAFT_ENGINE/allure/Linux/Web/1238//#testresult/888e18ab52705f43",
      "status" : "passed",
      "time" : {
        "start" : 1647483178952,
        "stop" : 1647483178954,
        "duration" : 2
      }
    } ]
  },
  "fb7f8cd889260df26b212bf10e840f0b" : {
    "statistic" : {
      "failed" : 0,
      "broken" : 0,
      "skipped" : 0,
      "passed" : 1,
      "unknown" : 0,
      "total" : 1
    },
    "items" : [ {
      "uid" : "7a3110532548eb71",
      "reportUrl" : "https://MohabMohie.github.io/SHAFT_ENGINE/allure/Linux/Web/1238//#testresult/7a3110532548eb71",
      "status" : "passed",
      "time" : {
        "start" : 1647483108862,
        "stop" : 1647483109324,
        "duration" : 462
      }
    } ]
  },
  "41278362e80181fdd24eb6bcfdf1706d" : {
    "statistic" : {
      "failed" : 0,
      "broken" : 0,
      "skipped" : 0,
      "passed" : 1,
      "unknown" : 0,
      "total" : 1
    },
    "items" : [ {
      "uid" : "ea72e81a61cf4555",
      "reportUrl" : "https://MohabMohie.github.io/SHAFT_ENGINE/allure/Linux/Web/1238//#testresult/ea72e81a61cf4555",
      "status" : "passed",
      "time" : {
        "start" : 1647483374190,
        "stop" : 1647483384914,
        "duration" : 10724
      }
    } ]
  },
  "a668d1f7bbf0bd93bfbcd970b468fe16" : {
    "statistic" : {
      "failed" : 0,
      "broken" : 0,
      "skipped" : 0,
      "passed" : 1,
      "unknown" : 0,
      "total" : 1
    },
    "items" : [ {
      "uid" : "c719d555e12d5dcf",
      "reportUrl" : "https://MohabMohie.github.io/SHAFT_ENGINE/allure/Linux/Web/1238//#testresult/c719d555e12d5dcf",
      "status" : "passed",
      "time" : {
        "start" : 1647483583999,
        "stop" : 1647483584005,
        "duration" : 6
      }
    } ]
  },
  "ceff922ad3b0be43f47e1a6c9f6d6bb7" : {
    "statistic" : {
      "failed" : 0,
      "broken" : 0,
      "skipped" : 0,
      "passed" : 1,
      "unknown" : 0,
      "total" : 1
    },
    "items" : [ {
      "uid" : "4205b4d45d024455",
      "reportUrl" : "https://MohabMohie.github.io/SHAFT_ENGINE/allure/Linux/Web/1238//#testresult/4205b4d45d024455",
      "status" : "passed",
      "time" : {
        "start" : 1647483452396,
        "stop" : 1647483452398,
        "duration" : 2
      }
    } ]
  },
  "d29c9fb7cd6947e47db9b9fdd63ebebd" : {
    "statistic" : {
      "failed" : 0,
      "broken" : 0,
      "skipped" : 0,
      "passed" : 1,
      "unknown" : 0,
      "total" : 1
    },
    "items" : [ {
      "uid" : "e7de771691c1ce8f",
      "reportUrl" : "https://MohabMohie.github.io/SHAFT_ENGINE/allure/Linux/Web/1238//#testresult/e7de771691c1ce8f",
      "status" : "passed",
      "time" : {
        "start" : 1647483583133,
        "stop" : 1647483583366,
        "duration" : 233
      }
    } ]
  },
  "c88b9e1406b592eee831601849d31189" : {
    "statistic" : {
      "failed" : 0,
      "broken" : 0,
      "skipped" : 0,
      "passed" : 1,
      "unknown" : 0,
      "total" : 1
    },
    "items" : [ {
      "uid" : "d8375d00e5243732",
      "reportUrl" : "https://MohabMohie.github.io/SHAFT_ENGINE/allure/Linux/Web/1238//#testresult/d8375d00e5243732",
      "status" : "passed",
      "time" : {
        "start" : 1647483392414,
        "stop" : 1647483418292,
        "duration" : 25878
      }
    } ]
  },
  "eef38b1ce4f88333b32ebfb6abbceeaa" : {
    "statistic" : {
      "failed" : 0,
      "broken" : 0,
      "skipped" : 0,
      "passed" : 1,
      "unknown" : 0,
      "total" : 1
    },
    "items" : [ {
      "uid" : "378acc9734056e2a",
      "reportUrl" : "https://MohabMohie.github.io/SHAFT_ENGINE/allure/Linux/Web/1238//#testresult/378acc9734056e2a",
      "status" : "passed",
      "time" : {
        "start" : 1647483558073,
        "stop" : 1647483558146,
        "duration" : 73
      }
    } ]
  },
  "5702a1676b94e58bea6b43247a9f5f63" : {
    "statistic" : {
      "failed" : 0,
      "broken" : 0,
      "skipped" : 0,
      "passed" : 1,
      "unknown" : 0,
      "total" : 1
    },
    "items" : [ {
      "uid" : "6be1e1895a5a7027",
      "reportUrl" : "https://MohabMohie.github.io/SHAFT_ENGINE/allure/Linux/Web/1238//#testresult/6be1e1895a5a7027",
      "status" : "passed",
      "time" : {
        "start" : 1647483185806,
        "stop" : 1647483370073,
        "duration" : 184267
      }
    } ]
  },
  "264074a39b89752d2d36dd84bd40d1a6" : {
    "statistic" : {
      "failed" : 0,
      "broken" : 0,
      "skipped" : 0,
      "passed" : 1,
      "unknown" : 0,
      "total" : 1
    },
    "items" : [ {
      "uid" : "9b1686e6fdbb1c3c",
      "reportUrl" : "https://MohabMohie.github.io/SHAFT_ENGINE/allure/Linux/Web/1238//#testresult/9b1686e6fdbb1c3c",
      "status" : "passed",
      "time" : {
        "start" : 1647483610237,
        "stop" : 1647483611654,
        "duration" : 1417
      }
    } ]
  },
  "476ac2975115e742d5e5e8c3b57ebdf4" : {
    "statistic" : {
      "failed" : 0,
      "broken" : 0,
      "skipped" : 0,
      "passed" : 1,
      "unknown" : 0,
      "total" : 1
    },
    "items" : [ {
      "uid" : "6d2c637eb41bd412",
      "reportUrl" : "https://MohabMohie.github.io/SHAFT_ENGINE/allure/Linux/Web/1238//#testresult/6d2c637eb41bd412",
      "status" : "passed",
      "time" : {
        "start" : 1647483561478,
        "stop" : 1647483561534,
        "duration" : 56
      }
    } ]
  },
  "bb7188203f90a1a2fad67230270ae7d6" : {
    "statistic" : {
      "failed" : 0,
      "broken" : 0,
      "skipped" : 0,
      "passed" : 1,
      "unknown" : 0,
      "total" : 1
    },
    "items" : [ {
      "uid" : "d2654ffac2ce2520",
      "reportUrl" : "https://MohabMohie.github.io/SHAFT_ENGINE/allure/Linux/Web/1238//#testresult/d2654ffac2ce2520",
      "status" : "passed",
      "time" : {
        "start" : 1647483040928,
        "stop" : 1647483044859,
        "duration" : 3931
      }
    } ]
  },
  "2665e846a50930cc0c074f7f99a4ca8a" : {
    "statistic" : {
      "failed" : 0,
      "broken" : 0,
      "skipped" : 0,
      "passed" : 1,
      "unknown" : 0,
      "total" : 1
    },
    "items" : [ {
      "uid" : "42b02dae887d6fa3",
      "reportUrl" : "https://MohabMohie.github.io/SHAFT_ENGINE/allure/Linux/Web/1238//#testresult/42b02dae887d6fa3",
      "status" : "passed",
      "time" : {
        "start" : 1647483055349,
        "stop" : 1647483055381,
        "duration" : 32
      }
    } ]
  },
  "1691af37f7c9ae9ee1c9cd54fed41695" : {
    "statistic" : {
      "failed" : 0,
      "broken" : 0,
      "skipped" : 0,
      "passed" : 1,
      "unknown" : 0,
      "total" : 1
    },
    "items" : [ {
      "uid" : "d90ca577dbcc7928",
      "reportUrl" : "https://MohabMohie.github.io/SHAFT_ENGINE/allure/Linux/Web/1238//#testresult/d90ca577dbcc7928",
      "status" : "passed",
      "time" : {
        "start" : 1647483452411,
        "stop" : 1647483452412,
        "duration" : 1
      }
    } ]
  },
  "c86091caae292bffb9efd84314332710" : {
    "statistic" : {
      "failed" : 0,
      "broken" : 0,
      "skipped" : 0,
      "passed" : 1,
      "unknown" : 0,
      "total" : 1
    },
    "items" : [ {
      "uid" : "388f5e3da4e798df",
      "reportUrl" : "https://MohabMohie.github.io/SHAFT_ENGINE/allure/Linux/Web/1238//#testresult/388f5e3da4e798df",
      "status" : "passed",
      "time" : {
        "start" : 1647483452440,
        "stop" : 1647483452441,
        "duration" : 1
      }
    } ]
  },
  "317e6cef9e3891b5a07975bb25bc5fb2" : {
    "statistic" : {
      "failed" : 0,
      "broken" : 0,
      "skipped" : 0,
      "passed" : 1,
      "unknown" : 0,
      "total" : 1
    },
    "items" : [ {
      "uid" : "5cb1e9b91342ba6f",
      "reportUrl" : "https://MohabMohie.github.io/SHAFT_ENGINE/allure/Linux/Web/1238//#testresult/5cb1e9b91342ba6f",
      "status" : "passed",
      "time" : {
        "start" : 1647483421953,
        "stop" : 1647483421955,
        "duration" : 2
      }
    } ]
  },
  "ac6789217d4b4a32d112e105cd2efa1f" : {
    "statistic" : {
      "failed" : 0,
      "broken" : 0,
      "skipped" : 0,
      "passed" : 1,
      "unknown" : 0,
      "total" : 1
    },
    "items" : [ {
      "uid" : "eb4b9b221b4603ac",
      "reportUrl" : "https://MohabMohie.github.io/SHAFT_ENGINE/allure/Linux/Web/1238//#testresult/eb4b9b221b4603ac",
      "status" : "passed",
      "time" : {
        "start" : 1647483631803,
        "stop" : 1647483633522,
        "duration" : 1719
      }
    } ]
  },
  "2a27a2abfdee42bde8e58c16a0e0f5dd" : {
    "statistic" : {
      "failed" : 0,
      "broken" : 0,
      "skipped" : 0,
      "passed" : 1,
      "unknown" : 0,
      "total" : 1
    },
    "items" : [ {
      "uid" : "953ce2d934b6572d",
      "reportUrl" : "https://MohabMohie.github.io/SHAFT_ENGINE/allure/Linux/Web/1238//#testresult/953ce2d934b6572d",
      "status" : "passed",
      "time" : {
        "start" : 1647483452429,
        "stop" : 1647483452430,
        "duration" : 1
      }
    } ]
  },
  "bef677b60015e2d35d5030f6c3bfcf99" : {
    "statistic" : {
      "failed" : 0,
      "broken" : 0,
      "skipped" : 0,
      "passed" : 1,
      "unknown" : 0,
      "total" : 1
    },
    "items" : [ {
      "uid" : "15ce5c102d2f97cc",
      "reportUrl" : "https://MohabMohie.github.io/SHAFT_ENGINE/allure/Linux/Web/1238//#testresult/15ce5c102d2f97cc",
      "status" : "passed",
      "time" : {
        "start" : 1647483692281,
        "stop" : 1647483692283,
        "duration" : 2
      }
    } ]
  },
  "8c403aaf85c1c2abafe0a9a5d008562b" : {
    "statistic" : {
      "failed" : 0,
      "broken" : 0,
      "skipped" : 0,
      "passed" : 1,
      "unknown" : 0,
      "total" : 1
    },
    "items" : [ {
      "uid" : "f8c728613795585e",
      "reportUrl" : "https://MohabMohie.github.io/SHAFT_ENGINE/allure/Linux/Web/1238//#testresult/f8c728613795585e",
      "status" : "passed",
      "time" : {
        "start" : 1647483104322,
        "stop" : 1647483107547,
        "duration" : 3225
      }
    } ]
  },
  "ada58dba4d4104022dc5d96f0cd4fe5" : {
    "statistic" : {
      "failed" : 0,
      "broken" : 0,
      "skipped" : 0,
      "passed" : 1,
      "unknown" : 0,
      "total" : 1
    },
    "items" : [ {
      "uid" : "2992f376b4416816",
      "reportUrl" : "https://MohabMohie.github.io/SHAFT_ENGINE/allure/Linux/Web/1238//#testresult/2992f376b4416816",
      "status" : "passed",
      "time" : {
        "start" : 1647483693311,
        "stop" : 1647483695367,
        "duration" : 2056
      }
    } ]
  },
  "dc2cc42de249444fb1e5a25eaca827d0" : {
    "statistic" : {
      "failed" : 0,
      "broken" : 0,
      "skipped" : 0,
      "passed" : 1,
      "unknown" : 0,
      "total" : 1
    },
    "items" : [ {
      "uid" : "4604813970e9cd39",
      "reportUrl" : "https://MohabMohie.github.io/SHAFT_ENGINE/allure/Linux/Web/1238//#testresult/4604813970e9cd39",
      "status" : "passed",
      "time" : {
        "start" : 1647483453200,
        "stop" : 1647483453853,
        "duration" : 653
      }
    } ]
  },
  "1ef8e17d688014fbe6390ba22408aa7b" : {
    "statistic" : {
      "failed" : 0,
      "broken" : 0,
      "skipped" : 0,
      "passed" : 1,
      "unknown" : 0,
      "total" : 1
    },
    "items" : [ {
      "uid" : "f51c7868ae600db",
      "reportUrl" : "https://MohabMohie.github.io/SHAFT_ENGINE/allure/Linux/Web/1238//#testresult/f51c7868ae600db",
      "status" : "passed",
      "time" : {
        "start" : 1647483635773,
        "stop" : 1647483637741,
        "duration" : 1968
      }
    } ]
  },
  "eb4868839e997e5aed90ae6a95488276" : {
    "statistic" : {
      "failed" : 0,
      "broken" : 0,
      "skipped" : 0,
      "passed" : 1,
      "unknown" : 0,
      "total" : 1
    },
    "items" : [ {
      "uid" : "9d8f189e4992a3f8",
      "reportUrl" : "https://MohabMohie.github.io/SHAFT_ENGINE/allure/Linux/Web/1238//#testresult/9d8f189e4992a3f8",
      "status" : "passed",
      "time" : {
        "start" : 1647483594777,
        "stop" : 1647483596023,
        "duration" : 1246
      }
    } ]
  },
  "2935f6195ae2ad2b57e1bc1f5cb3a205" : {
    "statistic" : {
      "failed" : 0,
      "broken" : 0,
      "skipped" : 0,
      "passed" : 1,
      "unknown" : 0,
      "total" : 1
    },
    "items" : [ {
      "uid" : "4c6c4e40492b7a56",
      "reportUrl" : "https://MohabMohie.github.io/SHAFT_ENGINE/allure/Linux/Web/1238//#testresult/4c6c4e40492b7a56",
      "status" : "passed",
      "time" : {
        "start" : 1647483066133,
        "stop" : 1647483070250,
        "duration" : 4117
      }
    } ]
  },
  "e8b8340fde60dd2f177bd721ae597277" : {
    "statistic" : {
      "failed" : 0,
      "broken" : 0,
      "skipped" : 0,
      "passed" : 1,
      "unknown" : 0,
      "total" : 1
    },
    "items" : [ {
      "uid" : "32d2b6ef027337b8",
      "reportUrl" : "https://MohabMohie.github.io/SHAFT_ENGINE/allure/Linux/Web/1238//#testresult/32d2b6ef027337b8",
      "status" : "passed",
      "time" : {
        "start" : 1647483531302,
        "stop" : 1647483533129,
        "duration" : 1827
      }
    } ]
  },
  "8d1d2653d45ddc1144dd8fa258b167c2" : {
    "statistic" : {
      "failed" : 0,
      "broken" : 0,
      "skipped" : 0,
      "passed" : 1,
      "unknown" : 0,
      "total" : 1
    },
    "items" : [ {
      "uid" : "dd13c4816b191e9",
      "reportUrl" : "https://MohabMohie.github.io/SHAFT_ENGINE/allure/Linux/Web/1238//#testresult/dd13c4816b191e9",
      "status" : "passed",
      "time" : {
        "start" : 1647483639486,
        "stop" : 1647483640174,
        "duration" : 688
      }
    } ]
  },
  "bdef01ca6cf8bbcc16448d374eaad143" : {
    "statistic" : {
      "failed" : 0,
      "broken" : 0,
      "skipped" : 0,
      "passed" : 1,
      "unknown" : 0,
      "total" : 1
    },
    "items" : [ {
      "uid" : "4eee2d112f3ddba7",
      "reportUrl" : "https://MohabMohie.github.io/SHAFT_ENGINE/allure/Linux/Web/1238//#testresult/4eee2d112f3ddba7",
      "status" : "passed",
      "time" : {
        "start" : 1647483452445,
        "stop" : 1647483452454,
        "duration" : 9
      }
    } ]
  },
  "a7e9d82b8312bf54112ba6b33d3a8577" : {
    "statistic" : {
      "failed" : 0,
      "broken" : 0,
      "skipped" : 0,
      "passed" : 1,
      "unknown" : 0,
      "total" : 1
    },
    "items" : [ {
      "uid" : "38e5c6e82fa0cf9c",
      "reportUrl" : "https://MohabMohie.github.io/SHAFT_ENGINE/allure/Linux/Web/1238//#testresult/38e5c6e82fa0cf9c",
      "status" : "passed",
      "time" : {
        "start" : 1647483452418,
        "stop" : 1647483452420,
        "duration" : 2
      }
    } ]
  },
  "7a5a0716c213c4b3784adbf28353af84" : {
    "statistic" : {
      "failed" : 0,
      "broken" : 0,
      "skipped" : 0,
      "passed" : 1,
      "unknown" : 0,
      "total" : 1
    },
    "items" : [ {
      "uid" : "55cb7369cd370fec",
      "reportUrl" : "https://MohabMohie.github.io/SHAFT_ENGINE/allure/Linux/Web/1238//#testresult/55cb7369cd370fec",
      "status" : "passed",
      "time" : {
        "start" : 1647483572317,
        "stop" : 1647483574786,
        "duration" : 2469
      }
    } ]
  },
  "f031b53e9f7c0028d5e3acbdc1200881" : {
    "statistic" : {
      "failed" : 0,
      "broken" : 0,
      "skipped" : 0,
      "passed" : 1,
      "unknown" : 0,
      "total" : 1
    },
    "items" : [ {
      "uid" : "a4c17644c1aaea59",
      "reportUrl" : "https://MohabMohie.github.io/SHAFT_ENGINE/allure/Linux/Web/1238//#testresult/a4c17644c1aaea59",
      "status" : "passed",
      "time" : {
        "start" : 1647483077990,
        "stop" : 1647483084820,
        "duration" : 6830
      }
    } ]
  },
  "50a7bbf2e6e4c20e0204965d4abee130" : {
    "statistic" : {
      "failed" : 0,
      "broken" : 0,
      "skipped" : 0,
      "passed" : 1,
      "unknown" : 0,
      "total" : 1
    },
    "items" : [ {
      "uid" : "e8f93155d100a8f",
      "reportUrl" : "https://MohabMohie.github.io/SHAFT_ENGINE/allure/Linux/Web/1238//#testresult/e8f93155d100a8f",
      "status" : "passed",
      "time" : {
        "start" : 1647483591830,
        "stop" : 1647483593160,
        "duration" : 1330
      }
    } ]
  },
  "b9150818268b7ec2c8e5485db15d9400" : {
    "statistic" : {
      "failed" : 0,
      "broken" : 0,
      "skipped" : 0,
      "passed" : 1,
      "unknown" : 0,
      "total" : 1
    },
    "items" : [ {
      "uid" : "4f2b77c7a3d69595",
      "reportUrl" : "https://MohabMohie.github.io/SHAFT_ENGINE/allure/Linux/Web/1238//#testresult/4f2b77c7a3d69595",
      "status" : "passed",
      "time" : {
        "start" : 1647483584012,
        "stop" : 1647483584013,
        "duration" : 1
      }
    } ]
  },
  "f7635885016b46463315d3b46906bf7a" : {
    "statistic" : {
      "failed" : 0,
      "broken" : 0,
      "skipped" : 0,
      "passed" : 1,
      "unknown" : 0,
      "total" : 1
    },
    "items" : [ {
      "uid" : "7b63850d636f887a",
      "reportUrl" : "https://MohabMohie.github.io/SHAFT_ENGINE/allure/Linux/Web/1238//#testresult/7b63850d636f887a",
      "status" : "passed",
      "time" : {
        "start" : 1647483693305,
        "stop" : 1647483693306,
        "duration" : 1
      }
    } ]
  },
  "badd6454e3076c44a673a71b57708fe0" : {
    "statistic" : {
      "failed" : 0,
      "broken" : 0,
      "skipped" : 0,
      "passed" : 1,
      "unknown" : 0,
      "total" : 1
    },
    "items" : [ {
      "uid" : "e513ec7aa25e4b2f",
      "reportUrl" : "https://MohabMohie.github.io/SHAFT_ENGINE/allure/Linux/Web/1238//#testresult/e513ec7aa25e4b2f",
      "status" : "passed",
      "time" : {
        "start" : 1647483175483,
        "stop" : 1647483178794,
        "duration" : 3311
      }
    } ]
  },
  "9829372d1b547228b4f16b7901ea9cc9" : {
    "statistic" : {
      "failed" : 0,
      "broken" : 0,
      "skipped" : 0,
      "passed" : 1,
      "unknown" : 0,
      "total" : 1
    },
    "items" : [ {
      "uid" : "f9a748b95d0a82fa",
      "reportUrl" : "https://MohabMohie.github.io/SHAFT_ENGINE/allure/Linux/Web/1238//#testresult/f9a748b95d0a82fa",
      "status" : "passed",
      "time" : {
        "start" : 1647483371550,
        "stop" : 1647483371575,
        "duration" : 25
      }
    } ]
  },
  "45dcfe76f1bd97f7cb03c724bcc68eb8" : {
    "statistic" : {
      "failed" : 0,
      "broken" : 0,
      "skipped" : 0,
      "passed" : 1,
      "unknown" : 0,
      "total" : 1
    },
    "items" : [ {
      "uid" : "d5a38f6659f7addd",
      "reportUrl" : "https://MohabMohie.github.io/SHAFT_ENGINE/allure/Linux/Web/1238//#testresult/d5a38f6659f7addd",
      "status" : "passed",
      "time" : {
        "start" : 1647483693307,
        "stop" : 1647483693308,
        "duration" : 1
      }
    } ]
  },
  "a56697260ac1ade7b44ceede44b0438a" : {
    "statistic" : {
      "failed" : 0,
      "broken" : 0,
      "skipped" : 0,
      "passed" : 1,
      "unknown" : 0,
      "total" : 1
    },
    "items" : [ {
      "uid" : "8311a25642f31ea4",
      "reportUrl" : "https://MohabMohie.github.io/SHAFT_ENGINE/allure/Linux/Web/1238//#testresult/8311a25642f31ea4",
      "status" : "passed",
      "time" : {
        "start" : 1647483452435,
        "stop" : 1647483452436,
        "duration" : 1
      }
    } ]
  },
  "7b01ba3878dc2dba2c2c7f95381cb742" : {
    "statistic" : {
      "failed" : 0,
      "broken" : 0,
      "skipped" : 0,
      "passed" : 1,
      "unknown" : 0,
      "total" : 1
    },
    "items" : [ {
      "uid" : "98a8582a175e0881",
      "reportUrl" : "https://MohabMohie.github.io/SHAFT_ENGINE/allure/Linux/Web/1238//#testresult/98a8582a175e0881",
      "status" : "passed",
      "time" : {
        "start" : 1647483387550,
        "stop" : 1647483388189,
        "duration" : 639
      }
    } ]
  },
  "5cf45cc810e8dfc458ef474e637734f6" : {
    "statistic" : {
      "failed" : 0,
      "broken" : 0,
      "skipped" : 0,
      "passed" : 1,
      "unknown" : 0,
      "total" : 1
    },
    "items" : [ {
      "uid" : "4075fb76571a781d",
      "reportUrl" : "https://MohabMohie.github.io/SHAFT_ENGINE/allure/Linux/Web/1238//#testresult/4075fb76571a781d",
      "status" : "passed",
      "time" : {
        "start" : 1647483588814,
        "stop" : 1647483590111,
        "duration" : 1297
      }
    } ]
  },
  "4f509b7f8127a2b88f6b1a2dc70a2a2d" : {
    "statistic" : {
      "failed" : 0,
      "broken" : 0,
      "skipped" : 0,
      "passed" : 1,
      "unknown" : 0,
      "total" : 1
    },
    "items" : [ {
      "uid" : "13679be9a19627f1",
      "reportUrl" : "https://MohabMohie.github.io/SHAFT_ENGINE/allure/Linux/Web/1238//#testresult/13679be9a19627f1",
      "status" : "passed",
      "time" : {
        "start" : 1647483370974,
        "stop" : 1647483371544,
        "duration" : 570
      }
    } ]
  },
  "265ede85dd354b1c18327880ee92510d" : {
    "statistic" : {
      "failed" : 0,
      "broken" : 0,
      "skipped" : 0,
      "passed" : 1,
      "unknown" : 0,
      "total" : 1
    },
    "items" : [ {
      "uid" : "dcf41fc0296c5f65",
      "reportUrl" : "https://MohabMohie.github.io/SHAFT_ENGINE/allure/Linux/Web/1238//#testresult/dcf41fc0296c5f65",
      "status" : "passed",
      "time" : {
        "start" : 1647483533543,
        "stop" : 1647483540042,
        "duration" : 6499
      }
    } ]
  },
  "e167cb0f0b9e165fa2d11a66959b8c90" : {
    "statistic" : {
      "failed" : 0,
      "broken" : 0,
      "skipped" : 0,
      "passed" : 1,
      "unknown" : 0,
      "total" : 1
    },
    "items" : [ {
      "uid" : "5c61273ef8f53461",
      "reportUrl" : "https://MohabMohie.github.io/SHAFT_ENGINE/allure/Linux/Web/1238//#testresult/5c61273ef8f53461",
      "status" : "passed",
      "time" : {
        "start" : 1647483370259,
        "stop" : 1647483370966,
        "duration" : 707
      }
    } ]
  },
  "780378a4706344e151b2791aff941970" : {
    "statistic" : {
      "failed" : 0,
      "broken" : 0,
      "skipped" : 0,
      "passed" : 1,
      "unknown" : 0,
      "total" : 1
    },
    "items" : [ {
      "uid" : "2bc6b0c60d029836",
      "reportUrl" : "https://MohabMohie.github.io/SHAFT_ENGINE/allure/Linux/Web/1238//#testresult/2bc6b0c60d029836",
      "status" : "passed",
      "time" : {
        "start" : 1647483178942,
        "stop" : 1647483178943,
        "duration" : 1
      }
    } ]
  },
  "b59581a81571dbdc3929ef903c9a68af" : {
    "statistic" : {
      "failed" : 0,
      "broken" : 0,
      "skipped" : 0,
      "passed" : 1,
      "unknown" : 0,
      "total" : 1
    },
    "items" : [ {
      "uid" : "e11f3c8f829ad67d",
      "reportUrl" : "https://MohabMohie.github.io/SHAFT_ENGINE/allure/Linux/Web/1238//#testresult/e11f3c8f829ad67d",
      "status" : "passed",
      "time" : {
        "start" : 1647483490185,
        "stop" : 1647483490748,
        "duration" : 563
      }
    } ]
  },
  "9c719c977867ad678cba36ac5ef0566e" : {
    "statistic" : {
      "failed" : 0,
      "broken" : 0,
      "skipped" : 0,
      "passed" : 1,
      "unknown" : 0,
      "total" : 1
    },
    "items" : [ {
      "uid" : "91366250058c727",
      "reportUrl" : "https://MohabMohie.github.io/SHAFT_ENGINE/allure/Linux/Web/1238//#testresult/91366250058c727",
      "status" : "passed",
      "time" : {
        "start" : 1647483049320,
        "stop" : 1647483051828,
        "duration" : 2508
      }
    } ]
  },
  "6bfdcb3e2066e47f76cdc938949ea3b5" : {
    "statistic" : {
      "failed" : 0,
      "broken" : 0,
      "skipped" : 0,
      "passed" : 1,
      "unknown" : 0,
      "total" : 1
    },
    "items" : [ {
      "uid" : "efd2d075d854eba4",
      "reportUrl" : "https://MohabMohie.github.io/SHAFT_ENGINE/allure/Linux/Web/1238//#testresult/efd2d075d854eba4",
      "status" : "passed",
      "time" : {
        "start" : 1647483584018,
        "stop" : 1647483584019,
        "duration" : 1
      }
    } ]
  },
  "f2d8045cb196fac44acf056daf2910f1" : {
    "statistic" : {
      "failed" : 0,
      "broken" : 0,
      "skipped" : 0,
      "passed" : 1,
      "unknown" : 0,
      "total" : 1
    },
    "items" : [ {
      "uid" : "e13f04a07845e30d",
      "reportUrl" : "https://MohabMohie.github.io/SHAFT_ENGINE/allure/Linux/Web/1238//#testresult/e13f04a07845e30d",
      "status" : "passed",
      "time" : {
        "start" : 1647483692279,
        "stop" : 1647483692280,
        "duration" : 1
      }
    } ]
  },
  "69bacfe7d32090425eadf00e77ec2fcd" : {
    "statistic" : {
      "failed" : 0,
      "broken" : 0,
      "skipped" : 0,
      "passed" : 1,
      "unknown" : 0,
      "total" : 1
    },
    "items" : [ {
      "uid" : "1f05ec3287d82b8d",
      "reportUrl" : "https://MohabMohie.github.io/SHAFT_ENGINE/allure/Linux/Web/1238//#testresult/1f05ec3287d82b8d",
      "status" : "passed",
      "time" : {
        "start" : 1647483451487,
        "stop" : 1647483452273,
        "duration" : 786
      }
    } ]
  },
  "8da2170c533f4aff45bc62dac6da1bf8" : {
    "statistic" : {
      "failed" : 0,
      "broken" : 0,
      "skipped" : 1,
      "passed" : 0,
      "unknown" : 0,
      "total" : 1
    },
    "items" : [ {
      "uid" : "7708d59d1431326f",
      "reportUrl" : "https://MohabMohie.github.io/SHAFT_ENGINE/allure/Linux/Web/1238//#testresult/7708d59d1431326f",
      "status" : "skipped",
      "statusDetails" : "Method testPackage01.TestJSPromptBox.assertOnConfirmPromptAlertWithoutTypingTextMessageResultText() on instance testPackage01.TestJSPromptBox@fd9ebde depends on not successfully finished methods \n[testPackage01.TestJSPromptBox.acceptPromptAlertWithoutTypingTextMessage() on instance testPackage01.TestJSPromptBox@fd9ebde]",
      "time" : {
        "start" : 1647483175025,
        "stop" : 1647483175040,
        "duration" : 15
      }
    } ]
  },
  "19a9da5f20787f6a62b7cf5efdc0b4e3" : {
    "statistic" : {
      "failed" : 0,
      "broken" : 0,
      "skipped" : 0,
      "passed" : 1,
      "unknown" : 0,
      "total" : 1
    },
    "items" : [ {
      "uid" : "f1e38245a0e64e51",
      "reportUrl" : "https://MohabMohie.github.io/SHAFT_ENGINE/allure/Linux/Web/1238//#testresult/f1e38245a0e64e51",
      "status" : "passed",
      "time" : {
        "start" : 1647483619314,
        "stop" : 1647483620624,
        "duration" : 1310
      }
    } ]
  },
  "60da75bce66f0a062056dcf68a93a62e" : {
    "statistic" : {
      "failed" : 0,
      "broken" : 0,
      "skipped" : 0,
      "passed" : 1,
      "unknown" : 0,
      "total" : 1
    },
    "items" : [ {
      "uid" : "866491868dbef33b",
      "reportUrl" : "https://MohabMohie.github.io/SHAFT_ENGINE/allure/Linux/Web/1238//#testresult/866491868dbef33b",
      "status" : "passed",
      "time" : {
        "start" : 1647483045540,
        "stop" : 1647483048692,
        "duration" : 3152
      }
    } ]
  },
  "4864018d69af2693dbef3cc79f4b7427" : {
    "statistic" : {
      "failed" : 0,
      "broken" : 0,
      "skipped" : 0,
      "passed" : 1,
      "unknown" : 0,
      "total" : 1
    },
    "items" : [ {
      "uid" : "e484c75cbd6cda6a",
      "reportUrl" : "https://MohabMohie.github.io/SHAFT_ENGINE/allure/Linux/Web/1238//#testresult/e484c75cbd6cda6a",
      "status" : "passed",
      "time" : {
        "start" : 1647483054198,
        "stop" : 1647483054211,
        "duration" : 13
      }
    } ]
  },
  "4417a672ef985b4faf9285ce39f0cc10" : {
    "statistic" : {
      "failed" : 0,
      "broken" : 0,
      "skipped" : 0,
      "passed" : 1,
      "unknown" : 0,
      "total" : 1
    },
    "items" : [ {
      "uid" : "6ad2d5255c871916",
      "reportUrl" : "https://MohabMohie.github.io/SHAFT_ENGINE/allure/Linux/Web/1238//#testresult/6ad2d5255c871916",
      "status" : "passed",
      "time" : {
        "start" : 1647483540454,
        "stop" : 1647483542270,
        "duration" : 1816
      }
    } ]
  },
  "83e3cd745c904b39ba98498d793686ca" : {
    "statistic" : {
      "failed" : 0,
      "broken" : 0,
      "skipped" : 0,
      "passed" : 1,
      "unknown" : 0,
      "total" : 1
    },
    "items" : [ {
      "uid" : "2ad95ff1e56191b5",
      "reportUrl" : "https://MohabMohie.github.io/SHAFT_ENGINE/allure/Linux/Web/1238//#testresult/2ad95ff1e56191b5",
      "status" : "passed",
      "time" : {
        "start" : 1647483062776,
        "stop" : 1647483065624,
        "duration" : 2848
      }
    } ]
  },
  "f18d7d9f5bd5a5538a7079ad2eaa14f" : {
    "statistic" : {
      "failed" : 0,
      "broken" : 0,
      "skipped" : 0,
      "passed" : 1,
      "unknown" : 0,
      "total" : 1
    },
    "items" : [ {
      "uid" : "646aed9178f0598d",
      "reportUrl" : "https://MohabMohie.github.io/SHAFT_ENGINE/allure/Linux/Web/1238//#testresult/646aed9178f0598d",
      "status" : "passed",
      "time" : {
        "start" : 1647483452476,
        "stop" : 1647483452478,
        "duration" : 2
      }
    } ]
  },
  "7701a929ba556c35243f11ba7bc07226" : {
    "statistic" : {
      "failed" : 0,
      "broken" : 0,
      "skipped" : 0,
      "passed" : 1,
      "unknown" : 0,
      "total" : 1
    },
    "items" : [ {
      "uid" : "47dc02ad857e2a04",
      "reportUrl" : "https://MohabMohie.github.io/SHAFT_ENGINE/allure/Linux/Web/1238//#testresult/47dc02ad857e2a04",
      "status" : "passed",
      "time" : {
        "start" : 1647483584031,
        "stop" : 1647483584032,
        "duration" : 1
      }
    } ]
  },
  "402cf2e9c00429e23b6068d754dd4dbe" : {
    "statistic" : {
      "failed" : 0,
      "broken" : 0,
      "skipped" : 0,
      "passed" : 1,
      "unknown" : 0,
      "total" : 1
    },
    "items" : [ {
      "uid" : "ac7abf45ef0023ff",
      "reportUrl" : "https://MohabMohie.github.io/SHAFT_ENGINE/allure/Linux/Web/1238//#testresult/ac7abf45ef0023ff",
      "status" : "passed",
      "time" : {
        "start" : 1647483656505,
        "stop" : 1647483687496,
        "duration" : 30991
      }
    } ]
  },
  "9ea97b85f51a64632f0eccbb9a2eca3e" : {
    "statistic" : {
      "failed" : 0,
      "broken" : 0,
      "skipped" : 0,
      "passed" : 1,
      "unknown" : 0,
      "total" : 1
    },
    "items" : [ {
      "uid" : "8d154d0548de6066",
      "reportUrl" : "https://MohabMohie.github.io/SHAFT_ENGINE/allure/Linux/Web/1238//#testresult/8d154d0548de6066",
      "status" : "passed",
      "time" : {
        "start" : 1647483692267,
        "stop" : 1647483692268,
        "duration" : 1
      }
    } ]
  },
  "ee987874b5afbcff3eca43bdb5081291" : {
    "statistic" : {
      "failed" : 0,
      "broken" : 0,
      "skipped" : 0,
      "passed" : 1,
      "unknown" : 0,
      "total" : 1
    },
    "items" : [ {
      "uid" : "6534a58725152419",
      "reportUrl" : "https://MohabMohie.github.io/SHAFT_ENGINE/allure/Linux/Web/1238//#testresult/6534a58725152419",
      "status" : "passed",
      "time" : {
        "start" : 1647483628639,
        "stop" : 1647483629967,
        "duration" : 1328
      }
    } ]
  },
  "c6d3ce9689e0c5467257ac5580affbdc" : {
    "statistic" : {
      "failed" : 0,
      "broken" : 0,
      "skipped" : 0,
      "passed" : 1,
      "unknown" : 0,
      "total" : 1
    },
    "items" : [ {
      "uid" : "1b1f2d95b73b8583",
      "reportUrl" : "https://MohabMohie.github.io/SHAFT_ENGINE/allure/Linux/Web/1238//#testresult/1b1f2d95b73b8583",
      "status" : "passed",
      "time" : {
        "start" : 1647483585564,
        "stop" : 1647483587021,
        "duration" : 1457
      }
    } ]
  },
  "e88a34f039ffaa5a3e7ec815fbf7e0ee" : {
    "statistic" : {
      "failed" : 0,
      "broken" : 0,
      "skipped" : 0,
      "passed" : 1,
      "unknown" : 0,
      "total" : 1
    },
    "items" : [ {
      "uid" : "8e16609c0f7dbd09",
      "reportUrl" : "https://MohabMohie.github.io/SHAFT_ENGINE/allure/Linux/Web/1238//#testresult/8e16609c0f7dbd09",
      "status" : "passed",
      "time" : {
        "start" : 1647483692265,
        "stop" : 1647483692266,
        "duration" : 1
      }
    } ]
  },
  "1e302c49c8f75fa918eb46dd6bc40b87" : {
    "statistic" : {
      "failed" : 0,
      "broken" : 0,
      "skipped" : 0,
      "passed" : 1,
      "unknown" : 0,
      "total" : 1
    },
    "items" : [ {
      "uid" : "25f778288549bb0f",
      "reportUrl" : "https://MohabMohie.github.io/SHAFT_ENGINE/allure/Linux/Web/1238//#testresult/25f778288549bb0f",
      "status" : "passed",
      "time" : {
        "start" : 1647483563173,
        "stop" : 1647483563214,
        "duration" : 41
      }
    } ]
  },
  "d5d715b3d739d9e30ec0c208231a5b19" : {
    "statistic" : {
      "failed" : 0,
      "broken" : 0,
      "skipped" : 0,
      "passed" : 1,
      "unknown" : 0,
      "total" : 1
    },
    "items" : [ {
      "uid" : "740776f384f3d08e",
      "reportUrl" : "https://MohabMohie.github.io/SHAFT_ENGINE/allure/Linux/Web/1238//#testresult/740776f384f3d08e",
      "status" : "passed",
      "time" : {
        "start" : 1647483372428,
        "stop" : 1647483373275,
        "duration" : 847
      }
    } ]
  },
  "a4a3705aa0579b42a1b50218e2c54e00" : {
    "statistic" : {
      "failed" : 0,
      "broken" : 0,
      "skipped" : 0,
      "passed" : 1,
      "unknown" : 0,
      "total" : 1
    },
    "items" : [ {
      "uid" : "802c6438fb772b7",
      "reportUrl" : "https://MohabMohie.github.io/SHAFT_ENGINE/allure/Linux/Web/1238//#testresult/802c6438fb772b7",
      "status" : "passed",
      "time" : {
        "start" : 1647483061189,
        "stop" : 1647483062289,
        "duration" : 1100
      }
    } ]
  },
  "2b4beb423f2d0918a09c19ca2ce5f015" : {
    "statistic" : {
      "failed" : 0,
      "broken" : 0,
      "skipped" : 0,
      "passed" : 1,
      "unknown" : 0,
      "total" : 1
    },
    "items" : [ {
      "uid" : "e23bd97f87f8978b",
      "reportUrl" : "https://MohabMohie.github.io/SHAFT_ENGINE/allure/Linux/Web/1238//#testresult/e23bd97f87f8978b",
      "status" : "passed",
      "time" : {
        "start" : 1647483101487,
        "stop" : 1647483104319,
        "duration" : 2832
      }
    } ]
  },
  "c8c76336a37556799805a49b42d957dc" : {
    "statistic" : {
      "failed" : 0,
      "broken" : 0,
      "skipped" : 0,
      "passed" : 1,
      "unknown" : 0,
      "total" : 1
    },
    "items" : [ {
      "uid" : "5bd568794783674",
      "reportUrl" : "https://MohabMohie.github.io/SHAFT_ENGINE/allure/Linux/Web/1238//#testresult/5bd568794783674",
      "status" : "passed",
      "time" : {
        "start" : 1647483691461,
        "stop" : 1647483692132,
        "duration" : 671
      }
    } ]
  },
  "f4e42247564f9e406ac4c030f5657555" : {
    "statistic" : {
      "failed" : 0,
      "broken" : 0,
      "skipped" : 0,
      "passed" : 1,
      "unknown" : 0,
      "total" : 1
    },
    "items" : [ {
      "uid" : "643a935bb0a57214",
      "reportUrl" : "https://MohabMohie.github.io/SHAFT_ENGINE/allure/Linux/Web/1238//#testresult/643a935bb0a57214",
      "status" : "passed",
      "time" : {
        "start" : 1647483693300,
        "stop" : 1647483693301,
        "duration" : 1
      }
    } ]
  },
  "b4d9a91b46088e954c06abadd0ea633f" : {
    "statistic" : {
      "failed" : 0,
      "broken" : 0,
      "skipped" : 0,
      "passed" : 1,
      "unknown" : 0,
      "total" : 1
    },
    "items" : [ {
      "uid" : "52f1d9157dfcadc8",
      "reportUrl" : "https://MohabMohie.github.io/SHAFT_ENGINE/allure/Linux/Web/1238//#testresult/52f1d9157dfcadc8",
      "status" : "passed",
      "time" : {
        "start" : 1647483603974,
        "stop" : 1647483605268,
        "duration" : 1294
      }
    } ]
  },
  "dbc6fbdd3600eccd40842e7fc2a996b7" : {
    "statistic" : {
      "failed" : 0,
      "broken" : 0,
      "skipped" : 0,
      "passed" : 1,
      "unknown" : 0,
      "total" : 1
    },
    "items" : [ {
      "uid" : "4d7f6025de35de90",
      "reportUrl" : "https://MohabMohie.github.io/SHAFT_ENGINE/allure/Linux/Web/1238//#testresult/4d7f6025de35de90",
      "status" : "passed",
      "time" : {
        "start" : 1647483554350,
        "stop" : 1647483554661,
        "duration" : 311
      }
    } ]
  },
  "171d46d4135b76235154b42b11cb9d6f" : {
    "statistic" : {
      "failed" : 0,
      "broken" : 0,
      "skipped" : 0,
      "passed" : 1,
      "unknown" : 0,
      "total" : 1
    },
    "items" : [ {
      "uid" : "49221b4feb017e77",
      "reportUrl" : "https://MohabMohie.github.io/SHAFT_ENGINE/allure/Linux/Web/1238//#testresult/49221b4feb017e77",
      "status" : "passed",
      "time" : {
        "start" : 1647483606899,
        "stop" : 1647483608318,
        "duration" : 1419
      }
    } ]
  },
  "18f634cf5b3568c85a21c57b6cffaa85" : {
    "statistic" : {
      "failed" : 0,
      "broken" : 0,
      "skipped" : 1,
      "passed" : 0,
      "unknown" : 0,
      "total" : 1
    },
    "items" : [ {
      "uid" : "7dcda26b89b50cdf",
      "reportUrl" : "https://MohabMohie.github.io/SHAFT_ENGINE/allure/Linux/Web/1238//#testresult/7dcda26b89b50cdf",
      "status" : "skipped",
      "statusDetails" : "Method testPackage01.TestJSPromptBox.assertOnConfirmPromptAlertWithTextMessageResultText() on instance testPackage01.TestJSPromptBox@fd9ebde depends on not successfully finished methods \n[testPackage01.TestJSPromptBox.acceptPromptAlertWithTextMessage() on instance testPackage01.TestJSPromptBox@fd9ebde]",
      "time" : {
        "start" : 1647483175054,
        "stop" : 1647483175070,
        "duration" : 16
      }
    } ]
  },
  "f5f5d884f40a700315cef26011f085c6" : {
    "statistic" : {
      "failed" : 0,
      "broken" : 0,
      "skipped" : 0,
      "passed" : 1,
      "unknown" : 0,
      "total" : 1
    },
    "items" : [ {
      "uid" : "c811ac6f09714dbc",
      "reportUrl" : "https://MohabMohie.github.io/SHAFT_ENGINE/allure/Linux/Web/1238//#testresult/c811ac6f09714dbc",
      "status" : "passed",
      "time" : {
        "start" : 1647483107996,
        "stop" : 1647483108028,
        "duration" : 32
      }
    } ]
  },
  "7b086c07a7672a87f96253ea13ac87a8" : {
    "statistic" : {
      "failed" : 0,
      "broken" : 0,
      "skipped" : 0,
      "passed" : 1,
      "unknown" : 0,
      "total" : 1
    },
    "items" : [ {
      "uid" : "128882f3f5fc596",
      "reportUrl" : "https://MohabMohie.github.io/SHAFT_ENGINE/allure/Linux/Web/1238//#testresult/128882f3f5fc596",
      "status" : "passed",
      "time" : {
        "start" : 1647483452442,
        "stop" : 1647483452443,
        "duration" : 1
      }
    } ]
  },
  "2502a22a0190a8d9d2d99a0b3742179f" : {
    "statistic" : {
      "failed" : 0,
      "broken" : 0,
      "skipped" : 0,
      "passed" : 1,
      "unknown" : 0,
      "total" : 1
    },
    "items" : [ {
      "uid" : "445f0c8c5a1b9f56",
      "reportUrl" : "https://MohabMohie.github.io/SHAFT_ENGINE/allure/Linux/Web/1238//#testresult/445f0c8c5a1b9f56",
      "status" : "passed",
      "time" : {
        "start" : 1647483452483,
        "stop" : 1647483452484,
        "duration" : 1
      }
    } ]
  },
  "9136ef17ad732926a16ab8d92c6bf567" : {
    "statistic" : {
      "failed" : 0,
      "broken" : 0,
      "skipped" : 0,
      "passed" : 1,
      "unknown" : 0,
      "total" : 1
    },
    "items" : [ {
      "uid" : "c42b0888b0244b69",
      "reportUrl" : "https://MohabMohie.github.io/SHAFT_ENGINE/allure/Linux/Web/1238//#testresult/c42b0888b0244b69",
      "status" : "passed",
      "time" : {
        "start" : 1647483107556,
        "stop" : 1647483107922,
        "duration" : 366
      }
    } ]
  },
  "9c149457b49558f6e51ed70eaa6cb83d" : {
    "statistic" : {
      "failed" : 0,
      "broken" : 0,
      "skipped" : 0,
      "passed" : 1,
      "unknown" : 0,
      "total" : 1
    },
    "items" : [ {
      "uid" : "80862634e1f81eea",
      "reportUrl" : "https://MohabMohie.github.io/SHAFT_ENGINE/allure/Linux/Web/1238//#testresult/80862634e1f81eea",
      "status" : "passed",
      "time" : {
        "start" : 1647483568130,
        "stop" : 1647483570648,
        "duration" : 2518
      }
    } ]
  },
  "a927bad4489beeee1ac4665341bb128" : {
    "statistic" : {
      "failed" : 0,
      "broken" : 0,
      "skipped" : 0,
      "passed" : 1,
      "unknown" : 0,
      "total" : 1
    },
    "items" : [ {
      "uid" : "50e0bc56e4bc42d2",
      "reportUrl" : "https://MohabMohie.github.io/SHAFT_ENGINE/allure/Linux/Web/1238//#testresult/50e0bc56e4bc42d2",
      "status" : "passed",
      "time" : {
        "start" : 1647483452492,
        "stop" : 1647483452493,
        "duration" : 1
      }
    } ]
  },
  "9ee600c4564b8a84210f113c6a571e46" : {
    "statistic" : {
      "failed" : 1,
      "broken" : 0,
      "skipped" : 0,
      "passed" : 0,
      "unknown" : 0,
      "total" : 1
    },
    "items" : [ {
      "uid" : "31995a6fa253a1b2",
      "reportUrl" : "https://MohabMohie.github.io/SHAFT_ENGINE/allure/Linux/Web/1238//#testresult/31995a6fa253a1b2",
      "status" : "failed",
      "statusDetails" : "Element Action [WaitForAlertToBePresent] failed.",
      "time" : {
        "start" : 1647483500355,
        "stop" : 1647483530920,
        "duration" : 30565
      }
    } ]
  },
  "b166e1c1837e7780d7033eca80f4a9c7" : {
    "statistic" : {
      "failed" : 0,
      "broken" : 0,
      "skipped" : 0,
      "passed" : 1,
      "unknown" : 0,
      "total" : 1
    },
    "items" : [ {
      "uid" : "6cb1798e13c8ef91",
      "reportUrl" : "https://MohabMohie.github.io/SHAFT_ENGINE/allure/Linux/Web/1238//#testresult/6cb1798e13c8ef91",
      "status" : "passed",
      "time" : {
        "start" : 1647483452403,
        "stop" : 1647483452404,
        "duration" : 1
      }
    } ]
  },
  "f8f970faae1267b4b5c08b241d01d5ce" : {
    "statistic" : {
      "failed" : 0,
      "broken" : 0,
      "skipped" : 0,
      "passed" : 1,
      "unknown" : 0,
      "total" : 1
    },
    "items" : [ {
      "uid" : "79f237bdc1ea3e5e",
      "reportUrl" : "https://MohabMohie.github.io/SHAFT_ENGINE/allure/Linux/Web/1238//#testresult/79f237bdc1ea3e5e",
      "status" : "passed",
      "time" : {
        "start" : 1647483564769,
        "stop" : 1647483564802,
        "duration" : 33
      }
    } ]
  },
  "f8b181c41d9f9edf4c60d33877099af8" : {
    "statistic" : {
      "failed" : 0,
      "broken" : 0,
      "skipped" : 0,
      "passed" : 1,
      "unknown" : 0,
      "total" : 1
    },
    "items" : [ {
      "uid" : "4aa21940a73da71f",
      "reportUrl" : "https://MohabMohie.github.io/SHAFT_ENGINE/allure/Linux/Web/1238//#testresult/4aa21940a73da71f",
      "status" : "passed",
      "time" : {
        "start" : 1647483452400,
        "stop" : 1647483452401,
        "duration" : 1
      }
    } ]
  },
  "13bf298e1e204216e174902a46417745" : {
    "statistic" : {
      "failed" : 0,
      "broken" : 0,
      "skipped" : 0,
      "passed" : 1,
      "unknown" : 0,
      "total" : 1
    },
    "items" : [ {
      "uid" : "5c7940832533b67",
      "reportUrl" : "https://MohabMohie.github.io/SHAFT_ENGINE/allure/Linux/Web/1238//#testresult/5c7940832533b67",
      "status" : "passed",
      "time" : {
        "start" : 1647483178928,
        "stop" : 1647483178931,
        "duration" : 3
      }
    } ]
  },
  "ac7fea32beee7e3033b84a4d116cf947" : {
    "statistic" : {
      "failed" : 0,
      "broken" : 0,
      "skipped" : 0,
      "passed" : 1,
      "unknown" : 0,
      "total" : 1
    },
    "items" : [ {
      "uid" : "1b8a5266a2b5080d",
      "reportUrl" : "https://MohabMohie.github.io/SHAFT_ENGINE/allure/Linux/Web/1238//#testresult/1b8a5266a2b5080d",
      "status" : "passed",
      "time" : {
        "start" : 1647483689221,
        "stop" : 1647483689924,
        "duration" : 703
      }
    } ]
  },
  "8161aacdafcd0cb42d3204fe0672f36b" : {
    "statistic" : {
      "failed" : 0,
      "broken" : 0,
      "skipped" : 0,
      "passed" : 1,
      "unknown" : 0,
      "total" : 1
    },
    "items" : [ {
      "uid" : "5a5ac07c7a5b3e5f",
      "reportUrl" : "https://MohabMohie.github.io/SHAFT_ENGINE/allure/Linux/Web/1238//#testresult/5a5ac07c7a5b3e5f",
      "status" : "passed",
      "time" : {
        "start" : 1647483179227,
        "stop" : 1647483180105,
        "duration" : 878
      }
    } ]
  },
  "2b4f1cef406e9101284474f8f715b361" : {
    "statistic" : {
      "failed" : 0,
      "broken" : 0,
      "skipped" : 0,
      "passed" : 1,
      "unknown" : 0,
      "total" : 1
    },
    "items" : [ {
      "uid" : "ad969464fa93879b",
      "reportUrl" : "https://MohabMohie.github.io/SHAFT_ENGINE/allure/Linux/Web/1238//#testresult/ad969464fa93879b",
      "status" : "passed",
      "time" : {
        "start" : 1647483143065,
        "stop" : 1647483143850,
        "duration" : 785
      }
    } ]
  },
  "50bcdd7464e6ba911e244a1b1a36da44" : {
    "statistic" : {
      "failed" : 0,
      "broken" : 0,
      "skipped" : 0,
      "passed" : 1,
      "unknown" : 0,
      "total" : 1
    },
    "items" : [ {
      "uid" : "4ad9b68b476b3e93",
      "reportUrl" : "https://MohabMohie.github.io/SHAFT_ENGINE/allure/Linux/Web/1238//#testresult/4ad9b68b476b3e93",
      "status" : "passed",
      "time" : {
        "start" : 1647483486319,
        "stop" : 1647483489884,
        "duration" : 3565
      }
    } ]
  },
  "5aeeb05dac2ac013bdebccaa0aaf698e" : {
    "statistic" : {
      "failed" : 0,
      "broken" : 0,
      "skipped" : 0,
      "passed" : 1,
      "unknown" : 0,
      "total" : 1
    },
    "items" : [ {
      "uid" : "e9c1d0fa61d74135",
      "reportUrl" : "https://MohabMohie.github.io/SHAFT_ENGINE/allure/Linux/Web/1238//#testresult/e9c1d0fa61d74135",
      "status" : "passed",
      "time" : {
        "start" : 1647483654206,
        "stop" : 1647483654881,
        "duration" : 675
      }
    } ]
  },
  "1d2f699b44814327bb7ff247318e9c4e" : {
    "statistic" : {
      "failed" : 0,
      "broken" : 0,
      "skipped" : 0,
      "passed" : 1,
      "unknown" : 0,
      "total" : 1
    },
    "items" : [ {
      "uid" : "25d9a0fd4d360f0f",
      "reportUrl" : "https://MohabMohie.github.io/SHAFT_ENGINE/allure/Linux/Web/1238//#testresult/25d9a0fd4d360f0f",
      "status" : "passed",
      "time" : {
        "start" : 1647483597631,
        "stop" : 1647483599008,
        "duration" : 1377
      }
    } ]
  },
  "e6016fd1907b3a0435b9f68cbecabd91" : {
    "statistic" : {
      "failed" : 0,
      "broken" : 0,
      "skipped" : 0,
      "passed" : 1,
      "unknown" : 0,
      "total" : 1
    },
    "items" : [ {
      "uid" : "27c8f3ed580096bf",
      "reportUrl" : "https://MohabMohie.github.io/SHAFT_ENGINE/allure/Linux/Web/1238//#testresult/27c8f3ed580096bf",
      "status" : "passed",
      "time" : {
        "start" : 1647483389090,
        "stop" : 1647483389758,
        "duration" : 668
      }
    } ]
  },
  "a3286ba2438900d0ed238b99b97c7891" : {
    "statistic" : {
      "failed" : 0,
      "broken" : 0,
      "skipped" : 0,
      "passed" : 1,
      "unknown" : 0,
      "total" : 1
    },
    "items" : [ {
      "uid" : "3665b6dfed4936cf",
      "reportUrl" : "https://MohabMohie.github.io/SHAFT_ENGINE/allure/Linux/Web/1238//#testresult/3665b6dfed4936cf",
      "status" : "passed",
      "time" : {
        "start" : 1647483584029,
        "stop" : 1647483584030,
        "duration" : 1
      }
    } ]
  },
  "3b2afb193a21ad7584f3b3879b7e7304" : {
    "statistic" : {
      "failed" : 0,
      "broken" : 0,
      "skipped" : 0,
      "passed" : 1,
      "unknown" : 0,
      "total" : 1
    },
    "items" : [ {
      "uid" : "70d8d77bdc7bac2",
      "reportUrl" : "https://MohabMohie.github.io/SHAFT_ENGINE/allure/Linux/Web/1238//#testresult/70d8d77bdc7bac2",
      "status" : "passed",
      "time" : {
        "start" : 1647483542708,
        "stop" : 1647483549598,
        "duration" : 6890
      }
    } ]
  },
  "eeb601a92e1e55857588ad433767f280" : {
    "statistic" : {
      "failed" : 0,
      "broken" : 0,
      "skipped" : 0,
      "passed" : 1,
      "unknown" : 0,
      "total" : 1
    },
    "items" : [ {
      "uid" : "98e2fb88f7c80721",
      "reportUrl" : "https://MohabMohie.github.io/SHAFT_ENGINE/allure/Linux/Web/1238//#testresult/98e2fb88f7c80721",
      "status" : "passed",
      "time" : {
        "start" : 1647483452472,
        "stop" : 1647483452473,
        "duration" : 1
      }
    } ]
  },
  "abb72e27d987b2601e9ffbedb4ad837e" : {
    "statistic" : {
      "failed" : 0,
      "broken" : 0,
      "skipped" : 0,
      "passed" : 1,
      "unknown" : 0,
      "total" : 1
    },
    "items" : [ {
      "uid" : "d075eb54c95eacb5",
      "reportUrl" : "https://MohabMohie.github.io/SHAFT_ENGINE/allure/Linux/Web/1238//#testresult/d075eb54c95eacb5",
      "status" : "passed",
      "time" : {
        "start" : 1647483452425,
        "stop" : 1647483452427,
        "duration" : 2
      }
    } ]
  },
  "a7ae2e4757a67e15ea26bc18a732a5d0" : {
    "statistic" : {
      "failed" : 0,
      "broken" : 0,
      "skipped" : 0,
      "passed" : 1,
      "unknown" : 0,
      "total" : 1
    },
    "items" : [ {
      "uid" : "77b9958632a66f96",
      "reportUrl" : "https://MohabMohie.github.io/SHAFT_ENGINE/allure/Linux/Web/1238//#testresult/77b9958632a66f96",
      "status" : "passed",
      "time" : {
        "start" : 1647483584007,
        "stop" : 1647483584008,
        "duration" : 1
      }
    } ]
  },
  "2fdd1b1e4216687e4f48e717329d30ac" : {
    "statistic" : {
      "failed" : 0,
      "broken" : 0,
      "skipped" : 0,
      "passed" : 1,
      "unknown" : 0,
      "total" : 1
    },
    "items" : [ {
      "uid" : "e3d8f52200330b9",
      "reportUrl" : "https://MohabMohie.github.io/SHAFT_ENGINE/allure/Linux/Web/1238//#testresult/e3d8f52200330b9",
      "status" : "passed",
      "time" : {
        "start" : 1647483559781,
        "stop" : 1647483559826,
        "duration" : 45
      }
    } ]
  },
  "8462550d8c94ec5a4ee08184c5723334" : {
    "statistic" : {
      "failed" : 0,
      "broken" : 0,
      "skipped" : 0,
      "passed" : 1,
      "unknown" : 0,
      "total" : 1
    },
    "items" : [ {
      "uid" : "208b034a5821b79e",
      "reportUrl" : "https://MohabMohie.github.io/SHAFT_ENGINE/allure/Linux/Web/1238//#testresult/208b034a5821b79e",
      "status" : "passed",
      "time" : {
        "start" : 1647483452480,
        "stop" : 1647483452482,
        "duration" : 2
      }
    } ]
  },
  "a861b2f90300876d9b9281725e416280" : {
    "statistic" : {
      "failed" : 0,
      "broken" : 0,
      "skipped" : 0,
      "passed" : 1,
      "unknown" : 0,
      "total" : 1
    },
    "items" : [ {
      "uid" : "f329aada4fc7df49",
      "reportUrl" : "https://MohabMohie.github.io/SHAFT_ENGINE/allure/Linux/Web/1238//#testresult/f329aada4fc7df49",
      "status" : "passed",
      "time" : {
        "start" : 1647483584009,
        "stop" : 1647483584011,
        "duration" : 2
      }
    } ]
  },
  "8f568206e17e876b394eac7436d24026" : {
    "statistic" : {
      "failed" : 0,
      "broken" : 0,
      "skipped" : 0,
      "passed" : 1,
      "unknown" : 0,
      "total" : 1
    },
    "items" : [ {
      "uid" : "7b4a3ebc235b6db4",
      "reportUrl" : "https://MohabMohie.github.io/SHAFT_ENGINE/allure/Linux/Web/1238//#testresult/7b4a3ebc235b6db4",
      "status" : "passed",
      "time" : {
        "start" : 1647483422777,
        "stop" : 1647483423471,
        "duration" : 694
      }
    } ]
  },
  "6279582d02bb323ff2fca935852a8c5f" : {
    "statistic" : {
      "failed" : 0,
      "broken" : 0,
      "skipped" : 0,
      "passed" : 1,
      "unknown" : 0,
      "total" : 1
    },
    "items" : [ {
      "uid" : "3e3512c4ad6b1d1d",
      "reportUrl" : "https://MohabMohie.github.io/SHAFT_ENGINE/allure/Linux/Web/1238//#testresult/3e3512c4ad6b1d1d",
      "status" : "passed",
      "time" : {
        "start" : 1647483692275,
        "stop" : 1647483692276,
        "duration" : 1
      }
    } ]
  },
  "127389d9950e04e895798bb93e2e53ef" : {
    "statistic" : {
      "failed" : 0,
      "broken" : 0,
      "skipped" : 0,
      "passed" : 1,
      "unknown" : 0,
      "total" : 1
    },
    "items" : [ {
      "uid" : "3a1921c69d38656",
      "reportUrl" : "https://MohabMohie.github.io/SHAFT_ENGINE/allure/Linux/Web/1238//#testresult/3a1921c69d38656",
      "status" : "passed",
      "time" : {
        "start" : 1647483371579,
        "stop" : 1647483371581,
        "duration" : 2
      }
    } ]
  },
  "a2b4829c99b25b0f138408ac2f2752bd" : {
    "statistic" : {
      "failed" : 0,
      "broken" : 0,
      "skipped" : 0,
      "passed" : 1,
      "unknown" : 0,
      "total" : 1
    },
    "items" : [ {
      "uid" : "b82da129627d633c",
      "reportUrl" : "https://MohabMohie.github.io/SHAFT_ENGINE/allure/Linux/Web/1238//#testresult/b82da129627d633c",
      "status" : "passed",
      "time" : {
        "start" : 1647483494858,
        "stop" : 1647483498754,
        "duration" : 3896
      }
    } ]
  },
  "f7cea628e60912dec54c96e154519b67" : {
    "statistic" : {
      "failed" : 0,
      "broken" : 0,
      "skipped" : 0,
      "passed" : 1,
      "unknown" : 0,
      "total" : 1
    },
    "items" : [ {
      "uid" : "f1b77476f6a781d7",
      "reportUrl" : "https://MohabMohie.github.io/SHAFT_ENGINE/allure/Linux/Web/1238//#testresult/f1b77476f6a781d7",
      "status" : "passed",
      "time" : {
        "start" : 1647483613353,
        "stop" : 1647483614769,
        "duration" : 1416
      }
    } ]
  },
  "605cff6f7746d803bcbc232d25a70fa0" : {
    "statistic" : {
      "failed" : 0,
      "broken" : 0,
      "skipped" : 0,
      "passed" : 1,
      "unknown" : 0,
      "total" : 1
    },
    "items" : [ {
      "uid" : "8442b5acf5206c05",
      "reportUrl" : "https://MohabMohie.github.io/SHAFT_ENGINE/allure/Linux/Web/1238//#testresult/8442b5acf5206c05",
      "status" : "passed",
      "time" : {
        "start" : 1647483452459,
        "stop" : 1647483452460,
        "duration" : 1
      }
    } ]
  },
  "1f0fafbcfcffce619645851c43df5ae4" : {
    "statistic" : {
      "failed" : 0,
      "broken" : 0,
      "skipped" : 0,
      "passed" : 1,
      "unknown" : 0,
      "total" : 1
    },
    "items" : [ {
      "uid" : "d0e8126fb4e29664",
      "reportUrl" : "https://MohabMohie.github.io/SHAFT_ENGINE/allure/Linux/Web/1238//#testresult/d0e8126fb4e29664",
      "status" : "passed",
      "time" : {
        "start" : 1647483549981,
        "stop" : 1647483551693,
        "duration" : 1712
      }
    } ]
  },
  "7c21062b2157c9c5386d90359de23d53" : {
    "statistic" : {
      "failed" : 0,
      "broken" : 0,
      "skipped" : 0,
      "passed" : 1,
      "unknown" : 0,
      "total" : 1
    },
    "items" : [ {
      "uid" : "866d2c1675f11873",
      "reportUrl" : "https://MohabMohie.github.io/SHAFT_ENGINE/allure/Linux/Web/1238//#testresult/866d2c1675f11873",
      "status" : "passed",
      "time" : {
        "start" : 1647483143858,
        "stop" : 1647483144351,
        "duration" : 493
      }
    } ]
  },
  "f76e83298b125d9f8051305662bd868b" : {
    "statistic" : {
      "failed" : 0,
      "broken" : 0,
      "skipped" : 0,
      "passed" : 1,
      "unknown" : 0,
      "total" : 1
    },
    "items" : [ {
      "uid" : "55029c78f7f04bd6",
      "reportUrl" : "https://MohabMohie.github.io/SHAFT_ENGINE/allure/Linux/Web/1238//#testresult/55029c78f7f04bd6",
      "status" : "passed",
      "time" : {
        "start" : 1647483390694,
        "stop" : 1647483391430,
        "duration" : 736
      }
    } ]
  },
  "8a583f3461f88d7c293779bde04a0e1d" : {
    "statistic" : {
      "failed" : 0,
      "broken" : 0,
      "skipped" : 0,
      "passed" : 1,
      "unknown" : 0,
      "total" : 1
    },
    "items" : [ {
      "uid" : "b208320b40397e48",
      "reportUrl" : "https://MohabMohie.github.io/SHAFT_ENGINE/allure/Linux/Web/1238//#testresult/b208320b40397e48",
      "status" : "passed",
      "time" : {
        "start" : 1647483385866,
        "stop" : 1647483386549,
        "duration" : 683
      }
    } ]
  },
  "36df61c5fa16064939f2168a752af02b" : {
    "statistic" : {
      "failed" : 0,
      "broken" : 0,
      "skipped" : 0,
      "passed" : 1,
      "unknown" : 0,
      "total" : 1
    },
    "items" : [ {
      "uid" : "92dd312c249258f4",
      "reportUrl" : "https://MohabMohie.github.io/SHAFT_ENGINE/allure/Linux/Web/1238//#testresult/92dd312c249258f4",
      "status" : "passed",
      "time" : {
        "start" : 1647483183239,
        "stop" : 1647483185441,
        "duration" : 2202
      }
    } ]
  },
  "d20688892e8370917ded3954bd58a936" : {
    "statistic" : {
      "failed" : 0,
      "broken" : 0,
      "skipped" : 0,
      "passed" : 1,
      "unknown" : 0,
      "total" : 1
    },
    "items" : [ {
      "uid" : "ec7678fc16dcec8d",
      "reportUrl" : "https://MohabMohie.github.io/SHAFT_ENGINE/allure/Linux/Web/1238//#testresult/ec7678fc16dcec8d",
      "status" : "passed",
      "time" : {
        "start" : 1647483692277,
        "stop" : 1647483692278,
        "duration" : 1
      }
    } ]
  },
  "d305933be8c1545e88e65f9f5733babf" : {
    "statistic" : {
      "failed" : 0,
      "broken" : 0,
      "skipped" : 0,
      "passed" : 1,
      "unknown" : 0,
      "total" : 1
    },
    "items" : [ {
      "uid" : "9d21ad7c34c2bb31",
      "reportUrl" : "https://MohabMohie.github.io/SHAFT_ENGINE/allure/Linux/Web/1238//#testresult/9d21ad7c34c2bb31",
      "status" : "passed",
      "time" : {
        "start" : 1647483058177,
        "stop" : 1647483061186,
        "duration" : 3009
      }
    } ]
  },
  "8a87a21477193c438040ea0bf35f7853" : {
    "statistic" : {
      "failed" : 0,
      "broken" : 0,
      "skipped" : 0,
      "passed" : 1,
      "unknown" : 0,
      "total" : 1
    },
    "items" : [ {
      "uid" : "a243d1ba445f2e52",
      "reportUrl" : "https://MohabMohie.github.io/SHAFT_ENGINE/allure/Linux/Web/1238//#testresult/a243d1ba445f2e52",
      "status" : "passed",
      "time" : {
        "start" : 1647483452466,
        "stop" : 1647483452467,
        "duration" : 1
      }
    } ]
  },
  "3e73c6377dbba1c4391d565476180108" : {
    "statistic" : {
      "failed" : 0,
      "broken" : 0,
      "skipped" : 0,
      "passed" : 1,
      "unknown" : 0,
      "total" : 1
    },
    "items" : [ {
      "uid" : "cf8a9d813d6a1a4a",
      "reportUrl" : "https://MohabMohie.github.io/SHAFT_ENGINE/allure/Linux/Web/1238//#testresult/cf8a9d813d6a1a4a",
      "status" : "passed",
      "time" : {
        "start" : 1647483553196,
        "stop" : 1647483553402,
        "duration" : 206
      }
    } ]
  },
  "b916e3a3cf9aae34687e6cba489385fd" : {
    "statistic" : {
      "failed" : 0,
      "broken" : 0,
      "skipped" : 0,
      "passed" : 1,
      "unknown" : 0,
      "total" : 1
    },
    "items" : [ {
      "uid" : "2759f5ee206d355c",
      "reportUrl" : "https://MohabMohie.github.io/SHAFT_ENGINE/allure/Linux/Web/1238//#testresult/2759f5ee206d355c",
      "status" : "passed",
      "time" : {
        "start" : 1647483556327,
        "stop" : 1647483556369,
        "duration" : 42
      }
    } ]
  },
  "fa265a8627bd99827e3fc01138cc6263" : {
    "statistic" : {
      "failed" : 0,
      "broken" : 0,
      "skipped" : 0,
      "passed" : 1,
      "unknown" : 0,
      "total" : 1
    },
    "items" : [ {
      "uid" : "4f59e3b5742bc80e",
      "reportUrl" : "https://MohabMohie.github.io/SHAFT_ENGINE/allure/Linux/Web/1238//#testresult/4f59e3b5742bc80e",
      "status" : "passed",
      "time" : {
        "start" : 1647483054213,
        "stop" : 1647483055341,
        "duration" : 1128
      }
    } ]
  },
  "afc8cfa07b82f889f102dc4910710386" : {
    "statistic" : {
      "failed" : 0,
      "broken" : 0,
      "skipped" : 0,
      "passed" : 1,
      "unknown" : 0,
      "total" : 1
    },
    "items" : [ {
      "uid" : "7bc10dfa9494b5c8",
      "reportUrl" : "https://MohabMohie.github.io/SHAFT_ENGINE/allure/Linux/Web/1238//#testresult/7bc10dfa9494b5c8",
      "status" : "passed",
      "time" : {
        "start" : 1647483491218,
        "stop" : 1647483494309,
        "duration" : 3091
      }
    } ]
  },
  "4059f51a9d634b52b216f44f3bf27ccc" : {
    "statistic" : {
      "failed" : 0,
      "broken" : 0,
      "skipped" : 0,
      "passed" : 1,
      "unknown" : 0,
      "total" : 1
    },
    "items" : [ {
      "uid" : "f3dc93fac77b8ffa",
      "reportUrl" : "https://MohabMohie.github.io/SHAFT_ENGINE/allure/Linux/Web/1238//#testresult/f3dc93fac77b8ffa",
      "status" : "passed",
      "time" : {
        "start" : 1647483692269,
        "stop" : 1647483692271,
        "duration" : 2
      }
    } ]
  },
  "33865050f01a74fce461b1ec0dbab96f" : {
    "statistic" : {
      "failed" : 1,
      "broken" : 0,
      "skipped" : 0,
      "passed" : 0,
      "unknown" : 0,
      "total" : 1
    },
    "items" : [ {
      "uid" : "25ac062c61940c5c",
      "reportUrl" : "https://MohabMohie.github.io/SHAFT_ENGINE/allure/Linux/Web/1238//#testresult/25ac062c61940c5c",
      "status" : "failed",
      "statusDetails" : "Element Action [WaitForAlertToBePresent] failed.",
      "time" : {
        "start" : 1647483110592,
        "stop" : 1647483141409,
        "duration" : 30817
      }
    } ]
  },
  "45512e220734b6213e89df6e5f078970" : {
    "statistic" : {
      "failed" : 0,
      "broken" : 0,
      "skipped" : 0,
      "passed" : 1,
      "unknown" : 0,
      "total" : 1
    },
    "items" : [ {
      "uid" : "6891f4aee8cb1921",
      "reportUrl" : "https://MohabMohie.github.io/SHAFT_ENGINE/allure/Linux/Web/1238//#testresult/6891f4aee8cb1921",
      "status" : "passed",
      "time" : {
        "start" : 1647483584025,
        "stop" : 1647483584026,
        "duration" : 1
      }
    } ]
  }
}