{
  "c80eb0293658685903bd1fd24f492c08" : {
    "statistic" : {
      "failed" : 0,
      "broken" : 0,
      "skipped" : 0,
      "passed" : 1,
      "unknown" : 0,
      "total" : 1
    },
    "items" : [ {
      "uid" : "2618a16edf81dc30",
      "reportUrl" : "https://MohabMohie.github.io/SHAFT_ENGINE/allure/Linux/Web/1243//#testresult/2618a16edf81dc30",
      "status" : "passed",
      "time" : {
        "start" : 1647754408510,
        "stop" : 1647754411082,
        "duration" : 2572
      }
    } ]
  },
  "5d486709805afb09377652af1cb44b43" : {
    "statistic" : {
      "failed" : 0,
      "broken" : 0,
      "skipped" : 1,
      "passed" : 0,
      "unknown" : 0,
      "total" : 1
    },
    "items" : [ {
      "uid" : "e8b2d690075a4f6d",
      "reportUrl" : "https://MohabMohie.github.io/SHAFT_ENGINE/allure/Linux/Web/1243//#testresult/e8b2d690075a4f6d",
      "status" : "skipped",
      "statusDetails" : "Method testPackage01.TestJSPromptBox.acceptPromptAlertWithTextMessage() on instance testPackage01.TestJSPromptBox@290d10ef depends on not successfully finished methods \n[testPackage01.TestJSPromptBox.assertOnConfirmPromptAlertWithoutTypingTextMessageResultText() on instance testPackage01.TestJSPromptBox@290d10ef]",
      "time" : {
        "start" : 1647754508719,
        "stop" : 1647754508727,
        "duration" : 8
      }
    } ]
  },
  "7b0f8854a7aed9a150b2fc57963781fa" : {
    "statistic" : {
      "failed" : 0,
      "broken" : 0,
      "skipped" : 0,
      "passed" : 1,
      "unknown" : 0,
      "total" : 1
    },
    "items" : [ {
      "uid" : "626113e12b5c56b",
      "reportUrl" : "https://MohabMohie.github.io/SHAFT_ENGINE/allure/Linux/Web/1243//#testresult/626113e12b5c56b",
      "status" : "passed",
      "time" : {
        "start" : 1647754615850,
        "stop" : 1647754615850,
        "duration" : 0
      }
    } ]
  },
  "42db9a0b95e9103a321dfe36eb368c1b" : {
    "statistic" : {
      "failed" : 0,
      "broken" : 0,
      "skipped" : 0,
      "passed" : 1,
      "unknown" : 0,
      "total" : 1
    },
    "items" : [ {
      "uid" : "7ad465f8a667de54",
      "reportUrl" : "https://MohabMohie.github.io/SHAFT_ENGINE/allure/Linux/Web/1243//#testresult/7ad465f8a667de54",
      "status" : "passed",
      "time" : {
        "start" : 1647754388046,
        "stop" : 1647754390317,
        "duration" : 2271
      }
    } ]
  },
  "9557c3315a180b8221de8066c242409a" : {
    "statistic" : {
      "failed" : 0,
      "broken" : 0,
      "skipped" : 0,
      "passed" : 1,
      "unknown" : 0,
      "total" : 1
    },
    "items" : [ {
      "uid" : "fbabcc74e6f68725",
      "reportUrl" : "https://MohabMohie.github.io/SHAFT_ENGINE/allure/Linux/Web/1243//#testresult/fbabcc74e6f68725",
      "status" : "passed",
      "time" : {
        "start" : 1647754729373,
        "stop" : 1647754729611,
        "duration" : 238
      }
    } ]
  },
  "2314bd23a656a36ab83c22386848f0d4" : {
    "statistic" : {
      "failed" : 0,
      "broken" : 0,
      "skipped" : 0,
      "passed" : 1,
      "unknown" : 0,
      "total" : 1
    },
    "items" : [ {
      "uid" : "438f294c5aff83f7",
      "reportUrl" : "https://MohabMohie.github.io/SHAFT_ENGINE/allure/Linux/Web/1243//#testresult/438f294c5aff83f7",
      "status" : "passed",
      "time" : {
        "start" : 1647754476497,
        "stop" : 1647754476928,
        "duration" : 431
      }
    } ]
  },
  "3f6e5843fc6c685f5ebc75fde75ac218" : {
    "statistic" : {
      "failed" : 0,
      "broken" : 0,
      "skipped" : 0,
      "passed" : 1,
      "unknown" : 0,
      "total" : 1
    },
    "items" : [ {
      "uid" : "716a07e51172007b",
      "reportUrl" : "https://MohabMohie.github.io/SHAFT_ENGINE/allure/Linux/Web/1243//#testresult/716a07e51172007b",
      "status" : "passed",
      "time" : {
        "start" : 1647754763186,
        "stop" : 1647754764629,
        "duration" : 1443
      }
    } ]
  },
  "973cdadfe7b0529022bcd219aff55968" : {
    "statistic" : {
      "failed" : 0,
      "broken" : 0,
      "skipped" : 0,
      "passed" : 1,
      "unknown" : 0,
      "total" : 1
    },
    "items" : [ {
      "uid" : "26df084d9aa79823",
      "reportUrl" : "https://MohabMohie.github.io/SHAFT_ENGINE/allure/Linux/Web/1243//#testresult/26df084d9aa79823",
      "status" : "passed",
      "time" : {
        "start" : 1647754650739,
        "stop" : 1647754650740,
        "duration" : 1
      }
    } ]
  },
  "4a29903560362dbd17b5dd05d236bc8b" : {
    "statistic" : {
      "failed" : 0,
      "broken" : 0,
      "skipped" : 0,
      "passed" : 1,
      "unknown" : 0,
      "total" : 1
    },
    "items" : [ {
      "uid" : "2c93fb8b69c11718",
      "reportUrl" : "https://MohabMohie.github.io/SHAFT_ENGINE/allure/Linux/Web/1243//#testresult/2c93fb8b69c11718",
      "status" : "passed",
      "time" : {
        "start" : 1647754443143,
        "stop" : 1647754443853,
        "duration" : 710
      }
    } ]
  },
  "7ce456f557879027bc598b94d15d7182" : {
    "statistic" : {
      "failed" : 0,
      "broken" : 0,
      "skipped" : 0,
      "passed" : 1,
      "unknown" : 0,
      "total" : 1
    },
    "items" : [ {
      "uid" : "e2f2469182749089",
      "reportUrl" : "https://MohabMohie.github.io/SHAFT_ENGINE/allure/Linux/Web/1243//#testresult/e2f2469182749089",
      "status" : "passed",
      "time" : {
        "start" : 1647754747451,
        "stop" : 1647754747452,
        "duration" : 1
      }
    } ]
  },
  "7e80de2d453155ab307b931149cee737" : {
    "statistic" : {
      "failed" : 0,
      "broken" : 0,
      "skipped" : 0,
      "passed" : 1,
      "unknown" : 0,
      "total" : 1
    },
    "items" : [ {
      "uid" : "2893c46eb00f7795",
      "reportUrl" : "https://MohabMohie.github.io/SHAFT_ENGINE/allure/Linux/Web/1243//#testresult/2893c46eb00f7795",
      "status" : "passed",
      "time" : {
        "start" : 1647754619659,
        "stop" : 1647754650630,
        "duration" : 30971
      }
    } ]
  },
  "d22b5e6c4280f54bf49831434b9e5018" : {
    "statistic" : {
      "failed" : 0,
      "broken" : 0,
      "skipped" : 0,
      "passed" : 1,
      "unknown" : 0,
      "total" : 1
    },
    "items" : [ {
      "uid" : "b3b988b768fb7119",
      "reportUrl" : "https://MohabMohie.github.io/SHAFT_ENGINE/allure/Linux/Web/1243//#testresult/b3b988b768fb7119",
      "status" : "passed",
      "time" : {
        "start" : 1647754860030,
        "stop" : 1647754860543,
        "duration" : 513
      }
    } ]
  },
  "d9c1f161fa2285acc4faca119ad8939" : {
    "statistic" : {
      "failed" : 0,
      "broken" : 0,
      "skipped" : 0,
      "passed" : 1,
      "unknown" : 0,
      "total" : 1
    },
    "items" : [ {
      "uid" : "2c567622b9b453f5",
      "reportUrl" : "https://MohabMohie.github.io/SHAFT_ENGINE/allure/Linux/Web/1243//#testresult/2c567622b9b453f5",
      "status" : "passed",
      "time" : {
        "start" : 1647754387635,
        "stop" : 1647754387638,
        "duration" : 3
      }
    } ]
  },
  "d766de23786c53f441d161eddaf1215a" : {
    "statistic" : {
      "failed" : 0,
      "broken" : 0,
      "skipped" : 0,
      "passed" : 1,
      "unknown" : 0,
      "total" : 1
    },
    "items" : [ {
      "uid" : "59030694e7eb88aa",
      "reportUrl" : "https://MohabMohie.github.io/SHAFT_ENGINE/allure/Linux/Web/1243//#testresult/59030694e7eb88aa",
      "status" : "passed",
      "time" : {
        "start" : 1647754615831,
        "stop" : 1647754615833,
        "duration" : 2
      }
    } ]
  },
  "64a8852b286bab5ef838177e652e731e" : {
    "statistic" : {
      "failed" : 0,
      "broken" : 0,
      "skipped" : 0,
      "passed" : 1,
      "unknown" : 0,
      "total" : 1
    },
    "items" : [ {
      "uid" : "f1fefcbd6ac93e20",
      "reportUrl" : "https://MohabMohie.github.io/SHAFT_ENGINE/allure/Linux/Web/1243//#testresult/f1fefcbd6ac93e20",
      "status" : "passed",
      "time" : {
        "start" : 1647754861053,
        "stop" : 1647754861054,
        "duration" : 1
      }
    } ]
  },
  "bb31d8b47e1a96c6836334320447d229" : {
    "statistic" : {
      "failed" : 0,
      "broken" : 0,
      "skipped" : 0,
      "passed" : 1,
      "unknown" : 0,
      "total" : 1
    },
    "items" : [ {
      "uid" : "594f5e2f30abfd7e",
      "reportUrl" : "https://MohabMohie.github.io/SHAFT_ENGINE/allure/Linux/Web/1243//#testresult/594f5e2f30abfd7e",
      "status" : "passed",
      "time" : {
        "start" : 1647754663650,
        "stop" : 1647754664096,
        "duration" : 446
      }
    } ]
  },
  "eb85811949f431b7a228b6de557ce34e" : {
    "statistic" : {
      "failed" : 0,
      "broken" : 0,
      "skipped" : 0,
      "passed" : 1,
      "unknown" : 0,
      "total" : 1
    },
    "items" : [ {
      "uid" : "1c80b9b3a8935989",
      "reportUrl" : "https://MohabMohie.github.io/SHAFT_ENGINE/allure/Linux/Web/1243//#testresult/1c80b9b3a8935989",
      "status" : "passed",
      "time" : {
        "start" : 1647754615896,
        "stop" : 1647754615897,
        "duration" : 1
      }
    } ]
  },
  "e025b82a7d1b9f5f8cfaebf774709daa" : {
    "statistic" : {
      "failed" : 0,
      "broken" : 0,
      "skipped" : 0,
      "passed" : 1,
      "unknown" : 0,
      "total" : 1
    },
    "items" : [ {
      "uid" : "7e587729c72f9864",
      "reportUrl" : "https://MohabMohie.github.io/SHAFT_ENGINE/allure/Linux/Web/1243//#testresult/7e587729c72f9864",
      "status" : "passed",
      "time" : {
        "start" : 1647754403875,
        "stop" : 1647754408235,
        "duration" : 4360
      }
    } ]
  },
  "89010c35d43262e5174c0abc3b833ff2" : {
    "statistic" : {
      "failed" : 1,
      "broken" : 0,
      "skipped" : 0,
      "passed" : 0,
      "unknown" : 0,
      "total" : 1
    },
    "items" : [ {
      "uid" : "903f769fe97ca74d",
      "reportUrl" : "https://MohabMohie.github.io/SHAFT_ENGINE/allure/Linux/Web/1243//#testresult/903f769fe97ca74d",
      "status" : "failed",
      "statusDetails" : "Element Action [WaitForAlertToBePresent] failed.",
      "time" : {
        "start" : 1647754478094,
        "stop" : 1647754508697,
        "duration" : 30603
      }
    } ]
  },
  "f5eb3e0657331ec851f236cbdec9dbc3" : {
    "statistic" : {
      "failed" : 0,
      "broken" : 0,
      "skipped" : 0,
      "passed" : 1,
      "unknown" : 0,
      "total" : 1
    },
    "items" : [ {
      "uid" : "841459864974a956",
      "reportUrl" : "https://MohabMohie.github.io/SHAFT_ENGINE/allure/Linux/Web/1243//#testresult/841459864974a956",
      "status" : "passed",
      "time" : {
        "start" : 1647754777556,
        "stop" : 1647754778903,
        "duration" : 1347
      }
    } ]
  },
  "b7fc3abf80e9bbdd5097280c59543cd9" : {
    "statistic" : {
      "failed" : 0,
      "broken" : 0,
      "skipped" : 0,
      "passed" : 1,
      "unknown" : 0,
      "total" : 1
    },
    "items" : [ {
      "uid" : "aad0474a189b2eb1",
      "reportUrl" : "https://MohabMohie.github.io/SHAFT_ENGINE/allure/Linux/Web/1243//#testresult/aad0474a189b2eb1",
      "status" : "passed",
      "time" : {
        "start" : 1647754860018,
        "stop" : 1647754860020,
        "duration" : 2
      }
    } ]
  },
  "18ebb827f5e596bdd48750256bb3ed08" : {
    "statistic" : {
      "failed" : 0,
      "broken" : 0,
      "skipped" : 0,
      "passed" : 1,
      "unknown" : 0,
      "total" : 1
    },
    "items" : [ {
      "uid" : "127d0dcf31734a1f",
      "reportUrl" : "https://MohabMohie.github.io/SHAFT_ENGINE/allure/Linux/Web/1243//#testresult/127d0dcf31734a1f",
      "status" : "passed",
      "time" : {
        "start" : 1647754741571,
        "stop" : 1647754742773,
        "duration" : 1202
      }
    } ]
  },
  "e13eda38936ccb8186efbcb0f47508c8" : {
    "statistic" : {
      "failed" : 0,
      "broken" : 0,
      "skipped" : 0,
      "passed" : 1,
      "unknown" : 0,
      "total" : 1
    },
    "items" : [ {
      "uid" : "572d4361af458c90",
      "reportUrl" : "https://MohabMohie.github.io/SHAFT_ENGINE/allure/Linux/Web/1243//#testresult/572d4361af458c90",
      "status" : "passed",
      "time" : {
        "start" : 1647754580082,
        "stop" : 1647754580798,
        "duration" : 716
      }
    } ]
  },
  "17b5b8806ac7eb710c4c7956140eaecf" : {
    "statistic" : {
      "failed" : 0,
      "broken" : 0,
      "skipped" : 0,
      "passed" : 1,
      "unknown" : 0,
      "total" : 1
    },
    "items" : [ {
      "uid" : "26f00884e43599c4",
      "reportUrl" : "https://MohabMohie.github.io/SHAFT_ENGINE/allure/Linux/Web/1243//#testresult/26f00884e43599c4",
      "status" : "passed",
      "time" : {
        "start" : 1647754866346,
        "stop" : 1647754867465,
        "duration" : 1119
      }
    } ]
  },
  "fa8089fdd54895368300d31f35070cea" : {
    "statistic" : {
      "failed" : 0,
      "broken" : 0,
      "skipped" : 0,
      "passed" : 1,
      "unknown" : 0,
      "total" : 1
    },
    "items" : [ {
      "uid" : "156d5d334f9ac9e6",
      "reportUrl" : "https://MohabMohie.github.io/SHAFT_ENGINE/allure/Linux/Web/1243//#testresult/156d5d334f9ac9e6",
      "status" : "passed",
      "time" : {
        "start" : 1647754860546,
        "stop" : 1647754861048,
        "duration" : 502
      }
    } ]
  },
  "19999555bce5de3735ec04b0e0646e14" : {
    "statistic" : {
      "failed" : 0,
      "broken" : 0,
      "skipped" : 1,
      "passed" : 0,
      "unknown" : 0,
      "total" : 1
    },
    "items" : [ {
      "uid" : "2641248612f35833",
      "reportUrl" : "https://MohabMohie.github.io/SHAFT_ENGINE/allure/Linux/Web/1243//#testresult/2641248612f35833",
      "status" : "skipped",
      "statusDetails" : "Method testPackage01.TestJSAlertBox.assertOnConfirmAlertResultText() on instance testPackage01.TestJSAlertBox@4c777e7b depends on not successfully finished methods \n[testPackage01.TestJSAlertBox.acceptAlert() on instance testPackage01.TestJSAlertBox@4c777e7b]",
      "time" : {
        "start" : 1647754694568,
        "stop" : 1647754694574,
        "duration" : 6
      }
    } ]
  },
  "381ba714b0c66de2985d3ae81acb5e17" : {
    "statistic" : {
      "failed" : 0,
      "broken" : 0,
      "skipped" : 0,
      "passed" : 1,
      "unknown" : 0,
      "total" : 1
    },
    "items" : [ {
      "uid" : "30a3f4d10685661f",
      "reportUrl" : "https://MohabMohie.github.io/SHAFT_ENGINE/allure/Linux/Web/1243//#testresult/30a3f4d10685661f",
      "status" : "passed",
      "time" : {
        "start" : 1647754615857,
        "stop" : 1647754615858,
        "duration" : 1
      }
    } ]
  },
  "8a857219522d374b9811362ab4602182" : {
    "statistic" : {
      "failed" : 0,
      "broken" : 0,
      "skipped" : 0,
      "passed" : 1,
      "unknown" : 0,
      "total" : 1
    },
    "items" : [ {
      "uid" : "fc72fde1e36e10f1",
      "reportUrl" : "https://MohabMohie.github.io/SHAFT_ENGINE/allure/Linux/Web/1243//#testresult/fc72fde1e36e10f1",
      "status" : "passed",
      "time" : {
        "start" : 1647754783242,
        "stop" : 1647754784704,
        "duration" : 1462
      }
    } ]
  },
  "b1a09b6933c16fdc5feb53cd6bbf1690" : {
    "statistic" : {
      "failed" : 0,
      "broken" : 0,
      "skipped" : 0,
      "passed" : 1,
      "unknown" : 0,
      "total" : 1
    },
    "items" : [ {
      "uid" : "545b7fba67399b0",
      "reportUrl" : "https://MohabMohie.github.io/SHAFT_ENGINE/allure/Linux/Web/1243//#testresult/545b7fba67399b0",
      "status" : "passed",
      "time" : {
        "start" : 1647754786290,
        "stop" : 1647754787653,
        "duration" : 1363
      }
    } ]
  },
  "7c02c0395504a7a7869fd091b6dfff0b" : {
    "statistic" : {
      "failed" : 0,
      "broken" : 0,
      "skipped" : 0,
      "passed" : 1,
      "unknown" : 0,
      "total" : 1
    },
    "items" : [ {
      "uid" : "41c949a49927571d",
      "reportUrl" : "https://MohabMohie.github.io/SHAFT_ENGINE/allure/Linux/Web/1243//#testresult/41c949a49927571d",
      "status" : "passed",
      "time" : {
        "start" : 1647754384688,
        "stop" : 1647754386273,
        "duration" : 1585
      }
    } ]
  },
  "7546566432535191f8975bb3f3cb9a48" : {
    "statistic" : {
      "failed" : 0,
      "broken" : 0,
      "skipped" : 0,
      "passed" : 1,
      "unknown" : 0,
      "total" : 1
    },
    "items" : [ {
      "uid" : "c1c9daf1722abb5e",
      "reportUrl" : "https://MohabMohie.github.io/SHAFT_ENGINE/allure/Linux/Web/1243//#testresult/c1c9daf1722abb5e",
      "status" : "passed",
      "time" : {
        "start" : 1647754650746,
        "stop" : 1647754650747,
        "duration" : 1
      }
    } ]
  },
  "81dccf0fa5dda2c07b8a2e38642301d4" : {
    "statistic" : {
      "failed" : 0,
      "broken" : 0,
      "skipped" : 0,
      "passed" : 1,
      "unknown" : 0,
      "total" : 1
    },
    "items" : [ {
      "uid" : "26523cca1a84875",
      "reportUrl" : "https://MohabMohie.github.io/SHAFT_ENGINE/allure/Linux/Web/1243//#testresult/26523cca1a84875",
      "status" : "passed",
      "time" : {
        "start" : 1647754514632,
        "stop" : 1647754518368,
        "duration" : 3736
      }
    } ]
  },
  "24d179f984390efd4095c1ca70d9ae83" : {
    "statistic" : {
      "failed" : 0,
      "broken" : 0,
      "skipped" : 1,
      "passed" : 0,
      "unknown" : 0,
      "total" : 1
    },
    "items" : [ {
      "uid" : "95d7d52fd9dc905b",
      "reportUrl" : "https://MohabMohie.github.io/SHAFT_ENGINE/allure/Linux/Web/1243//#testresult/95d7d52fd9dc905b",
      "status" : "skipped",
      "statusDetails" : "Method testPackage01.TestJSConfirmBox.assertOnConfirmAlertResultText() on instance testPackage01.TestJSConfirmBox@7899de11 depends on not successfully finished methods \n[testPackage01.TestJSConfirmBox.acceptAlert() on instance testPackage01.TestJSConfirmBox@7899de11]",
      "time" : {
        "start" : 1647754475005,
        "stop" : 1647754475018,
        "duration" : 13
      }
    } ]
  },
  "c5a92213d3cbe213658c780681a07039" : {
    "statistic" : {
      "failed" : 0,
      "broken" : 0,
      "skipped" : 0,
      "passed" : 1,
      "unknown" : 0,
      "total" : 1
    },
    "items" : [ {
      "uid" : "876083d9407db635",
      "reportUrl" : "https://MohabMohie.github.io/SHAFT_ENGINE/allure/Linux/Web/1243//#testresult/876083d9407db635",
      "status" : "passed",
      "time" : {
        "start" : 1647754744599,
        "stop" : 1647754744916,
        "duration" : 317
      }
    } ]
  },
  "5eb7f769276356accd4c25c7c882af5f" : {
    "statistic" : {
      "failed" : 0,
      "broken" : 0,
      "skipped" : 0,
      "passed" : 1,
      "unknown" : 0,
      "total" : 1
    },
    "items" : [ {
      "uid" : "dd625ab9718566f8",
      "reportUrl" : "https://MohabMohie.github.io/SHAFT_ENGINE/allure/Linux/Web/1243//#testresult/dd625ab9718566f8",
      "status" : "passed",
      "time" : {
        "start" : 1647754582497,
        "stop" : 1647754583340,
        "duration" : 843
      }
    } ]
  },
  "50b134c4ce45667640a8b328092e77c" : {
    "statistic" : {
      "failed" : 0,
      "broken" : 0,
      "skipped" : 0,
      "passed" : 1,
      "unknown" : 0,
      "total" : 1
    },
    "items" : [ {
      "uid" : "7775c7ecaa023fe6",
      "reportUrl" : "https://MohabMohie.github.io/SHAFT_ENGINE/allure/Linux/Web/1243//#testresult/7775c7ecaa023fe6",
      "status" : "passed",
      "time" : {
        "start" : 1647754863642,
        "stop" : 1647754866342,
        "duration" : 2700
      }
    } ]
  },
  "b27c77614b887aad9233c87f6d999b88" : {
    "statistic" : {
      "failed" : 0,
      "broken" : 0,
      "skipped" : 0,
      "passed" : 1,
      "unknown" : 0,
      "total" : 1
    },
    "items" : [ {
      "uid" : "ffb5cb1ba2982117",
      "reportUrl" : "https://MohabMohie.github.io/SHAFT_ENGINE/allure/Linux/Web/1243//#testresult/ffb5cb1ba2982117",
      "status" : "passed",
      "time" : {
        "start" : 1647754662260,
        "stop" : 1647754662296,
        "duration" : 36
      }
    } ]
  },
  "5514b76ba1dc4de2d7fa6ed8af87a94e" : {
    "statistic" : {
      "failed" : 0,
      "broken" : 0,
      "skipped" : 0,
      "passed" : 1,
      "unknown" : 0,
      "total" : 1
    },
    "items" : [ {
      "uid" : "db7b7d6f1fb2fe69",
      "reportUrl" : "https://MohabMohie.github.io/SHAFT_ENGINE/allure/Linux/Web/1243//#testresult/db7b7d6f1fb2fe69",
      "status" : "passed",
      "time" : {
        "start" : 1647754714327,
        "stop" : 1647754715574,
        "duration" : 1247
      }
    } ]
  },
  "259a17265cbc92933de3cafb98400a6e" : {
    "statistic" : {
      "failed" : 0,
      "broken" : 0,
      "skipped" : 0,
      "passed" : 1,
      "unknown" : 0,
      "total" : 1
    },
    "items" : [ {
      "uid" : "9a6a89ffab5b0180",
      "reportUrl" : "https://MohabMohie.github.io/SHAFT_ENGINE/allure/Linux/Web/1243//#testresult/9a6a89ffab5b0180",
      "status" : "passed",
      "time" : {
        "start" : 1647754587495,
        "stop" : 1647754613333,
        "duration" : 25838
      }
    } ]
  },
  "a55bf854e3301a0d60e84ba8c52fc696" : {
    "statistic" : {
      "failed" : 0,
      "broken" : 0,
      "skipped" : 0,
      "passed" : 1,
      "unknown" : 0,
      "total" : 1
    },
    "items" : [ {
      "uid" : "87178996ab795494",
      "reportUrl" : "https://MohabMohie.github.io/SHAFT_ENGINE/allure/Linux/Web/1243//#testresult/87178996ab795494",
      "status" : "passed",
      "time" : {
        "start" : 1647754655003,
        "stop" : 1647754655322,
        "duration" : 319
      }
    } ]
  },
  "29286b1e51fc227b9e82df438242ddee" : {
    "statistic" : {
      "failed" : 0,
      "broken" : 0,
      "skipped" : 0,
      "passed" : 1,
      "unknown" : 0,
      "total" : 1
    },
    "items" : [ {
      "uid" : "914c489a01857e0b",
      "reportUrl" : "https://MohabMohie.github.io/SHAFT_ENGINE/allure/Linux/Web/1243//#testresult/914c489a01857e0b",
      "status" : "passed",
      "time" : {
        "start" : 1647754443856,
        "stop" : 1647754444383,
        "duration" : 527
      }
    } ]
  },
  "8a4b6fbdb2fb99adceabd3a1832314da" : {
    "statistic" : {
      "failed" : 0,
      "broken" : 0,
      "skipped" : 0,
      "passed" : 1,
      "unknown" : 0,
      "total" : 1
    },
    "items" : [ {
      "uid" : "400bc93d6d43d356",
      "reportUrl" : "https://MohabMohie.github.io/SHAFT_ENGINE/allure/Linux/Web/1243//#testresult/400bc93d6d43d356",
      "status" : "passed",
      "time" : {
        "start" : 1647754662299,
        "stop" : 1647754662321,
        "duration" : 22
      }
    } ]
  },
  "449a6e184141d72ffe54fd6d696434a1" : {
    "statistic" : {
      "failed" : 0,
      "broken" : 0,
      "skipped" : 0,
      "passed" : 1,
      "unknown" : 0,
      "total" : 1
    },
    "items" : [ {
      "uid" : "e6ec43653abd1270",
      "reportUrl" : "https://MohabMohie.github.io/SHAFT_ENGINE/allure/Linux/Web/1243//#testresult/e6ec43653abd1270",
      "status" : "passed",
      "time" : {
        "start" : 1647754810079,
        "stop" : 1647754820738,
        "duration" : 10659
      }
    } ]
  },
  "8f7225c8a7be388cf13fecdcb10b58f2" : {
    "statistic" : {
      "failed" : 0,
      "broken" : 0,
      "skipped" : 0,
      "passed" : 1,
      "unknown" : 0,
      "total" : 1
    },
    "items" : [ {
      "uid" : "b5b3b0a19b1fad9a",
      "reportUrl" : "https://MohabMohie.github.io/SHAFT_ENGINE/allure/Linux/Web/1243//#testresult/b5b3b0a19b1fad9a",
      "status" : "passed",
      "time" : {
        "start" : 1647754615891,
        "stop" : 1647754615892,
        "duration" : 1
      }
    } ]
  },
  "4604ee6340e8cffa6c36a592668ef42b" : {
    "statistic" : {
      "failed" : 0,
      "broken" : 0,
      "skipped" : 0,
      "passed" : 1,
      "unknown" : 0,
      "total" : 1
    },
    "items" : [ {
      "uid" : "ba4f6a9e5c1e2708",
      "reportUrl" : "https://MohabMohie.github.io/SHAFT_ENGINE/allure/Linux/Web/1243//#testresult/ba4f6a9e5c1e2708",
      "status" : "passed",
      "time" : {
        "start" : 1647754861060,
        "stop" : 1647754861062,
        "duration" : 2
      }
    } ]
  },
  "8fbac502e2af59bbc9b8d6966d933655" : {
    "statistic" : {
      "failed" : 0,
      "broken" : 0,
      "skipped" : 0,
      "passed" : 1,
      "unknown" : 0,
      "total" : 1
    },
    "items" : [ {
      "uid" : "2fcc358a822e0f6",
      "reportUrl" : "https://MohabMohie.github.io/SHAFT_ENGINE/allure/Linux/Web/1243//#testresult/2fcc358a822e0f6",
      "status" : "passed",
      "time" : {
        "start" : 1647754739310,
        "stop" : 1647754739798,
        "duration" : 488
      }
    } ]
  },
  "544df7d2fdf8d5d984aa580e8196cbfd" : {
    "statistic" : {
      "failed" : 0,
      "broken" : 0,
      "skipped" : 0,
      "passed" : 1,
      "unknown" : 0,
      "total" : 1
    },
    "items" : [ {
      "uid" : "cf2d583e6672edc9",
      "reportUrl" : "https://MohabMohie.github.io/SHAFT_ENGINE/allure/Linux/Web/1243//#testresult/cf2d583e6672edc9",
      "status" : "passed",
      "time" : {
        "start" : 1647754512611,
        "stop" : 1647754512612,
        "duration" : 1
      }
    } ]
  },
  "fb7f8cd889260df26b212bf10e840f0b" : {
    "statistic" : {
      "failed" : 0,
      "broken" : 0,
      "skipped" : 0,
      "passed" : 1,
      "unknown" : 0,
      "total" : 1
    },
    "items" : [ {
      "uid" : "df37d7110357cf01",
      "reportUrl" : "https://MohabMohie.github.io/SHAFT_ENGINE/allure/Linux/Web/1243//#testresult/df37d7110357cf01",
      "status" : "passed",
      "time" : {
        "start" : 1647754442654,
        "stop" : 1647754443130,
        "duration" : 476
      }
    } ]
  },
  "41278362e80181fdd24eb6bcfdf1706d" : {
    "statistic" : {
      "failed" : 0,
      "broken" : 0,
      "skipped" : 0,
      "passed" : 1,
      "unknown" : 0,
      "total" : 1
    },
    "items" : [ {
      "uid" : "dbef41c6eea9d3bb",
      "reportUrl" : "https://MohabMohie.github.io/SHAFT_ENGINE/allure/Linux/Web/1243//#testresult/dbef41c6eea9d3bb",
      "status" : "passed",
      "time" : {
        "start" : 1647754530308,
        "stop" : 1647754540974,
        "duration" : 10666
      }
    } ]
  },
  "a668d1f7bbf0bd93bfbcd970b468fe16" : {
    "statistic" : {
      "failed" : 0,
      "broken" : 0,
      "skipped" : 0,
      "passed" : 1,
      "unknown" : 0,
      "total" : 1
    },
    "items" : [ {
      "uid" : "c157cc6307a0845c",
      "reportUrl" : "https://MohabMohie.github.io/SHAFT_ENGINE/allure/Linux/Web/1243//#testresult/c157cc6307a0845c",
      "status" : "passed",
      "time" : {
        "start" : 1647754747421,
        "stop" : 1647754747423,
        "duration" : 2
      }
    } ]
  },
  "ceff922ad3b0be43f47e1a6c9f6d6bb7" : {
    "statistic" : {
      "failed" : 0,
      "broken" : 0,
      "skipped" : 0,
      "passed" : 1,
      "unknown" : 0,
      "total" : 1
    },
    "items" : [ {
      "uid" : "b4a96b5112689550",
      "reportUrl" : "https://MohabMohie.github.io/SHAFT_ENGINE/allure/Linux/Web/1243//#testresult/b4a96b5112689550",
      "status" : "passed",
      "time" : {
        "start" : 1647754615819,
        "stop" : 1647754615821,
        "duration" : 2
      }
    } ]
  },
  "d29c9fb7cd6947e47db9b9fdd63ebebd" : {
    "statistic" : {
      "failed" : 0,
      "broken" : 0,
      "skipped" : 0,
      "passed" : 1,
      "unknown" : 0,
      "total" : 1
    },
    "items" : [ {
      "uid" : "cc29a2a04fd03f71",
      "reportUrl" : "https://MohabMohie.github.io/SHAFT_ENGINE/allure/Linux/Web/1243//#testresult/cc29a2a04fd03f71",
      "status" : "passed",
      "time" : {
        "start" : 1647754746576,
        "stop" : 1647754746805,
        "duration" : 229
      }
    } ]
  },
  "eef38b1ce4f88333b32ebfb6abbceeaa" : {
    "statistic" : {
      "failed" : 0,
      "broken" : 0,
      "skipped" : 0,
      "passed" : 1,
      "unknown" : 0,
      "total" : 1
    },
    "items" : [ {
      "uid" : "8442ddf441ebbac7",
      "reportUrl" : "https://MohabMohie.github.io/SHAFT_ENGINE/allure/Linux/Web/1243//#testresult/8442ddf441ebbac7",
      "status" : "passed",
      "time" : {
        "start" : 1647754720833,
        "stop" : 1647754720873,
        "duration" : 40
      }
    } ]
  },
  "c88b9e1406b592eee831601849d31189" : {
    "statistic" : {
      "failed" : 0,
      "broken" : 0,
      "skipped" : 0,
      "passed" : 1,
      "unknown" : 0,
      "total" : 1
    },
    "items" : [ {
      "uid" : "62eeaed1dc98401c",
      "reportUrl" : "https://MohabMohie.github.io/SHAFT_ENGINE/allure/Linux/Web/1243//#testresult/62eeaed1dc98401c",
      "status" : "passed",
      "time" : {
        "start" : 1647754552497,
        "stop" : 1647754578377,
        "duration" : 25880
      }
    } ]
  },
  "5702a1676b94e58bea6b43247a9f5f63" : {
    "statistic" : {
      "failed" : 0,
      "broken" : 0,
      "skipped" : 0,
      "passed" : 1,
      "unknown" : 0,
      "total" : 1
    },
    "items" : [ {
      "uid" : "d9eaf6da44cf8c3d",
      "reportUrl" : "https://MohabMohie.github.io/SHAFT_ENGINE/allure/Linux/Web/1243//#testresult/d9eaf6da44cf8c3d",
      "status" : "passed",
      "time" : {
        "start" : 1647754520989,
        "stop" : 1647754523828,
        "duration" : 2839
      }
    } ]
  },
  "264074a39b89752d2d36dd84bd40d1a6" : {
    "statistic" : {
      "failed" : 0,
      "broken" : 0,
      "skipped" : 0,
      "passed" : 1,
      "unknown" : 0,
      "total" : 1
    },
    "items" : [ {
      "uid" : "b2165d6cd3e992ed",
      "reportUrl" : "https://MohabMohie.github.io/SHAFT_ENGINE/allure/Linux/Web/1243//#testresult/b2165d6cd3e992ed",
      "status" : "passed",
      "time" : {
        "start" : 1647754771800,
        "stop" : 1647754773113,
        "duration" : 1313
      }
    } ]
  },
  "476ac2975115e742d5e5e8c3b57ebdf4" : {
    "statistic" : {
      "failed" : 0,
      "broken" : 0,
      "skipped" : 0,
      "passed" : 1,
      "unknown" : 0,
      "total" : 1
    },
    "items" : [ {
      "uid" : "6fd49e9b991907de",
      "reportUrl" : "https://MohabMohie.github.io/SHAFT_ENGINE/allure/Linux/Web/1243//#testresult/6fd49e9b991907de",
      "status" : "passed",
      "time" : {
        "start" : 1647754724243,
        "stop" : 1647754724315,
        "duration" : 72
      }
    } ]
  },
  "bb7188203f90a1a2fad67230270ae7d6" : {
    "statistic" : {
      "failed" : 0,
      "broken" : 0,
      "skipped" : 0,
      "passed" : 1,
      "unknown" : 0,
      "total" : 1
    },
    "items" : [ {
      "uid" : "5218df8cc90cc54b",
      "reportUrl" : "https://MohabMohie.github.io/SHAFT_ENGINE/allure/Linux/Web/1243//#testresult/5218df8cc90cc54b",
      "status" : "passed",
      "time" : {
        "start" : 1647754372066,
        "stop" : 1647754375730,
        "duration" : 3664
      }
    } ]
  },
  "1691af37f7c9ae9ee1c9cd54fed41695" : {
    "statistic" : {
      "failed" : 0,
      "broken" : 0,
      "skipped" : 0,
      "passed" : 1,
      "unknown" : 0,
      "total" : 1
    },
    "items" : [ {
      "uid" : "dcff786ee8ffab3c",
      "reportUrl" : "https://MohabMohie.github.io/SHAFT_ENGINE/allure/Linux/Web/1243//#testresult/dcff786ee8ffab3c",
      "status" : "passed",
      "time" : {
        "start" : 1647754615828,
        "stop" : 1647754615829,
        "duration" : 1
      }
    } ]
  },
  "2665e846a50930cc0c074f7f99a4ca8a" : {
    "statistic" : {
      "failed" : 0,
      "broken" : 0,
      "skipped" : 0,
      "passed" : 1,
      "unknown" : 0,
      "total" : 1
    },
    "items" : [ {
      "uid" : "16a1c5aa303df02a",
      "reportUrl" : "https://MohabMohie.github.io/SHAFT_ENGINE/allure/Linux/Web/1243//#testresult/16a1c5aa303df02a",
      "status" : "passed",
      "time" : {
        "start" : 1647754387582,
        "stop" : 1647754387630,
        "duration" : 48
      }
    } ]
  },
  "c86091caae292bffb9efd84314332710" : {
    "statistic" : {
      "failed" : 0,
      "broken" : 0,
      "skipped" : 0,
      "passed" : 1,
      "unknown" : 0,
      "total" : 1
    },
    "items" : [ {
      "uid" : "5195e91abdbeff9f",
      "reportUrl" : "https://MohabMohie.github.io/SHAFT_ENGINE/allure/Linux/Web/1243//#testresult/5195e91abdbeff9f",
      "status" : "passed",
      "time" : {
        "start" : 1647754615859,
        "stop" : 1647754615860,
        "duration" : 1
      }
    } ]
  },
  "317e6cef9e3891b5a07975bb25bc5fb2" : {
    "statistic" : {
      "failed" : 0,
      "broken" : 0,
      "skipped" : 0,
      "passed" : 1,
      "unknown" : 0,
      "total" : 1
    },
    "items" : [ {
      "uid" : "b79f86e868d8427d",
      "reportUrl" : "https://MohabMohie.github.io/SHAFT_ENGINE/allure/Linux/Web/1243//#testresult/b79f86e868d8427d",
      "status" : "passed",
      "time" : {
        "start" : 1647754583468,
        "stop" : 1647754583469,
        "duration" : 1
      }
    } ]
  },
  "ac6789217d4b4a32d112e105cd2efa1f" : {
    "statistic" : {
      "failed" : 0,
      "broken" : 0,
      "skipped" : 0,
      "passed" : 1,
      "unknown" : 0,
      "total" : 1
    },
    "items" : [ {
      "uid" : "fb5de139bf97a7b",
      "reportUrl" : "https://MohabMohie.github.io/SHAFT_ENGINE/allure/Linux/Web/1243//#testresult/fb5de139bf97a7b",
      "status" : "passed",
      "time" : {
        "start" : 1647754792184,
        "stop" : 1647754793487,
        "duration" : 1303
      }
    } ]
  },
  "2a27a2abfdee42bde8e58c16a0e0f5dd" : {
    "statistic" : {
      "failed" : 0,
      "broken" : 0,
      "skipped" : 0,
      "passed" : 1,
      "unknown" : 0,
      "total" : 1
    },
    "items" : [ {
      "uid" : "cd62cc9698b37f84",
      "reportUrl" : "https://MohabMohie.github.io/SHAFT_ENGINE/allure/Linux/Web/1243//#testresult/cd62cc9698b37f84",
      "status" : "passed",
      "time" : {
        "start" : 1647754615847,
        "stop" : 1647754615848,
        "duration" : 1
      }
    } ]
  },
  "bef677b60015e2d35d5030f6c3bfcf99" : {
    "statistic" : {
      "failed" : 0,
      "broken" : 0,
      "skipped" : 0,
      "passed" : 1,
      "unknown" : 0,
      "total" : 1
    },
    "items" : [ {
      "uid" : "cfebd36c89c2016a",
      "reportUrl" : "https://MohabMohie.github.io/SHAFT_ENGINE/allure/Linux/Web/1243//#testresult/cfebd36c89c2016a",
      "status" : "passed",
      "time" : {
        "start" : 1647754860028,
        "stop" : 1647754860029,
        "duration" : 1
      }
    } ]
  },
  "8c403aaf85c1c2abafe0a9a5d008562b" : {
    "statistic" : {
      "failed" : 0,
      "broken" : 0,
      "skipped" : 0,
      "passed" : 1,
      "unknown" : 0,
      "total" : 1
    },
    "items" : [ {
      "uid" : "11fe2e945e2cd6a7",
      "reportUrl" : "https://MohabMohie.github.io/SHAFT_ENGINE/allure/Linux/Web/1243//#testresult/11fe2e945e2cd6a7",
      "status" : "passed",
      "time" : {
        "start" : 1647754437760,
        "stop" : 1647754440540,
        "duration" : 2780
      }
    } ]
  },
  "ada58dba4d4104022dc5d96f0cd4fe5" : {
    "statistic" : {
      "failed" : 0,
      "broken" : 0,
      "skipped" : 0,
      "passed" : 1,
      "unknown" : 0,
      "total" : 1
    },
    "items" : [ {
      "uid" : "19d6d5f955091a3b",
      "reportUrl" : "https://MohabMohie.github.io/SHAFT_ENGINE/allure/Linux/Web/1243//#testresult/19d6d5f955091a3b",
      "status" : "passed",
      "time" : {
        "start" : 1647754861064,
        "stop" : 1647754863639,
        "duration" : 2575
      }
    } ]
  },
  "dc2cc42de249444fb1e5a25eaca827d0" : {
    "statistic" : {
      "failed" : 0,
      "broken" : 0,
      "skipped" : 0,
      "passed" : 1,
      "unknown" : 0,
      "total" : 1
    },
    "items" : [ {
      "uid" : "f73b5a37e1914c4b",
      "reportUrl" : "https://MohabMohie.github.io/SHAFT_ENGINE/allure/Linux/Web/1243//#testresult/f73b5a37e1914c4b",
      "status" : "passed",
      "time" : {
        "start" : 1647754617410,
        "stop" : 1647754618064,
        "duration" : 654
      }
    } ]
  },
  "1ef8e17d688014fbe6390ba22408aa7b" : {
    "statistic" : {
      "failed" : 0,
      "broken" : 0,
      "skipped" : 0,
      "passed" : 1,
      "unknown" : 0,
      "total" : 1
    },
    "items" : [ {
      "uid" : "c136943ea76ef9e1",
      "reportUrl" : "https://MohabMohie.github.io/SHAFT_ENGINE/allure/Linux/Web/1243//#testresult/c136943ea76ef9e1",
      "status" : "passed",
      "time" : {
        "start" : 1647754794991,
        "stop" : 1647754796363,
        "duration" : 1372
      }
    } ]
  },
  "eb4868839e997e5aed90ae6a95488276" : {
    "statistic" : {
      "failed" : 0,
      "broken" : 0,
      "skipped" : 0,
      "passed" : 1,
      "unknown" : 0,
      "total" : 1
    },
    "items" : [ {
      "uid" : "21f82bf0131a30ee",
      "reportUrl" : "https://MohabMohie.github.io/SHAFT_ENGINE/allure/Linux/Web/1243//#testresult/21f82bf0131a30ee",
      "status" : "passed",
      "time" : {
        "start" : 1647754757241,
        "stop" : 1647754758500,
        "duration" : 1259
      }
    } ]
  },
  "2935f6195ae2ad2b57e1bc1f5cb3a205" : {
    "statistic" : {
      "failed" : 1,
      "broken" : 0,
      "skipped" : 0,
      "passed" : 0,
      "unknown" : 0,
      "total" : 1
    },
    "items" : [ {
      "uid" : "cf5b6ba7707c6434",
      "reportUrl" : "https://MohabMohie.github.io/SHAFT_ENGINE/allure/Linux/Web/1243//#testresult/cf5b6ba7707c6434",
      "status" : "failed",
      "statusDetails" : "Element Action [Click] failed.",
      "time" : {
        "start" : 1647754398907,
        "stop" : 1647754403712,
        "duration" : 4805
      }
    } ]
  },
  "e8b8340fde60dd2f177bd721ae597277" : {
    "statistic" : {
      "failed" : 0,
      "broken" : 0,
      "skipped" : 0,
      "passed" : 1,
      "unknown" : 0,
      "total" : 1
    },
    "items" : [ {
      "uid" : "de08c598a87fc1e7",
      "reportUrl" : "https://MohabMohie.github.io/SHAFT_ENGINE/allure/Linux/Web/1243//#testresult/de08c598a87fc1e7",
      "status" : "passed",
      "time" : {
        "start" : 1647754694970,
        "stop" : 1647754696535,
        "duration" : 1565
      }
    } ]
  },
  "8d1d2653d45ddc1144dd8fa258b167c2" : {
    "statistic" : {
      "failed" : 0,
      "broken" : 0,
      "skipped" : 0,
      "passed" : 1,
      "unknown" : 0,
      "total" : 1
    },
    "items" : [ {
      "uid" : "fb7bf825517e3dfa",
      "reportUrl" : "https://MohabMohie.github.io/SHAFT_ENGINE/allure/Linux/Web/1243//#testresult/fb7bf825517e3dfa",
      "status" : "passed",
      "time" : {
        "start" : 1647754797856,
        "stop" : 1647754808497,
        "duration" : 10641
      }
    } ]
  },
  "a7e9d82b8312bf54112ba6b33d3a8577" : {
    "statistic" : {
      "failed" : 0,
      "broken" : 0,
      "skipped" : 0,
      "passed" : 1,
      "unknown" : 0,
      "total" : 1
    },
    "items" : [ {
      "uid" : "3804034a03e09f6c",
      "reportUrl" : "https://MohabMohie.github.io/SHAFT_ENGINE/allure/Linux/Web/1243//#testresult/3804034a03e09f6c",
      "status" : "passed",
      "time" : {
        "start" : 1647754615837,
        "stop" : 1647754615838,
        "duration" : 1
      }
    } ]
  },
  "bdef01ca6cf8bbcc16448d374eaad143" : {
    "statistic" : {
      "failed" : 0,
      "broken" : 0,
      "skipped" : 0,
      "passed" : 1,
      "unknown" : 0,
      "total" : 1
    },
    "items" : [ {
      "uid" : "c9a26aed1b235ab",
      "reportUrl" : "https://MohabMohie.github.io/SHAFT_ENGINE/allure/Linux/Web/1243//#testresult/c9a26aed1b235ab",
      "status" : "passed",
      "time" : {
        "start" : 1647754615865,
        "stop" : 1647754615872,
        "duration" : 7
      }
    } ]
  },
  "7a5a0716c213c4b3784adbf28353af84" : {
    "statistic" : {
      "failed" : 0,
      "broken" : 0,
      "skipped" : 0,
      "passed" : 1,
      "unknown" : 0,
      "total" : 1
    },
    "items" : [ {
      "uid" : "22bc0fc0b44c9b24",
      "reportUrl" : "https://MohabMohie.github.io/SHAFT_ENGINE/allure/Linux/Web/1243//#testresult/22bc0fc0b44c9b24",
      "status" : "passed",
      "time" : {
        "start" : 1647754734690,
        "stop" : 1647754737482,
        "duration" : 2792
      }
    } ]
  },
  "f031b53e9f7c0028d5e3acbdc1200881" : {
    "statistic" : {
      "failed" : 0,
      "broken" : 0,
      "skipped" : 0,
      "passed" : 1,
      "unknown" : 0,
      "total" : 1
    },
    "items" : [ {
      "uid" : "513adaa79a305e44",
      "reportUrl" : "https://MohabMohie.github.io/SHAFT_ENGINE/allure/Linux/Web/1243//#testresult/513adaa79a305e44",
      "status" : "passed",
      "time" : {
        "start" : 1647754411494,
        "stop" : 1647754419001,
        "duration" : 7507
      }
    } ]
  },
  "50a7bbf2e6e4c20e0204965d4abee130" : {
    "statistic" : {
      "failed" : 0,
      "broken" : 0,
      "skipped" : 0,
      "passed" : 1,
      "unknown" : 0,
      "total" : 1
    },
    "items" : [ {
      "uid" : "37a51823a57b6345",
      "reportUrl" : "https://MohabMohie.github.io/SHAFT_ENGINE/allure/Linux/Web/1243//#testresult/37a51823a57b6345",
      "status" : "passed",
      "time" : {
        "start" : 1647754754527,
        "stop" : 1647754755721,
        "duration" : 1194
      }
    } ]
  },
  "b9150818268b7ec2c8e5485db15d9400" : {
    "statistic" : {
      "failed" : 0,
      "broken" : 0,
      "skipped" : 0,
      "passed" : 1,
      "unknown" : 0,
      "total" : 1
    },
    "items" : [ {
      "uid" : "e9bbf524e7d619e0",
      "reportUrl" : "https://MohabMohie.github.io/SHAFT_ENGINE/allure/Linux/Web/1243//#testresult/e9bbf524e7d619e0",
      "status" : "passed",
      "time" : {
        "start" : 1647754747447,
        "stop" : 1647754747448,
        "duration" : 1
      }
    } ]
  },
  "f7635885016b46463315d3b46906bf7a" : {
    "statistic" : {
      "failed" : 0,
      "broken" : 0,
      "skipped" : 0,
      "passed" : 1,
      "unknown" : 0,
      "total" : 1
    },
    "items" : [ {
      "uid" : "d874509596ddce67",
      "reportUrl" : "https://MohabMohie.github.io/SHAFT_ENGINE/allure/Linux/Web/1243//#testresult/d874509596ddce67",
      "status" : "passed",
      "time" : {
        "start" : 1647754861055,
        "stop" : 1647754861056,
        "duration" : 1
      }
    } ]
  },
  "badd6454e3076c44a673a71b57708fe0" : {
    "statistic" : {
      "failed" : 0,
      "broken" : 0,
      "skipped" : 0,
      "passed" : 1,
      "unknown" : 0,
      "total" : 1
    },
    "items" : [ {
      "uid" : "45712a4b81a5ae7e",
      "reportUrl" : "https://MohabMohie.github.io/SHAFT_ENGINE/allure/Linux/Web/1243//#testresult/45712a4b81a5ae7e",
      "status" : "passed",
      "time" : {
        "start" : 1647754509254,
        "stop" : 1647754512421,
        "duration" : 3167
      }
    } ]
  },
  "45dcfe76f1bd97f7cb03c724bcc68eb8" : {
    "statistic" : {
      "failed" : 0,
      "broken" : 0,
      "skipped" : 0,
      "passed" : 1,
      "unknown" : 0,
      "total" : 1
    },
    "items" : [ {
      "uid" : "82a977e6b87f05c4",
      "reportUrl" : "https://MohabMohie.github.io/SHAFT_ENGINE/allure/Linux/Web/1243//#testresult/82a977e6b87f05c4",
      "status" : "passed",
      "time" : {
        "start" : 1647754861057,
        "stop" : 1647754861058,
        "duration" : 1
      }
    } ]
  },
  "9829372d1b547228b4f16b7901ea9cc9" : {
    "statistic" : {
      "failed" : 0,
      "broken" : 0,
      "skipped" : 0,
      "passed" : 1,
      "unknown" : 0,
      "total" : 1
    },
    "items" : [ {
      "uid" : "4d50808681cda168",
      "reportUrl" : "https://MohabMohie.github.io/SHAFT_ENGINE/allure/Linux/Web/1243//#testresult/4d50808681cda168",
      "status" : "passed",
      "time" : {
        "start" : 1647754526306,
        "stop" : 1647754526344,
        "duration" : 38
      }
    } ]
  },
  "a56697260ac1ade7b44ceede44b0438a" : {
    "statistic" : {
      "failed" : 0,
      "broken" : 0,
      "skipped" : 0,
      "passed" : 1,
      "unknown" : 0,
      "total" : 1
    },
    "items" : [ {
      "uid" : "c30e2c1141c142d2",
      "reportUrl" : "https://MohabMohie.github.io/SHAFT_ENGINE/allure/Linux/Web/1243//#testresult/c30e2c1141c142d2",
      "status" : "passed",
      "time" : {
        "start" : 1647754615853,
        "stop" : 1647754615854,
        "duration" : 1
      }
    } ]
  },
  "7b01ba3878dc2dba2c2c7f95381cb742" : {
    "statistic" : {
      "failed" : 0,
      "broken" : 0,
      "skipped" : 0,
      "passed" : 1,
      "unknown" : 0,
      "total" : 1
    },
    "items" : [ {
      "uid" : "24bcddb2ae6052cc",
      "reportUrl" : "https://MohabMohie.github.io/SHAFT_ENGINE/allure/Linux/Web/1243//#testresult/24bcddb2ae6052cc",
      "status" : "passed",
      "time" : {
        "start" : 1647754544935,
        "stop" : 1647754545551,
        "duration" : 616
      }
    } ]
  },
  "5cf45cc810e8dfc458ef474e637734f6" : {
    "statistic" : {
      "failed" : 0,
      "broken" : 0,
      "skipped" : 0,
      "passed" : 1,
      "unknown" : 0,
      "total" : 1
    },
    "items" : [ {
      "uid" : "dfffd272024fcd48",
      "reportUrl" : "https://MohabMohie.github.io/SHAFT_ENGINE/allure/Linux/Web/1243//#testresult/dfffd272024fcd48",
      "status" : "passed",
      "time" : {
        "start" : 1647754751776,
        "stop" : 1647754753014,
        "duration" : 1238
      }
    } ]
  },
  "4f509b7f8127a2b88f6b1a2dc70a2a2d" : {
    "statistic" : {
      "failed" : 0,
      "broken" : 0,
      "skipped" : 0,
      "passed" : 1,
      "unknown" : 0,
      "total" : 1
    },
    "items" : [ {
      "uid" : "e80919974411965d",
      "reportUrl" : "https://MohabMohie.github.io/SHAFT_ENGINE/allure/Linux/Web/1243//#testresult/e80919974411965d",
      "status" : "passed",
      "time" : {
        "start" : 1647754524644,
        "stop" : 1647754526294,
        "duration" : 1650
      }
    } ]
  },
  "265ede85dd354b1c18327880ee92510d" : {
    "statistic" : {
      "failed" : 0,
      "broken" : 0,
      "skipped" : 0,
      "passed" : 1,
      "unknown" : 0,
      "total" : 1
    },
    "items" : [ {
      "uid" : "e57d996fb5137b82",
      "reportUrl" : "https://MohabMohie.github.io/SHAFT_ENGINE/allure/Linux/Web/1243//#testresult/e57d996fb5137b82",
      "status" : "passed",
      "time" : {
        "start" : 1647754696974,
        "stop" : 1647754703200,
        "duration" : 6226
      }
    } ]
  },
  "e167cb0f0b9e165fa2d11a66959b8c90" : {
    "statistic" : {
      "failed" : 0,
      "broken" : 0,
      "skipped" : 0,
      "passed" : 1,
      "unknown" : 0,
      "total" : 1
    },
    "items" : [ {
      "uid" : "9e8d0f1d89e29ddd",
      "reportUrl" : "https://MohabMohie.github.io/SHAFT_ENGINE/allure/Linux/Web/1243//#testresult/9e8d0f1d89e29ddd",
      "status" : "passed",
      "time" : {
        "start" : 1647754524036,
        "stop" : 1647754524639,
        "duration" : 603
      }
    } ]
  },
  "780378a4706344e151b2791aff941970" : {
    "statistic" : {
      "failed" : 0,
      "broken" : 0,
      "skipped" : 0,
      "passed" : 1,
      "unknown" : 0,
      "total" : 1
    },
    "items" : [ {
      "uid" : "5161e6a737b70379",
      "reportUrl" : "https://MohabMohie.github.io/SHAFT_ENGINE/allure/Linux/Web/1243//#testresult/5161e6a737b70379",
      "status" : "passed",
      "time" : {
        "start" : 1647754512607,
        "stop" : 1647754512608,
        "duration" : 1
      }
    } ]
  },
  "b59581a81571dbdc3929ef903c9a68af" : {
    "statistic" : {
      "failed" : 0,
      "broken" : 0,
      "skipped" : 0,
      "passed" : 1,
      "unknown" : 0,
      "total" : 1
    },
    "items" : [ {
      "uid" : "b407b4f45201cb84",
      "reportUrl" : "https://MohabMohie.github.io/SHAFT_ENGINE/allure/Linux/Web/1243//#testresult/b407b4f45201cb84",
      "status" : "passed",
      "time" : {
        "start" : 1647754654338,
        "stop" : 1647754655000,
        "duration" : 662
      }
    } ]
  },
  "6bfdcb3e2066e47f76cdc938949ea3b5" : {
    "statistic" : {
      "failed" : 0,
      "broken" : 0,
      "skipped" : 0,
      "passed" : 1,
      "unknown" : 0,
      "total" : 1
    },
    "items" : [ {
      "uid" : "10252aef2882661a",
      "reportUrl" : "https://MohabMohie.github.io/SHAFT_ENGINE/allure/Linux/Web/1243//#testresult/10252aef2882661a",
      "status" : "passed",
      "time" : {
        "start" : 1647754747454,
        "stop" : 1647754747455,
        "duration" : 1
      }
    } ]
  },
  "9c719c977867ad678cba36ac5ef0566e" : {
    "statistic" : {
      "failed" : 0,
      "broken" : 0,
      "skipped" : 0,
      "passed" : 1,
      "unknown" : 0,
      "total" : 1
    },
    "items" : [ {
      "uid" : "4fb02d328d516098",
      "reportUrl" : "https://MohabMohie.github.io/SHAFT_ENGINE/allure/Linux/Web/1243//#testresult/4fb02d328d516098",
      "status" : "passed",
      "time" : {
        "start" : 1647754380092,
        "stop" : 1647754384158,
        "duration" : 4066
      }
    } ]
  },
  "f2d8045cb196fac44acf056daf2910f1" : {
    "statistic" : {
      "failed" : 0,
      "broken" : 0,
      "skipped" : 0,
      "passed" : 1,
      "unknown" : 0,
      "total" : 1
    },
    "items" : [ {
      "uid" : "1680510c6cd92c5e",
      "reportUrl" : "https://MohabMohie.github.io/SHAFT_ENGINE/allure/Linux/Web/1243//#testresult/1680510c6cd92c5e",
      "status" : "passed",
      "time" : {
        "start" : 1647754860026,
        "stop" : 1647754860027,
        "duration" : 1
      }
    } ]
  },
  "8da2170c533f4aff45bc62dac6da1bf8" : {
    "statistic" : {
      "failed" : 0,
      "broken" : 0,
      "skipped" : 1,
      "passed" : 0,
      "unknown" : 0,
      "total" : 1
    },
    "items" : [ {
      "uid" : "4944d4586d80a721",
      "reportUrl" : "https://MohabMohie.github.io/SHAFT_ENGINE/allure/Linux/Web/1243//#testresult/4944d4586d80a721",
      "status" : "skipped",
      "statusDetails" : "Method testPackage01.TestJSPromptBox.assertOnConfirmPromptAlertWithoutTypingTextMessageResultText() on instance testPackage01.TestJSPromptBox@290d10ef depends on not successfully finished methods \n[testPackage01.TestJSPromptBox.acceptPromptAlertWithoutTypingTextMessage() on instance testPackage01.TestJSPromptBox@290d10ef]",
      "time" : {
        "start" : 1647754508700,
        "stop" : 1647754508709,
        "duration" : 9
      }
    } ]
  },
  "69bacfe7d32090425eadf00e77ec2fcd" : {
    "statistic" : {
      "failed" : 0,
      "broken" : 0,
      "skipped" : 0,
      "passed" : 1,
      "unknown" : 0,
      "total" : 1
    },
    "items" : [ {
      "uid" : "b8b3c2551442015c",
      "reportUrl" : "https://MohabMohie.github.io/SHAFT_ENGINE/allure/Linux/Web/1243//#testresult/b8b3c2551442015c",
      "status" : "passed",
      "time" : {
        "start" : 1647754615034,
        "stop" : 1647754615709,
        "duration" : 675
      }
    } ]
  },
  "19a9da5f20787f6a62b7cf5efdc0b4e3" : {
    "statistic" : {
      "failed" : 0,
      "broken" : 0,
      "skipped" : 0,
      "passed" : 1,
      "unknown" : 0,
      "total" : 1
    },
    "items" : [ {
      "uid" : "b4d28fce2ccf5198",
      "reportUrl" : "https://MohabMohie.github.io/SHAFT_ENGINE/allure/Linux/Web/1243//#testresult/b4d28fce2ccf5198",
      "status" : "passed",
      "time" : {
        "start" : 1647754780431,
        "stop" : 1647754781664,
        "duration" : 1233
      }
    } ]
  },
  "60da75bce66f0a062056dcf68a93a62e" : {
    "statistic" : {
      "failed" : 0,
      "broken" : 0,
      "skipped" : 0,
      "passed" : 1,
      "unknown" : 0,
      "total" : 1
    },
    "items" : [ {
      "uid" : "bb2701a0588212d4",
      "reportUrl" : "https://MohabMohie.github.io/SHAFT_ENGINE/allure/Linux/Web/1243//#testresult/bb2701a0588212d4",
      "status" : "passed",
      "time" : {
        "start" : 1647754376300,
        "stop" : 1647754379494,
        "duration" : 3194
      }
    } ]
  },
  "4864018d69af2693dbef3cc79f4b7427" : {
    "statistic" : {
      "failed" : 0,
      "broken" : 0,
      "skipped" : 0,
      "passed" : 1,
      "unknown" : 0,
      "total" : 1
    },
    "items" : [ {
      "uid" : "49f2fae889bf13c9",
      "reportUrl" : "https://MohabMohie.github.io/SHAFT_ENGINE/allure/Linux/Web/1243//#testresult/49f2fae889bf13c9",
      "status" : "passed",
      "time" : {
        "start" : 1647754386470,
        "stop" : 1647754386485,
        "duration" : 15
      }
    } ]
  },
  "4417a672ef985b4faf9285ce39f0cc10" : {
    "statistic" : {
      "failed" : 0,
      "broken" : 0,
      "skipped" : 0,
      "passed" : 1,
      "unknown" : 0,
      "total" : 1
    },
    "items" : [ {
      "uid" : "d8a7be1404d93cea",
      "reportUrl" : "https://MohabMohie.github.io/SHAFT_ENGINE/allure/Linux/Web/1243//#testresult/d8a7be1404d93cea",
      "status" : "passed",
      "time" : {
        "start" : 1647754703568,
        "stop" : 1647754705181,
        "duration" : 1613
      }
    } ]
  },
  "83e3cd745c904b39ba98498d793686ca" : {
    "statistic" : {
      "failed" : 0,
      "broken" : 0,
      "skipped" : 0,
      "passed" : 1,
      "unknown" : 0,
      "total" : 1
    },
    "items" : [ {
      "uid" : "b50c4fa5eea25dac",
      "reportUrl" : "https://MohabMohie.github.io/SHAFT_ENGINE/allure/Linux/Web/1243//#testresult/b50c4fa5eea25dac",
      "status" : "passed",
      "time" : {
        "start" : 1647754395235,
        "stop" : 1647754398445,
        "duration" : 3210
      }
    } ]
  },
  "f18d7d9f5bd5a5538a7079ad2eaa14f" : {
    "statistic" : {
      "failed" : 0,
      "broken" : 0,
      "skipped" : 0,
      "passed" : 1,
      "unknown" : 0,
      "total" : 1
    },
    "items" : [ {
      "uid" : "14cabaf7e044e52f",
      "reportUrl" : "https://MohabMohie.github.io/SHAFT_ENGINE/allure/Linux/Web/1243//#testresult/14cabaf7e044e52f",
      "status" : "passed",
      "time" : {
        "start" : 1647754615883,
        "stop" : 1647754615884,
        "duration" : 1
      }
    } ]
  },
  "7701a929ba556c35243f11ba7bc07226" : {
    "statistic" : {
      "failed" : 0,
      "broken" : 0,
      "skipped" : 0,
      "passed" : 1,
      "unknown" : 0,
      "total" : 1
    },
    "items" : [ {
      "uid" : "d5614e3402614270",
      "reportUrl" : "https://MohabMohie.github.io/SHAFT_ENGINE/allure/Linux/Web/1243//#testresult/d5614e3402614270",
      "status" : "passed",
      "time" : {
        "start" : 1647754747471,
        "stop" : 1647754747472,
        "duration" : 1
      }
    } ]
  },
  "402cf2e9c00429e23b6068d754dd4dbe" : {
    "statistic" : {
      "failed" : 0,
      "broken" : 0,
      "skipped" : 0,
      "passed" : 1,
      "unknown" : 0,
      "total" : 1
    },
    "items" : [ {
      "uid" : "ca7e41c5abfea8f5",
      "reportUrl" : "https://MohabMohie.github.io/SHAFT_ENGINE/allure/Linux/Web/1243//#testresult/ca7e41c5abfea8f5",
      "status" : "passed",
      "time" : {
        "start" : 1647754824492,
        "stop" : 1647754855453,
        "duration" : 30961
      }
    } ]
  },
  "9ea97b85f51a64632f0eccbb9a2eca3e" : {
    "statistic" : {
      "failed" : 0,
      "broken" : 0,
      "skipped" : 0,
      "passed" : 1,
      "unknown" : 0,
      "total" : 1
    },
    "items" : [ {
      "uid" : "c9b6f9ad7337e883",
      "reportUrl" : "https://MohabMohie.github.io/SHAFT_ENGINE/allure/Linux/Web/1243//#testresult/c9b6f9ad7337e883",
      "status" : "passed",
      "time" : {
        "start" : 1647754860012,
        "stop" : 1647754860013,
        "duration" : 1
      }
    } ]
  },
  "ee987874b5afbcff3eca43bdb5081291" : {
    "statistic" : {
      "failed" : 0,
      "broken" : 0,
      "skipped" : 0,
      "passed" : 1,
      "unknown" : 0,
      "total" : 1
    },
    "items" : [ {
      "uid" : "c44692c38efd3839",
      "reportUrl" : "https://MohabMohie.github.io/SHAFT_ENGINE/allure/Linux/Web/1243//#testresult/c44692c38efd3839",
      "status" : "passed",
      "time" : {
        "start" : 1647754789295,
        "stop" : 1647754790646,
        "duration" : 1351
      }
    } ]
  },
  "c6d3ce9689e0c5467257ac5580affbdc" : {
    "statistic" : {
      "failed" : 0,
      "broken" : 0,
      "skipped" : 0,
      "passed" : 1,
      "unknown" : 0,
      "total" : 1
    },
    "items" : [ {
      "uid" : "f13c05c6713958de",
      "reportUrl" : "https://MohabMohie.github.io/SHAFT_ENGINE/allure/Linux/Web/1243//#testresult/f13c05c6713958de",
      "status" : "passed",
      "time" : {
        "start" : 1647754748893,
        "stop" : 1647754750208,
        "duration" : 1315
      }
    } ]
  },
  "e88a34f039ffaa5a3e7ec815fbf7e0ee" : {
    "statistic" : {
      "failed" : 0,
      "broken" : 0,
      "skipped" : 0,
      "passed" : 1,
      "unknown" : 0,
      "total" : 1
    },
    "items" : [ {
      "uid" : "531fdda6c8ce4dd6",
      "reportUrl" : "https://MohabMohie.github.io/SHAFT_ENGINE/allure/Linux/Web/1243//#testresult/531fdda6c8ce4dd6",
      "status" : "passed",
      "time" : {
        "start" : 1647754860009,
        "stop" : 1647754860011,
        "duration" : 2
      }
    } ]
  },
  "1e302c49c8f75fa918eb46dd6bc40b87" : {
    "statistic" : {
      "failed" : 0,
      "broken" : 0,
      "skipped" : 0,
      "passed" : 1,
      "unknown" : 0,
      "total" : 1
    },
    "items" : [ {
      "uid" : "6151fa70e3824c29",
      "reportUrl" : "https://MohabMohie.github.io/SHAFT_ENGINE/allure/Linux/Web/1243//#testresult/6151fa70e3824c29",
      "status" : "passed",
      "time" : {
        "start" : 1647754725980,
        "stop" : 1647754726013,
        "duration" : 33
      }
    } ]
  },
  "d5d715b3d739d9e30ec0c208231a5b19" : {
    "statistic" : {
      "failed" : 0,
      "broken" : 0,
      "skipped" : 0,
      "passed" : 1,
      "unknown" : 0,
      "total" : 1
    },
    "items" : [ {
      "uid" : "a1dbfa2666a763c1",
      "reportUrl" : "https://MohabMohie.github.io/SHAFT_ENGINE/allure/Linux/Web/1243//#testresult/a1dbfa2666a763c1",
      "status" : "passed",
      "time" : {
        "start" : 1647754527941,
        "stop" : 1647754528711,
        "duration" : 770
      }
    } ]
  },
  "2b4beb423f2d0918a09c19ca2ce5f015" : {
    "statistic" : {
      "failed" : 0,
      "broken" : 0,
      "skipped" : 0,
      "passed" : 1,
      "unknown" : 0,
      "total" : 1
    },
    "items" : [ {
      "uid" : "e70fda51b2368570",
      "reportUrl" : "https://MohabMohie.github.io/SHAFT_ENGINE/allure/Linux/Web/1243//#testresult/e70fda51b2368570",
      "status" : "passed",
      "time" : {
        "start" : 1647754435031,
        "stop" : 1647754437757,
        "duration" : 2726
      }
    } ]
  },
  "a4a3705aa0579b42a1b50218e2c54e00" : {
    "statistic" : {
      "failed" : 0,
      "broken" : 0,
      "skipped" : 0,
      "passed" : 1,
      "unknown" : 0,
      "total" : 1
    },
    "items" : [ {
      "uid" : "e07f8d66426f1666",
      "reportUrl" : "https://MohabMohie.github.io/SHAFT_ENGINE/allure/Linux/Web/1243//#testresult/e07f8d66426f1666",
      "status" : "passed",
      "time" : {
        "start" : 1647754393615,
        "stop" : 1647754394670,
        "duration" : 1055
      }
    } ]
  },
  "c8c76336a37556799805a49b42d957dc" : {
    "statistic" : {
      "failed" : 0,
      "broken" : 0,
      "skipped" : 0,
      "passed" : 1,
      "unknown" : 0,
      "total" : 1
    },
    "items" : [ {
      "uid" : "c3659bbf505384ae",
      "reportUrl" : "https://MohabMohie.github.io/SHAFT_ENGINE/allure/Linux/Web/1243//#testresult/c3659bbf505384ae",
      "status" : "passed",
      "time" : {
        "start" : 1647754859176,
        "stop" : 1647754859828,
        "duration" : 652
      }
    } ]
  },
  "f4e42247564f9e406ac4c030f5657555" : {
    "statistic" : {
      "failed" : 0,
      "broken" : 0,
      "skipped" : 0,
      "passed" : 1,
      "unknown" : 0,
      "total" : 1
    },
    "items" : [ {
      "uid" : "fa194774d02e14eb",
      "reportUrl" : "https://MohabMohie.github.io/SHAFT_ENGINE/allure/Linux/Web/1243//#testresult/fa194774d02e14eb",
      "status" : "passed",
      "time" : {
        "start" : 1647754861050,
        "stop" : 1647754861051,
        "duration" : 1
      }
    } ]
  },
  "b4d9a91b46088e954c06abadd0ea633f" : {
    "statistic" : {
      "failed" : 0,
      "broken" : 0,
      "skipped" : 0,
      "passed" : 1,
      "unknown" : 0,
      "total" : 1
    },
    "items" : [ {
      "uid" : "a63233cdd9cae595",
      "reportUrl" : "https://MohabMohie.github.io/SHAFT_ENGINE/allure/Linux/Web/1243//#testresult/a63233cdd9cae595",
      "status" : "passed",
      "time" : {
        "start" : 1647754766142,
        "stop" : 1647754767459,
        "duration" : 1317
      }
    } ]
  },
  "dbc6fbdd3600eccd40842e7fc2a996b7" : {
    "statistic" : {
      "failed" : 0,
      "broken" : 0,
      "skipped" : 0,
      "passed" : 1,
      "unknown" : 0,
      "total" : 1
    },
    "items" : [ {
      "uid" : "5cd12efcf752aef3",
      "reportUrl" : "https://MohabMohie.github.io/SHAFT_ENGINE/allure/Linux/Web/1243//#testresult/5cd12efcf752aef3",
      "status" : "passed",
      "time" : {
        "start" : 1647754717012,
        "stop" : 1647754717325,
        "duration" : 313
      }
    } ]
  },
  "171d46d4135b76235154b42b11cb9d6f" : {
    "statistic" : {
      "failed" : 0,
      "broken" : 0,
      "skipped" : 0,
      "passed" : 1,
      "unknown" : 0,
      "total" : 1
    },
    "items" : [ {
      "uid" : "2c619007374169ce",
      "reportUrl" : "https://MohabMohie.github.io/SHAFT_ENGINE/allure/Linux/Web/1243//#testresult/2c619007374169ce",
      "status" : "passed",
      "time" : {
        "start" : 1647754768996,
        "stop" : 1647754770250,
        "duration" : 1254
      }
    } ]
  },
  "f5f5d884f40a700315cef26011f085c6" : {
    "statistic" : {
      "failed" : 0,
      "broken" : 0,
      "skipped" : 0,
      "passed" : 1,
      "unknown" : 0,
      "total" : 1
    },
    "items" : [ {
      "uid" : "c4539c5849b470c5",
      "reportUrl" : "https://MohabMohie.github.io/SHAFT_ENGINE/allure/Linux/Web/1243//#testresult/c4539c5849b470c5",
      "status" : "passed",
      "time" : {
        "start" : 1647754440992,
        "stop" : 1647754441030,
        "duration" : 38
      }
    } ]
  },
  "18f634cf5b3568c85a21c57b6cffaa85" : {
    "statistic" : {
      "failed" : 0,
      "broken" : 0,
      "skipped" : 1,
      "passed" : 0,
      "unknown" : 0,
      "total" : 1
    },
    "items" : [ {
      "uid" : "8c1942e8532f3fbc",
      "reportUrl" : "https://MohabMohie.github.io/SHAFT_ENGINE/allure/Linux/Web/1243//#testresult/8c1942e8532f3fbc",
      "status" : "skipped",
      "statusDetails" : "Method testPackage01.TestJSPromptBox.assertOnConfirmPromptAlertWithTextMessageResultText() on instance testPackage01.TestJSPromptBox@290d10ef depends on not successfully finished methods \n[testPackage01.TestJSPromptBox.acceptPromptAlertWithTextMessage() on instance testPackage01.TestJSPromptBox@290d10ef]",
      "time" : {
        "start" : 1647754508730,
        "stop" : 1647754508746,
        "duration" : 16
      }
    } ]
  },
  "7b086c07a7672a87f96253ea13ac87a8" : {
    "statistic" : {
      "failed" : 0,
      "broken" : 0,
      "skipped" : 0,
      "passed" : 1,
      "unknown" : 0,
      "total" : 1
    },
    "items" : [ {
      "uid" : "caf713127005a8d7",
      "reportUrl" : "https://MohabMohie.github.io/SHAFT_ENGINE/allure/Linux/Web/1243//#testresult/caf713127005a8d7",
      "status" : "passed",
      "time" : {
        "start" : 1647754615862,
        "stop" : 1647754615864,
        "duration" : 2
      }
    } ]
  },
  "9136ef17ad732926a16ab8d92c6bf567" : {
    "statistic" : {
      "failed" : 0,
      "broken" : 0,
      "skipped" : 0,
      "passed" : 1,
      "unknown" : 0,
      "total" : 1
    },
    "items" : [ {
      "uid" : "9d16ae45f3e6e416",
      "reportUrl" : "https://MohabMohie.github.io/SHAFT_ENGINE/allure/Linux/Web/1243//#testresult/9d16ae45f3e6e416",
      "status" : "passed",
      "time" : {
        "start" : 1647754440543,
        "stop" : 1647754440912,
        "duration" : 369
      }
    } ]
  },
  "2502a22a0190a8d9d2d99a0b3742179f" : {
    "statistic" : {
      "failed" : 0,
      "broken" : 0,
      "skipped" : 0,
      "passed" : 1,
      "unknown" : 0,
      "total" : 1
    },
    "items" : [ {
      "uid" : "74de83c96f277199",
      "reportUrl" : "https://MohabMohie.github.io/SHAFT_ENGINE/allure/Linux/Web/1243//#testresult/74de83c96f277199",
      "status" : "passed",
      "time" : {
        "start" : 1647754615888,
        "stop" : 1647754615889,
        "duration" : 1
      }
    } ]
  },
  "9c149457b49558f6e51ed70eaa6cb83d" : {
    "statistic" : {
      "failed" : 1,
      "broken" : 0,
      "skipped" : 0,
      "passed" : 0,
      "unknown" : 0,
      "total" : 1
    },
    "items" : [ {
      "uid" : "ec64c18534125430",
      "reportUrl" : "https://MohabMohie.github.io/SHAFT_ENGINE/allure/Linux/Web/1243//#testresult/ec64c18534125430",
      "status" : "failed",
      "statusDetails" : "Assertion [ValidateBrowserAttribute] FAILED. Expected [Value Should be 'https://duckduckgo.com' for the 'CurrentUrl' attribute] and Actual [Failed to read the desired browser attribute]. Comparison Type [CONTAINS]. Validation Type [POSITIVE].",
      "time" : {
        "start" : 1647754731288,
        "stop" : 1647754732980,
        "duration" : 1692
      }
    } ]
  },
  "a927bad4489beeee1ac4665341bb128" : {
    "statistic" : {
      "failed" : 0,
      "broken" : 0,
      "skipped" : 0,
      "passed" : 1,
      "unknown" : 0,
      "total" : 1
    },
    "items" : [ {
      "uid" : "c1da7b508a490d55",
      "reportUrl" : "https://MohabMohie.github.io/SHAFT_ENGINE/allure/Linux/Web/1243//#testresult/c1da7b508a490d55",
      "status" : "passed",
      "time" : {
        "start" : 1647754615894,
        "stop" : 1647754615895,
        "duration" : 1
      }
    } ]
  },
  "9ee600c4564b8a84210f113c6a571e46" : {
    "statistic" : {
      "failed" : 1,
      "broken" : 0,
      "skipped" : 0,
      "passed" : 0,
      "unknown" : 0,
      "total" : 1
    },
    "items" : [ {
      "uid" : "3d61da577333dbf6",
      "reportUrl" : "https://MohabMohie.github.io/SHAFT_ENGINE/allure/Linux/Web/1243//#testresult/3d61da577333dbf6",
      "status" : "failed",
      "statusDetails" : "Element Action [WaitForAlertToBePresent] failed.",
      "time" : {
        "start" : 1647754664099,
        "stop" : 1647754694566,
        "duration" : 30467
      }
    } ]
  },
  "b166e1c1837e7780d7033eca80f4a9c7" : {
    "statistic" : {
      "failed" : 0,
      "broken" : 0,
      "skipped" : 0,
      "passed" : 1,
      "unknown" : 0,
      "total" : 1
    },
    "items" : [ {
      "uid" : "28ec6bf9df08c04",
      "reportUrl" : "https://MohabMohie.github.io/SHAFT_ENGINE/allure/Linux/Web/1243//#testresult/28ec6bf9df08c04",
      "status" : "passed",
      "time" : {
        "start" : 1647754615826,
        "stop" : 1647754615827,
        "duration" : 1
      }
    } ]
  },
  "f8f970faae1267b4b5c08b241d01d5ce" : {
    "statistic" : {
      "failed" : 0,
      "broken" : 0,
      "skipped" : 0,
      "passed" : 1,
      "unknown" : 0,
      "total" : 1
    },
    "items" : [ {
      "uid" : "3e94c64b3db5fead",
      "reportUrl" : "https://MohabMohie.github.io/SHAFT_ENGINE/allure/Linux/Web/1243//#testresult/3e94c64b3db5fead",
      "status" : "passed",
      "time" : {
        "start" : 1647754727663,
        "stop" : 1647754727715,
        "duration" : 52
      }
    } ]
  },
  "f8b181c41d9f9edf4c60d33877099af8" : {
    "statistic" : {
      "failed" : 0,
      "broken" : 0,
      "skipped" : 0,
      "passed" : 1,
      "unknown" : 0,
      "total" : 1
    },
    "items" : [ {
      "uid" : "cbe2423ca50b2771",
      "reportUrl" : "https://MohabMohie.github.io/SHAFT_ENGINE/allure/Linux/Web/1243//#testresult/cbe2423ca50b2771",
      "status" : "passed",
      "time" : {
        "start" : 1647754615823,
        "stop" : 1647754615824,
        "duration" : 1
      }
    } ]
  },
  "ac7fea32beee7e3033b84a4d116cf947" : {
    "statistic" : {
      "failed" : 0,
      "broken" : 0,
      "skipped" : 0,
      "passed" : 1,
      "unknown" : 0,
      "total" : 1
    },
    "items" : [ {
      "uid" : "45afa2b7f145049d",
      "reportUrl" : "https://MohabMohie.github.io/SHAFT_ENGINE/allure/Linux/Web/1243//#testresult/45afa2b7f145049d",
      "status" : "passed",
      "time" : {
        "start" : 1647754857039,
        "stop" : 1647754857650,
        "duration" : 611
      }
    } ]
  },
  "13bf298e1e204216e174902a46417745" : {
    "statistic" : {
      "failed" : 0,
      "broken" : 0,
      "skipped" : 0,
      "passed" : 1,
      "unknown" : 0,
      "total" : 1
    },
    "items" : [ {
      "uid" : "9af09188fe7723d2",
      "reportUrl" : "https://MohabMohie.github.io/SHAFT_ENGINE/allure/Linux/Web/1243//#testresult/9af09188fe7723d2",
      "status" : "passed",
      "time" : {
        "start" : 1647754512599,
        "stop" : 1647754512601,
        "duration" : 2
      }
    } ]
  },
  "8161aacdafcd0cb42d3204fe0672f36b" : {
    "statistic" : {
      "failed" : 0,
      "broken" : 0,
      "skipped" : 0,
      "passed" : 1,
      "unknown" : 0,
      "total" : 1
    },
    "items" : [ {
      "uid" : "a3e41f9652b637e4",
      "reportUrl" : "https://MohabMohie.github.io/SHAFT_ENGINE/allure/Linux/Web/1243//#testresult/a3e41f9652b637e4",
      "status" : "passed",
      "time" : {
        "start" : 1647754512860,
        "stop" : 1647754514432,
        "duration" : 1572
      }
    } ]
  },
  "2b4f1cef406e9101284474f8f715b361" : {
    "statistic" : {
      "failed" : 0,
      "broken" : 0,
      "skipped" : 0,
      "passed" : 1,
      "unknown" : 0,
      "total" : 1
    },
    "items" : [ {
      "uid" : "bd535f13854cbc6d",
      "reportUrl" : "https://MohabMohie.github.io/SHAFT_ENGINE/allure/Linux/Web/1243//#testresult/bd535f13854cbc6d",
      "status" : "passed",
      "time" : {
        "start" : 1647754476932,
        "stop" : 1647754477628,
        "duration" : 696
      }
    } ]
  },
  "5aeeb05dac2ac013bdebccaa0aaf698e" : {
    "statistic" : {
      "failed" : 0,
      "broken" : 0,
      "skipped" : 0,
      "passed" : 1,
      "unknown" : 0,
      "total" : 1
    },
    "items" : [ {
      "uid" : "76d2934f1eb67311",
      "reportUrl" : "https://MohabMohie.github.io/SHAFT_ENGINE/allure/Linux/Web/1243//#testresult/76d2934f1eb67311",
      "status" : "passed",
      "time" : {
        "start" : 1647754822364,
        "stop" : 1647754822951,
        "duration" : 587
      }
    } ]
  },
  "50bcdd7464e6ba911e244a1b1a36da44" : {
    "statistic" : {
      "failed" : 0,
      "broken" : 0,
      "skipped" : 0,
      "passed" : 1,
      "unknown" : 0,
      "total" : 1
    },
    "items" : [ {
      "uid" : "9bfc81356ef818fc",
      "reportUrl" : "https://MohabMohie.github.io/SHAFT_ENGINE/allure/Linux/Web/1243//#testresult/9bfc81356ef818fc",
      "status" : "passed",
      "time" : {
        "start" : 1647754650990,
        "stop" : 1647754654153,
        "duration" : 3163
      }
    } ]
  },
  "1d2f699b44814327bb7ff247318e9c4e" : {
    "statistic" : {
      "failed" : 0,
      "broken" : 0,
      "skipped" : 0,
      "passed" : 1,
      "unknown" : 0,
      "total" : 1
    },
    "items" : [ {
      "uid" : "3f9af0ddd89e5016",
      "reportUrl" : "https://MohabMohie.github.io/SHAFT_ENGINE/allure/Linux/Web/1243//#testresult/3f9af0ddd89e5016",
      "status" : "passed",
      "time" : {
        "start" : 1647754760142,
        "stop" : 1647754761575,
        "duration" : 1433
      }
    } ]
  },
  "e6016fd1907b3a0435b9f68cbecabd91" : {
    "statistic" : {
      "failed" : 0,
      "broken" : 0,
      "skipped" : 0,
      "passed" : 1,
      "unknown" : 0,
      "total" : 1
    },
    "items" : [ {
      "uid" : "459804fe3f50f108",
      "reportUrl" : "https://MohabMohie.github.io/SHAFT_ENGINE/allure/Linux/Web/1243//#testresult/459804fe3f50f108",
      "status" : "passed",
      "time" : {
        "start" : 1647754547162,
        "stop" : 1647754547826,
        "duration" : 664
      }
    } ]
  },
  "a3286ba2438900d0ed238b99b97c7891" : {
    "statistic" : {
      "failed" : 0,
      "broken" : 0,
      "skipped" : 0,
      "passed" : 1,
      "unknown" : 0,
      "total" : 1
    },
    "items" : [ {
      "uid" : "caf32d53426095cd",
      "reportUrl" : "https://MohabMohie.github.io/SHAFT_ENGINE/allure/Linux/Web/1243//#testresult/caf32d53426095cd",
      "status" : "passed",
      "time" : {
        "start" : 1647754747467,
        "stop" : 1647754747468,
        "duration" : 1
      }
    } ]
  },
  "eeb601a92e1e55857588ad433767f280" : {
    "statistic" : {
      "failed" : 0,
      "broken" : 0,
      "skipped" : 0,
      "passed" : 1,
      "unknown" : 0,
      "total" : 1
    },
    "items" : [ {
      "uid" : "2f91b5ae83461668",
      "reportUrl" : "https://MohabMohie.github.io/SHAFT_ENGINE/allure/Linux/Web/1243//#testresult/2f91b5ae83461668",
      "status" : "passed",
      "time" : {
        "start" : 1647754615880,
        "stop" : 1647754615881,
        "duration" : 1
      }
    } ]
  },
  "3b2afb193a21ad7584f3b3879b7e7304" : {
    "statistic" : {
      "failed" : 0,
      "broken" : 0,
      "skipped" : 0,
      "passed" : 1,
      "unknown" : 0,
      "total" : 1
    },
    "items" : [ {
      "uid" : "410f30fcffa95e29",
      "reportUrl" : "https://MohabMohie.github.io/SHAFT_ENGINE/allure/Linux/Web/1243//#testresult/410f30fcffa95e29",
      "status" : "passed",
      "time" : {
        "start" : 1647754705562,
        "stop" : 1647754712235,
        "duration" : 6673
      }
    } ]
  },
  "abb72e27d987b2601e9ffbedb4ad837e" : {
    "statistic" : {
      "failed" : 0,
      "broken" : 0,
      "skipped" : 0,
      "passed" : 1,
      "unknown" : 0,
      "total" : 1
    },
    "items" : [ {
      "uid" : "ff40a6ae352f2450",
      "reportUrl" : "https://MohabMohie.github.io/SHAFT_ENGINE/allure/Linux/Web/1243//#testresult/ff40a6ae352f2450",
      "status" : "passed",
      "time" : {
        "start" : 1647754615841,
        "stop" : 1647754615844,
        "duration" : 3
      }
    } ]
  },
  "a7ae2e4757a67e15ea26bc18a732a5d0" : {
    "statistic" : {
      "failed" : 0,
      "broken" : 0,
      "skipped" : 0,
      "passed" : 1,
      "unknown" : 0,
      "total" : 1
    },
    "items" : [ {
      "uid" : "1ae2872e84d9395c",
      "reportUrl" : "https://MohabMohie.github.io/SHAFT_ENGINE/allure/Linux/Web/1243//#testresult/1ae2872e84d9395c",
      "status" : "passed",
      "time" : {
        "start" : 1647754747426,
        "stop" : 1647754747427,
        "duration" : 1
      }
    } ]
  },
  "2fdd1b1e4216687e4f48e717329d30ac" : {
    "statistic" : {
      "failed" : 0,
      "broken" : 0,
      "skipped" : 0,
      "passed" : 1,
      "unknown" : 0,
      "total" : 1
    },
    "items" : [ {
      "uid" : "53d5ab2a75dd3936",
      "reportUrl" : "https://MohabMohie.github.io/SHAFT_ENGINE/allure/Linux/Web/1243//#testresult/53d5ab2a75dd3936",
      "status" : "passed",
      "time" : {
        "start" : 1647754722461,
        "stop" : 1647754722546,
        "duration" : 85
      }
    } ]
  },
  "a861b2f90300876d9b9281725e416280" : {
    "statistic" : {
      "failed" : 0,
      "broken" : 0,
      "skipped" : 0,
      "passed" : 1,
      "unknown" : 0,
      "total" : 1
    },
    "items" : [ {
      "uid" : "2ee1b7341f9053f3",
      "reportUrl" : "https://MohabMohie.github.io/SHAFT_ENGINE/allure/Linux/Web/1243//#testresult/2ee1b7341f9053f3",
      "status" : "passed",
      "time" : {
        "start" : 1647754747442,
        "stop" : 1647754747443,
        "duration" : 1
      }
    } ]
  },
  "8462550d8c94ec5a4ee08184c5723334" : {
    "statistic" : {
      "failed" : 0,
      "broken" : 0,
      "skipped" : 0,
      "passed" : 1,
      "unknown" : 0,
      "total" : 1
    },
    "items" : [ {
      "uid" : "80cc7884e034f75c",
      "reportUrl" : "https://MohabMohie.github.io/SHAFT_ENGINE/allure/Linux/Web/1243//#testresult/80cc7884e034f75c",
      "status" : "passed",
      "time" : {
        "start" : 1647754615886,
        "stop" : 1647754615887,
        "duration" : 1
      }
    } ]
  },
  "8f568206e17e876b394eac7436d24026" : {
    "statistic" : {
      "failed" : 0,
      "broken" : 0,
      "skipped" : 0,
      "passed" : 1,
      "unknown" : 0,
      "total" : 1
    },
    "items" : [ {
      "uid" : "52e84fd8ba4593d3",
      "reportUrl" : "https://MohabMohie.github.io/SHAFT_ENGINE/allure/Linux/Web/1243//#testresult/52e84fd8ba4593d3",
      "status" : "passed",
      "time" : {
        "start" : 1647754585110,
        "stop" : 1647754585889,
        "duration" : 779
      }
    } ]
  },
  "6279582d02bb323ff2fca935852a8c5f" : {
    "statistic" : {
      "failed" : 0,
      "broken" : 0,
      "skipped" : 0,
      "passed" : 1,
      "unknown" : 0,
      "total" : 1
    },
    "items" : [ {
      "uid" : "9dab6ba70b1527fc",
      "reportUrl" : "https://MohabMohie.github.io/SHAFT_ENGINE/allure/Linux/Web/1243//#testresult/9dab6ba70b1527fc",
      "status" : "passed",
      "time" : {
        "start" : 1647754860021,
        "stop" : 1647754860022,
        "duration" : 1
      }
    } ]
  },
  "127389d9950e04e895798bb93e2e53ef" : {
    "statistic" : {
      "failed" : 0,
      "broken" : 0,
      "skipped" : 0,
      "passed" : 1,
      "unknown" : 0,
      "total" : 1
    },
    "items" : [ {
      "uid" : "66236175cef72f91",
      "reportUrl" : "https://MohabMohie.github.io/SHAFT_ENGINE/allure/Linux/Web/1243//#testresult/66236175cef72f91",
      "status" : "passed",
      "time" : {
        "start" : 1647754526349,
        "stop" : 1647754526351,
        "duration" : 2
      }
    } ]
  },
  "a2b4829c99b25b0f138408ac2f2752bd" : {
    "statistic" : {
      "failed" : 0,
      "broken" : 0,
      "skipped" : 0,
      "passed" : 1,
      "unknown" : 0,
      "total" : 1
    },
    "items" : [ {
      "uid" : "c1a5b46ba4b1b44f",
      "reportUrl" : "https://MohabMohie.github.io/SHAFT_ENGINE/allure/Linux/Web/1243//#testresult/c1a5b46ba4b1b44f",
      "status" : "passed",
      "time" : {
        "start" : 1647754658743,
        "stop" : 1647754662066,
        "duration" : 3323
      }
    } ]
  },
  "f7cea628e60912dec54c96e154519b67" : {
    "statistic" : {
      "failed" : 0,
      "broken" : 0,
      "skipped" : 0,
      "passed" : 1,
      "unknown" : 0,
      "total" : 1
    },
    "items" : [ {
      "uid" : "683188f777f7c7aa",
      "reportUrl" : "https://MohabMohie.github.io/SHAFT_ENGINE/allure/Linux/Web/1243//#testresult/683188f777f7c7aa",
      "status" : "passed",
      "time" : {
        "start" : 1647754774634,
        "stop" : 1647754775928,
        "duration" : 1294
      }
    } ]
  },
  "605cff6f7746d803bcbc232d25a70fa0" : {
    "statistic" : {
      "failed" : 0,
      "broken" : 0,
      "skipped" : 0,
      "passed" : 1,
      "unknown" : 0,
      "total" : 1
    },
    "items" : [ {
      "uid" : "82398518d2a06355",
      "reportUrl" : "https://MohabMohie.github.io/SHAFT_ENGINE/allure/Linux/Web/1243//#testresult/82398518d2a06355",
      "status" : "passed",
      "time" : {
        "start" : 1647754615874,
        "stop" : 1647754615875,
        "duration" : 1
      }
    } ]
  },
  "1f0fafbcfcffce619645851c43df5ae4" : {
    "statistic" : {
      "failed" : 0,
      "broken" : 0,
      "skipped" : 0,
      "passed" : 1,
      "unknown" : 0,
      "total" : 1
    },
    "items" : [ {
      "uid" : "e59281c52cb73fbf",
      "reportUrl" : "https://MohabMohie.github.io/SHAFT_ENGINE/allure/Linux/Web/1243//#testresult/e59281c52cb73fbf",
      "status" : "passed",
      "time" : {
        "start" : 1647754712627,
        "stop" : 1647754714169,
        "duration" : 1542
      }
    } ]
  },
  "7c21062b2157c9c5386d90359de23d53" : {
    "statistic" : {
      "failed" : 0,
      "broken" : 0,
      "skipped" : 0,
      "passed" : 1,
      "unknown" : 0,
      "total" : 1
    },
    "items" : [ {
      "uid" : "984e58913ac2cec1",
      "reportUrl" : "https://MohabMohie.github.io/SHAFT_ENGINE/allure/Linux/Web/1243//#testresult/984e58913ac2cec1",
      "status" : "passed",
      "time" : {
        "start" : 1647754477632,
        "stop" : 1647754478087,
        "duration" : 455
      }
    } ]
  },
  "f76e83298b125d9f8051305662bd868b" : {
    "statistic" : {
      "failed" : 0,
      "broken" : 0,
      "skipped" : 0,
      "passed" : 1,
      "unknown" : 0,
      "total" : 1
    },
    "items" : [ {
      "uid" : "4b0330036cab4287",
      "reportUrl" : "https://MohabMohie.github.io/SHAFT_ENGINE/allure/Linux/Web/1243//#testresult/4b0330036cab4287",
      "status" : "passed",
      "time" : {
        "start" : 1647754550146,
        "stop" : 1647754550819,
        "duration" : 673
      }
    } ]
  },
  "8a583f3461f88d7c293779bde04a0e1d" : {
    "statistic" : {
      "failed" : 0,
      "broken" : 0,
      "skipped" : 0,
      "passed" : 1,
      "unknown" : 0,
      "total" : 1
    },
    "items" : [ {
      "uid" : "f86e6f74a303f019",
      "reportUrl" : "https://MohabMohie.github.io/SHAFT_ENGINE/allure/Linux/Web/1243//#testresult/f86e6f74a303f019",
      "status" : "passed",
      "time" : {
        "start" : 1647754542607,
        "stop" : 1647754543204,
        "duration" : 597
      }
    } ]
  },
  "36df61c5fa16064939f2168a752af02b" : {
    "statistic" : {
      "failed" : 0,
      "broken" : 0,
      "skipped" : 0,
      "passed" : 1,
      "unknown" : 0,
      "total" : 1
    },
    "items" : [ {
      "uid" : "f3a406d285f50b33",
      "reportUrl" : "https://MohabMohie.github.io/SHAFT_ENGINE/allure/Linux/Web/1243//#testresult/f3a406d285f50b33",
      "status" : "passed",
      "time" : {
        "start" : 1647754518373,
        "stop" : 1647754520666,
        "duration" : 2293
      }
    } ]
  },
  "d20688892e8370917ded3954bd58a936" : {
    "statistic" : {
      "failed" : 0,
      "broken" : 0,
      "skipped" : 0,
      "passed" : 1,
      "unknown" : 0,
      "total" : 1
    },
    "items" : [ {
      "uid" : "294b33140ce47f95",
      "reportUrl" : "https://MohabMohie.github.io/SHAFT_ENGINE/allure/Linux/Web/1243//#testresult/294b33140ce47f95",
      "status" : "passed",
      "time" : {
        "start" : 1647754860024,
        "stop" : 1647754860025,
        "duration" : 1
      }
    } ]
  },
  "d305933be8c1545e88e65f9f5733babf" : {
    "statistic" : {
      "failed" : 0,
      "broken" : 0,
      "skipped" : 0,
      "passed" : 1,
      "unknown" : 0,
      "total" : 1
    },
    "items" : [ {
      "uid" : "c15d0c276dad38bf",
      "reportUrl" : "https://MohabMohie.github.io/SHAFT_ENGINE/allure/Linux/Web/1243//#testresult/c15d0c276dad38bf",
      "status" : "passed",
      "time" : {
        "start" : 1647754390326,
        "stop" : 1647754393605,
        "duration" : 3279
      }
    } ]
  },
  "8a87a21477193c438040ea0bf35f7853" : {
    "statistic" : {
      "failed" : 0,
      "broken" : 0,
      "skipped" : 0,
      "passed" : 1,
      "unknown" : 0,
      "total" : 1
    },
    "items" : [ {
      "uid" : "96ce1873bd4575af",
      "reportUrl" : "https://MohabMohie.github.io/SHAFT_ENGINE/allure/Linux/Web/1243//#testresult/96ce1873bd4575af",
      "status" : "passed",
      "time" : {
        "start" : 1647754615877,
        "stop" : 1647754615879,
        "duration" : 2
      }
    } ]
  },
  "3e73c6377dbba1c4391d565476180108" : {
    "statistic" : {
      "failed" : 0,
      "broken" : 0,
      "skipped" : 0,
      "passed" : 1,
      "unknown" : 0,
      "total" : 1
    },
    "items" : [ {
      "uid" : "93787414fa94e3a4",
      "reportUrl" : "https://MohabMohie.github.io/SHAFT_ENGINE/allure/Linux/Web/1243//#testresult/93787414fa94e3a4",
      "status" : "passed",
      "time" : {
        "start" : 1647754715581,
        "stop" : 1647754715881,
        "duration" : 300
      }
    } ]
  },
  "b916e3a3cf9aae34687e6cba489385fd" : {
    "statistic" : {
      "failed" : 0,
      "broken" : 0,
      "skipped" : 0,
      "passed" : 1,
      "unknown" : 0,
      "total" : 1
    },
    "items" : [ {
      "uid" : "934c804720e4c6ce",
      "reportUrl" : "https://MohabMohie.github.io/SHAFT_ENGINE/allure/Linux/Web/1243//#testresult/934c804720e4c6ce",
      "status" : "passed",
      "time" : {
        "start" : 1647754718964,
        "stop" : 1647754719043,
        "duration" : 79
      }
    } ]
  },
  "fa265a8627bd99827e3fc01138cc6263" : {
    "statistic" : {
      "failed" : 0,
      "broken" : 0,
      "skipped" : 0,
      "passed" : 1,
      "unknown" : 0,
      "total" : 1
    },
    "items" : [ {
      "uid" : "3e6655808954b3bc",
      "reportUrl" : "https://MohabMohie.github.io/SHAFT_ENGINE/allure/Linux/Web/1243//#testresult/3e6655808954b3bc",
      "status" : "passed",
      "time" : {
        "start" : 1647754386489,
        "stop" : 1647754387576,
        "duration" : 1087
      }
    } ]
  },
  "afc8cfa07b82f889f102dc4910710386" : {
    "statistic" : {
      "failed" : 0,
      "broken" : 0,
      "skipped" : 0,
      "passed" : 1,
      "unknown" : 0,
      "total" : 1
    },
    "items" : [ {
      "uid" : "6cfcb2b24f1fa0fc",
      "reportUrl" : "https://MohabMohie.github.io/SHAFT_ENGINE/allure/Linux/Web/1243//#testresult/6cfcb2b24f1fa0fc",
      "status" : "passed",
      "time" : {
        "start" : 1647754655629,
        "stop" : 1647754658361,
        "duration" : 2732
      }
    } ]
  },
  "33865050f01a74fce461b1ec0dbab96f" : {
    "statistic" : {
      "failed" : 1,
      "broken" : 0,
      "skipped" : 0,
      "passed" : 0,
      "unknown" : 0,
      "total" : 1
    },
    "items" : [ {
      "uid" : "19a19474d47d07f3",
      "reportUrl" : "https://MohabMohie.github.io/SHAFT_ENGINE/allure/Linux/Web/1243//#testresult/19a19474d47d07f3",
      "status" : "failed",
      "statusDetails" : "Element Action [WaitForAlertToBePresent] failed.",
      "time" : {
        "start" : 1647754444395,
        "stop" : 1647754474997,
        "duration" : 30602
      }
    } ]
  },
  "4059f51a9d634b52b216f44f3bf27ccc" : {
    "statistic" : {
      "failed" : 0,
      "broken" : 0,
      "skipped" : 0,
      "passed" : 1,
      "unknown" : 0,
      "total" : 1
    },
    "items" : [ {
      "uid" : "d678495c274466ca",
      "reportUrl" : "https://MohabMohie.github.io/SHAFT_ENGINE/allure/Linux/Web/1243//#testresult/d678495c274466ca",
      "status" : "passed",
      "time" : {
        "start" : 1647754860015,
        "stop" : 1647754860017,
        "duration" : 2
      }
    } ]
  },
  "45512e220734b6213e89df6e5f078970" : {
    "statistic" : {
      "failed" : 0,
      "broken" : 0,
      "skipped" : 0,
      "passed" : 1,
      "unknown" : 0,
      "total" : 1
    },
    "items" : [ {
      "uid" : "990f669df7a31d5c",
      "reportUrl" : "https://MohabMohie.github.io/SHAFT_ENGINE/allure/Linux/Web/1243//#testresult/990f669df7a31d5c",
      "status" : "passed",
      "time" : {
        "start" : 1647754747459,
        "stop" : 1647754747462,
        "duration" : 3
      }
    } ]
  }
}